Workbook

Sheet BBDD
A1: DIA SEG | B1: MES SEG | C1: SEMANA | D1: QUIEBRE | E1: ATRIBUIBLE | F1: REINGRESO | G1: SUPERVISOR | H1: LINEA | I1: ESTADO | J1: TERMINADA | K1: ANULADA | L1: PENDIENTE | M1: AGENDADAS | N1: PENDIENTES | O1: SUSPENDIDAS | P1: ESTADO AGENDA | Q1: FECHA AGENDA | R1: FRANJA AGENDA | S1: DIA AGENDA | T1: MES AGENDA | U1: MOTIVO DE SUSPENSION | V1: CEDULA CLIENTE | W1: TELEFONO CLIENTE | X1: LEGALIZADA | Y1: PEND LEGALIZAR | Z1: ESTADO LEG | AA1: DIF DIAS | AB1: FECHA LEG | AC1: FINAL Vs LG | AD1: % PAGO | AE1: DIA PDC | AF1: DIAS MES PDC | AG1: EMPAQUETADAS | AH1: META | AI1: BA | AJ1: DUO | AK1: TRIO | AL1: SubPeticionTramitadorCD | AM1: CanalRegistroPeticionID | AN1: SubPeticionID | AO1: Num_Subpeticion_Atis | AP1: FechaRegistroPeticion | AQ1: FuerzaVentaID | AR1: Telefono | AS1: ProductoID | AT1: PlanContratadoID | AU1: PlanID | AV1: DireccionID | AW1: OperacionComercialProductoID | AX1: Nom_OC | AY1: ClienteID | AZ1: Anio_Seg | BA1: Mes_Seg | BB1: Dia_Seg | BC1: TipoOperacionPeticionID | BD1: Tipo_Operacion_Peticion | BE1: PeticionID | BF1: ID_Peticion | BG1: Nom_PS | BH1: ProductoPlanCD | BI1: Num_Agrupacion_Pet_Atis | BJ1: AgrupacionPeticionID | BK1: CuentaFacturacionID | BL1: SuscripcionID | BM1: Variable | BN1: Nom_Segmento_Cuenta | BO1: ID_Cuenta | BP1: SubSegmentoCuentaDesc | BQ1: Anio_Reg | BR1: Mes_Reg | BS1: Dia_Reg | BT1: FechaIniEstPetAtis | BU1: EstadoPetAtis | BV1: FechaIniEstadoSubPetAtis | BW1: EstadoSubPetAtis | BX1: FechaIngresoAtiempo | BY1: FechaIniEstadoAtiempo | BZ1: EstadoAtiempo | CA1: Localidad | CB1: Depto | CC1: Direccion | CD1: Nom_Barrio_PC | CE1: BarrioID | CF1: Cod_Dane | CG1: Distrito | CH1: Cluster1 | CI1: Cedula_Vendedor_Atis | CJ1: Nom_Fuerza_Venta | CK1: Canal | CL1: SubCanal | CM1: Unidad_Fuerza_de_Ventas | CN1: Nom_Punto_Venta | CO1: Nom_Canal_Venta | CP1: ID_Canal_Venta | CQ1: TipoFuerzaVentaCD | CR1: TipoFuerzaVentaDesc | CS1: Nom_Tipo_Uso | CT1: Estrato | CU1: MX_Hom | CV1: ProductoDesc | CW1: Nom_Plan_Tarifario | CX1: Nom_PS_Equipo | CY1: Nom_Ult_Quiebre_Atmp | CZ1: TipoQuiebreDesc | DA1: Nom_Usuario_Ult_Actividad | DB1: ActividadPeticionID | DC1: Fec_Ini_Ult_Actividad | DD1: Fec_Est_Ult_Actividad | DE1: Desc_Est_Ult_Actividad | DF1: Variable_Hom | DG1: DireccionElectronica | DH1: Correo_Valido | DI1: DSLAM | DJ1: Velocidad | DK1: TenenciaCliente | DL1: Tipo_Cliente | DM1: Paquete | DN1: Producto | DO1: MX_Configurado | DP1: distribuidor | DQ1: proy_soc | DR1: Tramitador_UsuAtis | DS1: Tramitador_Nom | DT1: Cedula_Tramitador | DU1: Flag_Recibido_ATiempo | DV1: Total_Homol | DW1: Regional | DX1: CuentaPadre | DY1: TipoEnvio | DZ1: CaracteristicaEquipo | EA1: TVHD | EB1: Reingreso2 | EC1: Bianual3 | ED1: FechaSeguimiento | EE1: Zona | EF1: CicloFacturacion | EG1: DocInterlocutor | EH1: NombreInterlocutor | EI1: FechaAltaFactElect | EJ1: CorreoFactElect | EK1: DocumentoFventaFactElect | EL1: UsuarioCdFactElect | EM1: NombreVendFactElect | EN1: UnidadFactElect | EO1: ActivacionFactElect | EP1: NitUnidadFuerzaventa | EQ1: NombreProfesional | ER1: CedulaProfesional | ES1: PlanExpansion | ET1: BAEstratoSup | EU1: CodPlanDcto | EV1: NomPlanDcto | EW1: SegmentoCliente | EX1: SubsegmentoCliente | EY1: FlagTvAzteca | EZ1: ZonaBA | FA1: Canal_Hom | FB1: Dpto_Hom | FC1: Estado_Hom | FD1: Dpto_Nom | FE1: Mun_Nom | FF1: Loc_Nom | FG1: Producto_Hom | FH1: Plan_Hom | FI1: Portafolio | FJ1: SubCanal_Hom | FK1: Unidad_Fuerza_de_Ventas_Hom | FL1: DistArmCaja | FM1: FlagCyC | FN1: NombrePunto | FO1: CodigoPunto | FP1: Tarifa_full | FQ1: Tarifa_sin_SubsContr | FR1: TarifaMXFinal | FS1: CodDaneEmpresas | FT1: LocalidadEmpresas | FU1: DepartamentoEmpresas | FV1: RegionalEmpresas | FW1: MarcaTrioMV | FX1: CodigoCliente | FY1: AplicacionRespetoiVentas | FZ1: FlagOfertaPRO | GA1: MarcaTrioHD | GB1: FTTH | GC1: TenenciaPlanta | GD1: PlanLB | GE1: TarifaFullLB | GF1: TarifaMXLB | GG1: PlanBA | GH1: TarifaFullBA | GI1: TarifaMXBA | GJ1: PlanTV | GK1: TarifaFullTV | GL1: TarifaMXTV | GM1: Tarifa_MXFinal | GN1: Tarifa_MXInicial | GO1: DeltaMX | GP1: FlagEnvioCampana | GQ1: SVATV2833 | GR1: SVABA2864 | GS1: Empresa | GT1: fec_comercializacion_cto | GU1: Canal_Acceso | GV1: Autenticacion_Correo | GW1: Convergente | GX1: MacroTenenciaIni | GY1: MacroTenenciaFin | GZ1: Tipo_Convergente | HA1: Coinversion | HB1: poligono_kkr | HC1: comuna_kkr | HD1: region_kkr | HE1: Segmento_Homologado | HF1: Id_Tiles | HG1: Alta_mismo_mes_MTotal | HH1: CC_Pospago_MTotal | HI1: Fuente_Pospago_MTotal | HJ1: fecha_registro_movil_MTotal | HK1: Nom_Agente_Movil_MTotal | HL1: Canal_Movil_MTotal | HM1: id_punto_Mov_MTotal | HN1: nom_punto_Mov_MTotal | HO1: nom_vendedor_Mov_MTotal | HP1: NumIdentVendedor_Mov_MTotal | HQ1: NBA | HR1: Tipo_Venta | HS1: Flag_TAT | HT1: cod_tienda | HU1: canal_fibra | HV1: Valor_Vision_Cliente | HW1: Oferta_Empaquetada | HX1: OF_Empaquetada_Movil | HY1: TarifaMXFinalEMPAQ | HZ1: TarifaMXFinalMovilEMP | IA1: Pot_Conv | IB1: Oferta_Descuento | IC1: REMARK | ID1: Ant_Pos_Empaq | IE1: Region_Venta | IF1: Departamento_Venta | IG1: Municipio_Venta | IH1: CANAL_HOMO_DIG | II1: PRODUCTO_HOMO_DIG | IJ1: MACROSEG_DIG | IK1: TIPO_VENTA_DIG | IL1: UNIDAD_VENTA_DIG | IM1: ALIADO_VENTA_DIG | IN1: ESTADO_VARIABLE_DIG | IO1: TIPO_MEDIO_DIG | IP1: MOTIVO_QUIEBRE_DIG | IQ1: CANAL_DIR_DIG | IR1: Altas_Con_Reingreso | IS1: TipoFactura | IT1: ATR_VENTA_SOURCE | IU1: ATR_VENTA_CAMPANA | IV1: ATR_VENTA_MEDIUM | IW1: ATR_VENTA_LANDING | IX1: PLACE_ID | IY1: Oferta_empaquetada_comisiones
A2: =DAY(AVANZA[[#This Row],[FechaSeguimiento]]) -> 1 | B2: =MONTH(AVANZA[[#This Row],[FechaSeguimiento]]) -> 5 | C2: =LOWER(IF(AND(AVANZA[[#This Row],[Mes_Reg]]=MONTH(TODAY()),AND(AVANZA[[#This Row],[Dia_Reg]]>0,AVANZA[[#This Row],[Dia_Reg]]<9)),"SEMANA 1","")&IF(AND(AVANZA[[#This Row],[Mes_Reg]]=MONTH(TODAY()),AND(AVANZA[[#This Row],[Dia_Reg]]>8,AVANZA[[#This Row],[Dia_Reg]]<16)),"SEMANA 2","")&IF(AND(AVANZA[[#This Row],[Mes_Reg]]=MONTH(TODAY()),AND(AVANZA[[#This Row],[Dia_Reg]]>15,AVANZA[[#This Row],[Dia_Reg]]<23)),"SEMANA 3","")&IF(AND(AVANZA[[#This Row],[Mes_Reg]]=MONTH(TODAY()),AND(AVANZA[[#This Row],[Dia_Reg]]>22,AVANZA[[#This Row],[Dia_Reg]]<31)),"SEMANA 4","")&IF(AVANZA[[#This Row],[Mes_Reg]]<>MONTH(TODAY()),"BOLSA MES ANTERIOR","")) -> semana 1 | D2: =LOWER(IFERROR(VLOOKUP(AVANZA[[#This Row],[ID_Peticion]],CANCELADAS[#All],2,0),"")) | E2: =LOWER(IFERROR(VLOOKUP(AVANZA[[#This Row],[ID_Peticion]],CANCELADAS[#All],3,0),"")) | F2: =LOWER(IF(AVANZA[[#This Row],[CEDULA CLIENTE]]<>""," CC: " & COUNTIFS(AVANZA[CEDULA CLIENTE],AVANZA[[#This Row],[CEDULA CLIENTE]]),"")& IF(AVANZA[[#This Row],[Direccion]]<>""," DIR: " & COUNTIFS(AVANZA[Direccion],AVANZA[[#This Row],[Direccion]]),"")) -> dir: 1 | G2: =IFERROR(VLOOKUP(AVANZA[[#This Row],[Cedula_Vendedor_Atis]],PLANTA[[#All],[CEDULA]:[LINEA]],3,0),"No Cruza") -> Marisol Avella | H2: =IFERROR(VLOOKUP(AVANZA[[#This Row],[Cedula_Vendedor_Atis]],PLANTA[[#All],[CEDULA]:[LINEA]],4,0),"No Cruza") -> Fija | I2: =LOWER(IF(AVANZA[[#This Row],[ATRIBUIBLE]]="",AVANZA[[#This Row],[Variable]],AVANZA[[#This Row],[ATRIBUIBLE]])) -> terminada | J2: =IF(AVANZA[[#This Row],[Variable]]=AVANZA[[#Headers],[TERMINADA]],1,0) -> 1 | K2: =IF(AVANZA[[#This Row],[Variable]]=AVANZA[[#Headers],[ANULADA]],1,0) -> 0 | L2: =IF(AVANZA[[#This Row],[Variable]]=AVANZA[[#Headers],[PENDIENTE]],1,0) -> 0 | M2: =IF(AVANZA[[#This Row],[ESTADO AGENDA]]="AGENDADA",1,0) -> 0 | N2: =IF(AVANZA[[#This Row],[ESTADO AGENDA]]="PENDIENTE DE AGENDAR",1,0) -> 0 | O2: =IF(AVANZA[[#This Row],[ESTADO AGENDA]]="SUSPENDIDA",1,0) -> 0 | P2: {=_xlfn.XLOOKUP(AVANZA[[#This Row],[Num_Agrupacion_Pet_Atis]],Tabla1[[#All],[Numero_de_actuacion]],Tabla1[[#All],[Estado_de_la_orden]],"",0)} | Q2: {=_xlfn.XLOOKUP(AVANZA[[#This Row],[Num_Agrupacion_Pet_Atis]],Tabla1[[#All],[Numero_de_actuacion]],Tabla1[[#All],[Fecha_de_la_cita]],"",0)} | R2: {=_xlfn.XLOOKUP(AVANZA[[#This Row],[Num_Agrupacion_Pet_Atis]],Tabla1[[#All],[Numero_de_actuacion]],Tabla1[[#All],[Franja_horaria_de_la_cita]],"",0)} | S2: =IFERROR(DAY(AVANZA[[#This Row],[FECHA AGENDA]]),"") | T2: =IFERROR(MONTH(AVANZA[[#This Row],[FECHA AGENDA]]),"") | U2: {=_xlfn.XLOOKUP(AVANZA[[#This Row],[Num_Agrupacion_Pet_Atis]],Tabla1[[#All],[Numero_de_actuacion]],Tabla1[[#All],[Motivo_de_suspension]],"",0)} | V2: {=_xlfn.XLOOKUP(AVANZA[[#This Row],[Num_Agrupacion_Pet_Atis]],Tabla1[[#All],[Numero_de_actuacion]],Tabla1[[#All],[No_identificacion_cliente]],"",0)} | W2: {=_xlfn.XLOOKUP(AVANZA[[#This Row],[Num_Agrupacion_Pet_Atis]],Tabla1[[#All],[Numero_de_actuacion]],Tabla1[[#All],[Movil_de_contacto]],"",0)} | X2: =IF(OR(AVANZA[[#This Row],[ESTADO LEG]]="Legalizada grabacion",AVANZA[[#This Row],[ESTADO LEG]]="Legalizada aut"),1,0) -> 1 | Y2: =IF(OR(AVANZA[[#This Row],[ESTADO LEG]]="pdte legalizar",AVANZA[[#This Row],[ESTADO LEG]]="No cruza"),1,0) -> 0 | Z2: {=IF(AVANZA[[#This Row],[Variable]]="Terminada",LOWER(_xlfn.XLOOKUP(AVANZA[[#This Row],[ID_Peticion]],Tabla6[[#All],[NUM_PETICION]],Tabla6[[#All],[ESTADO_LEG]],"NO CRUZA",0)),AVANZA[[#This Row],[Variable]])} -> legalizada grabacion | AA2: {=_xlfn.XLOOKUP(AVANZA[[#This Row],[ID_Peticion]],Tabla6[[#All],[NUM_PETICION]],Tabla6[[#All],[DIF_DIAS]],"",0)} -> 4 | AB2: {=IFERROR(_xlfn.XLOOKUP(AVANZA[[#This Row],[ID_Peticion]],Tabla6[[#All],[NUM_PETICION]],Tabla6[[#All],[FEC_LEGAL]],"",0),"")} -> 46147 | AC2: =IF(AVANZA[[#This Row],[FECHA LEG]]<>0,IFERROR(AVANZA[[#This Row],[FECHA LEG]]-AVANZA[[#This Row],[FechaIniEstadoSubPetAtis]],0),TODAY()-AVANZA[[#This Row],[FechaIniEstadoSubPetAtis]]) -> 4 | AD2: =IF(AVANZA[[#This Row],[FINAL Vs LG]]<>0,IF(AVANZA[[#This Row],[FINAL Vs LG]]<7.1,"100%",IF(AND(AVANZA[[#This Row],[FINAL Vs LG]]>7.1,AVANZA[[#This Row],[FINAL Vs LG]]<11.1),"50%","0%")),0) -> 100% | AE2: =VLOOKUP(DAY(TODAY()),BACK!F:G,2,0) -> 14 | AF2: =BACK!$I$2 -> 24 | AG2: =IF(AVANZA[[#This Row],[Oferta_empaquetada_comisiones]]="SI",1,0) -> 1 | AH2: =IF(AVANZA[[#This Row],[Variable]]="TERMINADA",IFERROR(VLOOKUP(AVANZA[[#This Row],[SUPERVISOR]],Tabla2[#All],4,0),0),) -> 3.5 | AI2: =IF(AVANZA[[#This Row],[Producto]]="BA",1,0) -> 1 | AJ2: =IF(AVANZA[[#This Row],[Producto]]="DUO",1,0) -> 0 | AK2: =IF(AVANZA[[#This Row],[Producto]]="TRIO",1,0) -> 0 | AL2: 1624058238002044670 | AM2: -1 | AN2: -1 | AO2: 1785901244 | AP2: 46143.484 | AQ2: -1 | AR2: 2512691090 | AS2: -1 | AT2: -1 | AU2: -1 | AV2: -1 | AW2: -1 | AX2: FixedCreateSubscriber | AY2: -1 | AZ2: 2026 | BA2: 5 | BB2: 1 | BC2: -1 | BD2: Broadband Service | BE2: -1 | BF2: 20001621103978 | BG2: Convergente_MTotal_Single_Voz Ilim Nal _Ba Ancha 900Mbps_Mov Ilim_Nac_25421 | BH2: 25421 | BI2: FS202605011137041941 | BJ2: -1 | BK2: -1 | BL2: -1 | BM2: TERMINADA | BN2: Individual | BO2: 6108776323 | BP2: Movistar Total | BQ2: 2026 | BR2: 5 | BS2: 1 | BT2: 46143.618 | BU2: OS90 | BV2: 46143 | BW2: Completed | BX2: 46143 | BY2: 46143 | BZ2: Call Back To CRM | CA2: BOGOTA, D.C. | CB2: BOGOTA, D.C. | CC2: KR 121 CL 70 A-16 LA FAENA 16 APT 2 LAT:4.71684612 LON:-74.13659734 | CD2: LA FAENA | CE2: -1 | CF2: 11001000 | CG2: Bogota | CH2: ATACANTE | CI2: 1018514067 | CJ2: JHOJAN ALEXANDER JIMENEZ MELO | CK2: CANAL ONLINE | CL2: TELEVENTAS | CM2: ATENTO COLOMBIA S.A. | CN2: CANAL ON LINE - ATENTO OUT BOUND | CT2: 2 | CU2: Broadband Service | CW2: Convergente_MTotal_Single_Voz Ilim Nal _Ba Ancha 900Mbps_Mov Ilim_Nac_25421 | CX2: 25421 | DA2: SV | DB2: -1 | DF2: ALTA | DJ2: 900000 | DK2: Cliente Nuevo | DL2: Cliente Existente | DN2: BA | DR2: jajimenezme1 | DS2: JHOJAN ALEXANDER JIMENEZ MELO | DT2: 1018514067 | DV2: 1 | DW2: BOGOTA | ED2: 46143 | EE2: Occidente | EF2: 9 | EP2: 830065842-5 | ES2: 158 | FA2: CANAL ONLINE | FB2: Bogotá D.C | FD2: Bogotá D.C | FE2: Bogotá | FF2: Bogotá | FK2: ATENTO | FL2: 11001000OH_BOGALEIVA_I_7360_32050_Engativa_1ENGAT-CT3/4-43-04SS3-43-04@11001000_OH_BOGALEIVA_I_7360_32050_Engativa_1_ENGAT-CT3/4-43-04_SS3-43-04 | FN2: CANAL ON LINE - ATENTO OUT BOUND | FO2: 9900202020034 | FR2: 85900 | GB2: PON | GC2: Broadband Service | GD2: 0 | GF2: 0 | GG2: 25421 | GI2: 85900 | GJ2: 0 | GL2: 0 | GM2: 102221 | GS2: FS | GT2: 45107 | GU2: CENTRO EXP | GV2: SIN EMAIL | GW2: Si | GX2: SV | GY2: Convergente Solo Contrato | GZ2: Convergente Nuevo | HA2: ONNET | HB2: BOGOTA 1 | HC2: BOGOTA 1 | HD2: BOGOTA NORTE | HE2: Individual | HF2: 471574135 | HG2: Venta mismo mes (F+M) mismo Canal_mismo Aliado | HH2: 52077088 | HI2: 1. Radicadas | HJ2: 46150 | HK2: ATENTO COLOMBIA S.A. | HL2: CANAL ONLINE | HM2: 9900202020034 | HN2: CANAL ON LINE - ATENTO OUT BOUND | HO2: JHOJAN ALEXANDER JIMENEZ MELO | HP2: 1018514067 | HR2: Asistido | HV2: 85900 | HW2: SI | HX2: Radicada - No nato igual a NO | HY2: 103568 | HZ2: 17668 | IA2: SI | IB2: NO | IE2: BOGOTA | IF2: BOGOTA | IG2: BOGOTA | IH2: Digital | II2: Fibra | IJ2: B2C | IK2: Asistido | IL2: Outbound | IM2: Atento | IN2: Alta | IP2: - | IQ2: Digital | IS2: ELECTRONICA | IT2: WhatsApp Bot | IY2: SI
A3: =DAY(AVANZA[[#This Row],[FechaSeguimiento]]) -> 1 | B3: =MONTH(AVANZA[[#This Row],[FechaSeguimiento]]) -> 5 | C3: =LOWER(IF(AND(AVANZA[[#This Row],[Mes_Reg]]=MONTH(TODAY()),AND(AVANZA[[#This Row],[Dia_Reg]]>0,AVANZA[[#This Row],[Dia_Reg]]<9)),"SEMANA 1","")&IF(AND(AVANZA[[#This Row],[Mes_Reg]]=MONTH(TODAY()),AND(AVANZA[[#This Row],[Dia_Reg]]>8,AVANZA[[#This Row],[Dia_Reg]]<16)),"SEMANA 2","")&IF(AND(AVANZA[[#This Row],[Mes_Reg]]=MONTH(TODAY()),AND(AVANZA[[#This Row],[Dia_Reg]]>15,AVANZA[[#This Row],[Dia_Reg]]<23)),"SEMANA 3","")&IF(AND(AVANZA[[#This Row],[Mes_Reg]]=MONTH(TODAY()),AND(AVANZA[[#This Row],[Dia_Reg]]>22,AVANZA[[#This Row],[Dia_Reg]]<31)),"SEMANA 4","")&IF(AVANZA[[#This Row],[Mes_Reg]]<>MONTH(TODAY()),"BOLSA MES ANTERIOR","")) -> bolsa mes anterior | D3: =LOWER(IFERROR(VLOOKUP(AVANZA[[#This Row],[ID_Peticion]],CANCELADAS[#All],2,0),"")) | E3: =LOWER(IFERROR(VLOOKUP(AVANZA[[#This Row],[ID_Peticion]],CANCELADAS[#All],3,0),"")) | F3: =LOWER(IF(AVANZA[[#This Row],[CEDULA CLIENTE]]<>""," CC: " & COUNTIFS(AVANZA[CEDULA CLIENTE],AVANZA[[#This Row],[CEDULA CLIENTE]]),"")& IF(AVANZA[[#This Row],[Direccion]]<>""," DIR: " & COUNTIFS(AVANZA[Direccion],AVANZA[[#This Row],[Direccion]]),"")) -> dir: 1 | G3: =IFERROR(VLOOKUP(AVANZA[[#This Row],[Cedula_Vendedor_Atis]],PLANTA[[#All],[CEDULA]:[LINEA]],3,0),"No Cruza") -> Marisol Avella | H3: =IFERROR(VLOOKUP(AVANZA[[#This Row],[Cedula_Vendedor_Atis]],PLANTA[[#All],[CEDULA]:[LINEA]],4,0),"No Cruza") -> Fija | I3: =LOWER(IF(AVANZA[[#This Row],[ATRIBUIBLE]]="",AVANZA[[#This Row],[Variable]],AVANZA[[#This Row],[ATRIBUIBLE]])) -> terminada | J3: =IF(AVANZA[[#This Row],[Variable]]=AVANZA[[#Headers],[TERMINADA]],1,0) -> 1 | K3: =IF(AVANZA[[#This Row],[Variable]]=AVANZA[[#Headers],[ANULADA]],1,0) -> 0 | L3: =IF(AVANZA[[#This Row],[Variable]]=AVANZA[[#Headers],[PENDIENTE]],1,0) -> 0 | M3: =IF(AVANZA[[#This Row],[ESTADO AGENDA]]="AGENDADA",1,0) -> 0 | N3: =IF(AVANZA[[#This Row],[ESTADO AGENDA]]="PENDIENTE DE AGENDAR",1,0) -> 0 | O3: =IF(AVANZA[[#This Row],[ESTADO AGENDA]]="SUSPENDIDA",1,0) -> 0 | P3: {=_xlfn.XLOOKUP(AVANZA[[#This Row],[Num_Agrupacion_Pet_Atis]],Tabla1[[#All],[Numero_de_actuacion]],Tabla1[[#All],[Estado_de_la_orden]],"",0)} | Q3: {=_xlfn.XLOOKUP(AVANZA[[#This Row],[Num_Agrupacion_Pet_Atis]],Tabla1[[#All],[Numero_de_actuacion]],Tabla1[[#All],[Fecha_de_la_cita]],"",0)} | R3: {=_xlfn.XLOOKUP(AVANZA[[#This Row],[Num_Agrupacion_Pet_Atis]],Tabla1[[#All],[Numero_de_actuacion]],Tabla1[[#All],[Franja_horaria_de_la_cita]],"",0)} | S3: =IFERROR(DAY(AVANZA[[#This Row],[FECHA AGENDA]]),"") | T3: =IFERROR(MONTH(AVANZA[[#This Row],[FECHA AGENDA]]),"") | U3: {=_xlfn.XLOOKUP(AVANZA[[#This Row],[Num_Agrupacion_Pet_Atis]],Tabla1[[#All],[Numero_de_actuacion]],Tabla1[[#All],[Motivo_de_suspension]],"",0)} | V3: {=_xlfn.XLOOKUP(AVANZA[[#This Row],[Num_Agrupacion_Pet_Atis]],Tabla1[[#All],[Numero_de_actuacion]],Tabla1[[#All],[No_identificacion_cliente]],"",0)} | W3: {=_xlfn.XLOOKUP(AVANZA[[#This Row],[Num_Agrupacion_Pet_Atis]],Tabla1[[#All],[Numero_de_actuacion]],Tabla1[[#All],[Movil_de_contacto]],"",0)} | X3: =IF(OR(AVANZA[[#This Row],[ESTADO LEG]]="Legalizada grabacion",AVANZA[[#This Row],[ESTADO LEG]]="Legalizada aut"),1,0) -> 1 | Y3: =IF(OR(AVANZA[[#This Row],[ESTADO LEG]]="pdte legalizar",AVANZA[[#This Row],[ESTADO LEG]]="No cruza"),1,0) -> 0 | Z3: {=IF(AVANZA[[#This Row],[Variable]]="Terminada",LOWER(_xlfn.XLOOKUP(AVANZA[[#This Row],[ID_Peticion]],Tabla6[[#All],[NUM_PETICION]],Tabla6[[#All],[ESTADO_LEG]],"NO CRUZA",0)),AVANZA[[#This Row],[Variable]])} -> legalizada grabacion | AA3: {=_xlfn.XLOOKUP(AVANZA[[#This Row],[ID_Peticion]],Tabla6[[#All],[NUM_PETICION]],Tabla6[[#All],[DIF_DIAS]],"",0)} -> 4 | AB3: {=IFERROR(_xlfn.XLOOKUP(AVANZA[[#This Row],[ID_Peticion]],Tabla6[[#All],[NUM_PETICION]],Tabla6[[#All],[FEC_LEGAL]],"",0),"")} -> 46147 | AC3: =IF(AVANZA[[#This Row],[FECHA LEG]]<>0,IFERROR(AVANZA[[#This Row],[FECHA LEG]]-AVANZA[[#This Row],[FechaIniEstadoSubPetAtis]],0),TODAY()-AVANZA[[#This Row],[FechaIniEstadoSubPetAtis]]) -> 4 | AD3: =IF(AVANZA[[#This Row],[FINAL Vs LG]]<>0,IF(AVANZA[[#This Row],[FINAL Vs LG]]<7.1,"100%",IF(AND(AVANZA[[#This Row],[FINAL Vs LG]]>7.1,AVANZA[[#This Row],[FINAL Vs LG]]<11.1),"50%","0%")),0) -> 100% | AE3: =VLOOKUP(DAY(TODAY()),BACK!F:G,2,0) -> 14 | AF3: =BACK!$I$2 -> 24 | AG3: =IF(AVANZA[[#This Row],[Oferta_empaquetada_comisiones]]="SI",1,0) -> 0 | AH3: =IF(AVANZA[[#This Row],[Variable]]="TERMINADA",IFERROR(VLOOKUP(AVANZA[[#This Row],[SUPERVISOR]],Tabla2[#All],4,0),0),) -> 3.5 | AI3: =IF(AVANZA[[#This Row],[Producto]]="BA",1,0) -> 1 | AJ3: =IF(AVANZA[[#This Row],[Producto]]="DUO",1,0) -> 0 | AK3: =IF(AVANZA[[#This Row],[Producto]]="TRIO",1,0) -> 0 | AL3: 1648048636331251387 | AM3: -1 | AN3: -1 | AO3: 1785369241 | AP3: 46142.386 | AQ3: -1 | AR3: 2512688904 | AS3: -1 | AT3: -1 | AU3: -1 | AV3: -1 | AW3: -1 | AX3: FixedCreateSubscriber | AY3: -1 | AZ3: 2026 | BA3: 5 | BB3: 1 | BC3: -1 | BD3: Broadband Service | BE3: -1 | BF3: 20001620503190 | BG3: Plan Banda Ancha 900Mbps Solo Internet_Nac_25423 | BH3: 25423 | BI3: FS202604300915040963 | BJ3: -1 | BK3: -1 | BL3: -1 | BM3: TERMINADA | BN3: Individual | BO3: 6108760564 | BP3: Movistar Total | BQ3: 2026 | BR3: 4 | BS3: 30 | BT3: 46143.43 | BU3: OS90 | BV3: 46143 | BW3: Completed | BX3: 46142 | BY3: 46143 | BZ3: Call Back To CRM | CA3: MEDELLIN | CB3: ANTIOQUIA | CC3: KR 84 CL 77 C C-57 BELLO HORIZONTE 57 APT 201 LAT:6.28199227 LON:-75.58856262 | CD3: BELLO HORIZONTE | CE3: -1 | CF3: 05001000 | CG3: Antioquia - Choco | CH3: SIN PRESENCIA | CI3: 1073250775 | CJ3: SHARON NATALIA GONZALEZ CAAADULCE | CK3: CANAL ONLINE | CL3: ON LINE | CM3: ATENTO COLOMBIA S.A. | CN3: CANAL ON LINE - ATENTO CLICK TO CALL | CT3: 2 | CU3: Broadband Service | CW3: Plan Banda Ancha 900Mbps Solo Internet_Nac_25423 | CX3: 25423 | DA3: SV | DB3: -1 | DF3: ALTA | DJ3: 900000 | DK3: Cliente Nuevo | DL3: Cliente Existente | DN3: BA | DR3: sngonzalezca | DS3: SHARON NATALIA GONZALEZ CAAADULCE | DT3: 1073250775 | DV3: 1 | DW3: NOROCCIDENTE | ED3: 46143 | EF3: 9 | EP3: 830065842-5 | ES3: 3_1 | FA3: CANAL ONLINE | FB3: Antioquia | FD3: Antioquia | FE3: Medellín | FF3: Medellín | FK3: ATENTO | FL3: 5001000OH_ANTALCLLC_I_7360_Medellin_Castilla_3CASTI-CT3/4-60-06SS3-60-06@5001000_OH_ANTALCLLC_I_7360_Medellin_Castilla_3_CASTI-CT3/4-60-06_SS3-60-06 | FN3: CANAL ON LINE - ATENTO CLICK TO CALL | FO3: 9900202020033 | FR3: 94990 | GB3: PON | GC3: Broadband Service | GD3: 0 | GF3: 0 | GG3: 25423 | GI3: 94990 | GJ3: 0 | GL3: 0 | GM3: 113038 | GS3: FS | GT3: 45473 | GU3: CENTRO EXP | GV3: VALIDADO | GW3: Si | GX3: SV | GY3: Convergente Solo Contrato | GZ3: Convergente Nuevo | HA3: ONNET | HB3: MEDELLIN | HC3: MEDELLIN | HD3: MEDELLIN + NOROCCIDENTE | HE3: Individual | HF3: 628075585 | HG3: Venta mismo mes (F+M) diferente Canal_diferente Al | HH3: 1025889366 | HI3: 1. Radicadas | HJ3: 46151 | HK3: BECALL | HL3: TELEVENTAS | HM3: 9900210050001 | HN3: TELEVENTAS - BECALL | HO3: LUIS ALEJANDRO NIETO MARIN | HP3: 1116434451 | HR3: Asistido | HV3: 94990 | HW3: NO | HY3: 0 | HZ3: 0 | IA3: SI | IB3: NO | IE3: BOGOTA | IF3: BOGOTA | IG3: BOGOTA | IH3: Digital | II3: Fibra | IJ3: B2C | IK3: Asistido | IL3: C2C | IM3: Atento | IN3: Alta | IP3: - | IQ3: Digital | IS3: ELECTRONICA | IT3: WhatsApp Bot | IY3: NO
A4: =DAY(AVANZA[[#This Row],[FechaSeguimiento]]) -> 1 | B4: =MONTH(AVANZA[[#This Row],[FechaSeguimiento]]) -> 5 | C4: =LOWER(IF(AND(AVANZA[[#This Row],[Mes_Reg]]=MONTH(TODAY()),AND(AVANZA[[#This Row],[Dia_Reg]]>0,AVANZA[[#This Row],[Dia_Reg]]<9)),"SEMANA 1","")&IF(AND(AVANZA[[#This Row],[Mes_Reg]]=MONTH(TODAY()),AND(AVANZA[[#This Row],[Dia_Reg]]>8,AVANZA[[#This Row],[Dia_Reg]]<16)),"SEMANA 2","")&IF(AND(AVANZA[[#This Row],[Mes_Reg]]=MONTH(TODAY()),AND(AVANZA[[#This Row],[Dia_Reg]]>15,AVANZA[[#This Row],[Dia_Reg]]<23)),"SEMANA 3","")&IF(AND(AVANZA[[#This Row],[Mes_Reg]]=MONTH(TODAY()),AND(AVANZA[[#This Row],[Dia_Reg]]>22,AVANZA[[#This Row],[Dia_Reg]]<31)),"SEMANA 4","")&IF(AVANZA[[#This Row],[Mes_Reg]]<>MONTH(TODAY()),"BOLSA MES ANTERIOR","")) -> bolsa mes anterior | D4: =LOWER(IFERROR(VLOOKUP(AVANZA[[#This Row],[ID_Peticion]],CANCELADAS[#All],2,0),"")) | E4: =LOWER(IFERROR(VLOOKUP(AVANZA[[#This Row],[ID_Peticion]],CANCELADAS[#All],3,0),"")) | F4: =LOWER(IF(AVANZA[[#This Row],[CEDULA CLIENTE]]<>""," CC: " & COUNTIFS(AVANZA[CEDULA CLIENTE],AVANZA[[#This Row],[CEDULA CLIENTE]]),"")& IF(AVANZA[[#This Row],[Direccion]]<>""," DIR: " & COUNTIFS(AVANZA[Direccion],AVANZA[[#This Row],[Direccion]]),"")) -> dir: 1 | G4: =IFERROR(VLOOKUP(AVANZA[[#This Row],[Cedula_Vendedor_Atis]],PLANTA[[#All],[CEDULA]:[LINEA]],3,0),"No Cruza") -> Marisol Avella | H4: =IFERROR(VLOOKUP(AVANZA[[#This Row],[Cedula_Vendedor_Atis]],PLANTA[[#All],[CEDULA]:[LINEA]],4,0),"No Cruza") -> Fija | I4: =LOWER(IF(AVANZA[[#This Row],[ATRIBUIBLE]]="",AVANZA[[#This Row],[Variable]],AVANZA[[#This Row],[ATRIBUIBLE]])) -> terminada | J4: =IF(AVANZA[[#This Row],[Variable]]=AVANZA[[#Headers],[TERMINADA]],1,0) -> 1 | K4: =IF(AVANZA[[#This Row],[Variable]]=AVANZA[[#Headers],[ANULADA]],1,0) -> 0 | L4: =IF(AVANZA[[#This Row],[Variable]]=AVANZA[[#Headers],[PENDIENTE]],1,0) -> 0 | M4: =IF(AVANZA[[#This Row],[ESTADO AGENDA]]="AGENDADA",1,0) -> 0 | N4: =IF(AVANZA[[#This Row],[ESTADO AGENDA]]="PENDIENTE DE AGENDAR",1,0) -> 0 | O4: =IF(AVANZA[[#This Row],[ESTADO AGENDA]]="SUSPENDIDA",1,0) -> 0 | P4: {=_xlfn.XLOOKUP(AVANZA[[#This Row],[Num_Agrupacion_Pet_Atis]],Tabla1[[#All],[Numero_de_actuacion]],Tabla1[[#All],[Estado_de_la_orden]],"",0)} | Q4: {=_xlfn.XLOOKUP(AVANZA[[#This Row],[Num_Agrupacion_Pet_Atis]],Tabla1[[#All],[Numero_de_actuacion]],Tabla1[[#All],[Fecha_de_la_cita]],"",0)} | R4: {=_xlfn.XLOOKUP(AVANZA[[#This Row],[Num_Agrupacion_Pet_Atis]],Tabla1[[#All],[Numero_de_actuacion]],Tabla1[[#All],[Franja_horaria_de_la_cita]],"",0)} | S4: =IFERROR(DAY(AVANZA[[#This Row],[FECHA AGENDA]]),"") | T4: =IFERROR(MONTH(AVANZA[[#This Row],[FECHA AGENDA]]),"") | U4: {=_xlfn.XLOOKUP(AVANZA[[#This Row],[Num_Agrupacion_Pet_Atis]],Tabla1[[#All],[Numero_de_actuacion]],Tabla1[[#All],[Motivo_de_suspension]],"",0)} | V4: {=_xlfn.XLOOKUP(AVANZA[[#This Row],[Num_Agrupacion_Pet_Atis]],Tabla1[[#All],[Numero_de_actuacion]],Tabla1[[#All],[No_identificacion_cliente]],"",0)} | W4: {=_xlfn.XLOOKUP(AVANZA[[#This Row],[Num_Agrupacion_Pet_Atis]],Tabla1[[#All],[Numero_de_actuacion]],Tabla1[[#All],[Movil_de_contacto]],"",0)} | X4: =IF(OR(AVANZA[[#This Row],[ESTADO LEG]]="Legalizada grabacion",AVANZA[[#This Row],[ESTADO LEG]]="Legalizada aut"),1,0) -> 1 | Y4: =IF(OR(AVANZA[[#This Row],[ESTADO LEG]]="pdte legalizar",AVANZA[[#This Row],[ESTADO LEG]]="No cruza"),1,0) -> 0 | Z4: {=IF(AVANZA[[#This Row],[Variable]]="Terminada",LOWER(_xlfn.XLOOKUP(AVANZA[[#This Row],[ID_Peticion]],Tabla6[[#All],[NUM_PETICION]],Tabla6[[#All],[ESTADO_LEG]],"NO CRUZA",0)),AVANZA[[#This Row],[Variable]])} -> legalizada grabacion | AA4: {=_xlfn.XLOOKUP(AVANZA[[#This Row],[ID_Peticion]],Tabla6[[#All],[NUM_PETICION]],Tabla6[[#All],[DIF_DIAS]],"",0)} -> 4 | AB4: {=IFERROR(_xlfn.XLOOKUP(AVANZA[[#This Row],[ID_Peticion]],Tabla6[[#All],[NUM_PETICION]],Tabla6[[#All],[FEC_LEGAL]],"",0),"")} -> 46147 | AC4: =IF(AVANZA[[#This Row],[FECHA LEG]]<>0,IFERROR(AVANZA[[#This Row],[FECHA LEG]]-AVANZA[[#This Row],[FechaIniEstadoSubPetAtis]],0),TODAY()-AVANZA[[#This Row],[FechaIniEstadoSubPetAtis]]) -> 4 | AD4: =IF(AVANZA[[#This Row],[FINAL Vs LG]]<>0,IF(AVANZA[[#This Row],[FINAL Vs LG]]<7.1,"100%",IF(AND(AVANZA[[#This Row],[FINAL Vs LG]]>7.1,AVANZA[[#This Row],[FINAL Vs LG]]<11.1),"50%","0%")),0) -> 100% | AE4: =VLOOKUP(DAY(TODAY()),BACK!F:G,2,0) -> 14 | AF4: =BACK!$I$2 -> 24 | AG4: =IF(AVANZA[[#This Row],[Oferta_empaquetada_comisiones]]="SI",1,0) -> 0 | AH4: =IF(AVANZA[[#This Row],[Variable]]="TERMINADA",IFERROR(VLOOKUP(AVANZA[[#This Row],[SUPERVISOR]],Tabla2[#All],4,0),0),) -> 3.5 | AI4: =IF(AVANZA[[#This Row],[Producto]]="BA",1,0) -> 1 | AJ4: =IF(AVANZA[[#This Row],[Producto]]="DUO",1,0) -> 0 | AK4: =IF(AVANZA[[#This Row],[Producto]]="TRIO",1,0) -> 0 | AL4: 1624058238002044670 | AM4: -1 | AN4: -1 | AO4: 1784982688 | AP4: 46141.697 | AQ4: -1 | AR4: 2512687770 | AS4: -1 | AT4: -1 | AU4: -1 | AV4: -1 | AW4: -1 | AX4: FixedCreateSubscriber | AY4: -1 | AZ4: 2026 | BA4: 5 | BB4: 1 | BC4: -1 | BD4: Broadband Service | BE4: -1 | BF4: 20001620107451 | BG4: Plan Banda Ancha 900Mbps Solo Internet_Nac_25423 | BH4: 25423 | BI4: FS202604291641141607 | BJ4: -1 | BK4: -1 | BL4: -1 | BM4: TERMINADA | BN4: Individual | BO4: 6108749533 | BP4: Gold | BQ4: 2026 | BR4: 4 | BS4: 29 | BT4: 46143.449 | BU4: OS90 | BV4: 46143 | BW4: Completed | BX4: 46141 | BY4: 46143 | BZ4: Call Back To CRM | CA4: MEDELLIN | CB4: ANTIOQUIA | CC4: CL 97 KR 76-119 SAN MARTIN DE PORRES 119 APT 201 LAT:6.2952141966666 LON:-75.58087016666 | CD4: SAN MARTIN DE PORRES | CE4: -1 | CF4: 05001000 | CG4: Antioquia - Choco | CH4: SIN PRESENCIA | CI4: 1018514067 | CJ4: JHOJAN ALEXANDER JIMENEZ MELO | CK4: CANAL ONLINE | CL4: TELEVENTAS | CM4: ATENTO COLOMBIA S.A. | CN4: CANAL ON LINE - ATENTO OUT BOUND | CT4: 2 | CU4: Broadband Service | CW4: Plan Banda Ancha 900Mbps Solo Internet_Nac_25423 | CX4: 25423 | DA4: SV | DB4: -1 | DF4: ALTA | DJ4: 900000 | DK4: Cliente Nuevo | DL4: Cliente Existente | DN4: BA | DR4: jajimenezme1 | DS4: JHOJAN ALEXANDER JIMENEZ MELO | DT4: 1018514067 | DV4: 1 | DW4: NOROCCIDENTE | ED4: 46143 | EF4: 5 | EP4: 830065842-5 | ES4: 3_1 | FA4: CANAL ONLINE | FB4: Antioquia | FD4: Antioquia | FE4: Medellín | FF4: Medellín | FK4: ATENTO | FL4: 5001000OH_ANTALCLLA_I_7360_Medellin_CastillaCASTI-CT3/4-19-03SS4-19-03@5001000_OH_ANTALCLLA_I_7360_Medellin_Castilla_CASTI-CT3/4-19-03_SS4-19-03 | FN4: CANAL ON LINE - ATENTO OUT BOUND | FO4: 9900202020034 | FR4: 94990 | GB4: PON | GC4: Broadband Service | GD4: 0 | GF4: 0 | GG4: 25423 | GI4: 94990 | GJ4: 0 | GL4: 0 | GM4: 113038 | GS4: FS | GT4: 45322 | GU4: CENTRO EXP | GV4: SIN EMAIL | GW4: No | GZ4: No Convergente | HA4: ONNET | HB4: MEDELLIN | HC4: MEDELLIN | HD4: MEDELLIN + NOROCCIDENTE | HE4: Individual | HF4: 629575580 | HR4: Asistido | HV4: 94990 | HW4: NO | HY4: 0 | HZ4: 0 | IA4: NO | IB4: NO | IE4: BOGOTA | IF4: BOGOTA | IG4: BOGOTA | IH4: Digital | II4: Fibra | IJ4: B2C | IK4: Asistido | IL4: Inbound | IM4: Atento | IN4: Alta | IP4: - | IQ4: Digital | IS4: ELECTRONICA | IT4: Inbound | IY4: NO
A5: =DAY(AVANZA[[#This Row],[FechaSeguimiento]]) -> 1 | B5: =MONTH(AVANZA[[#This Row],[FechaSeguimiento]]) -> 5 | C5: =LOWER(IF(AND(AVANZA[[#This Row],[Mes_Reg]]=MONTH(TODAY()),AND(AVANZA[[#This Row],[Dia_Reg]]>0,AVANZA[[#This Row],[Dia_Reg]]<9)),"SEMANA 1","")&IF(AND(AVANZA[[#This Row],[Mes_Reg]]=MONTH(TODAY()),AND(AVANZA[[#This Row],[Dia_Reg]]>8,AVANZA[[#This Row],[Dia_Reg]]<16)),"SEMANA 2","")&IF(AND(AVANZA[[#This Row],[Mes_Reg]]=MONTH(TODAY()),AND(AVANZA[[#This Row],[Dia_Reg]]>15,AVANZA[[#This Row],[Dia_Reg]]<23)),"SEMANA 3","")&IF(AND(AVANZA[[#This Row],[Mes_Reg]]=MONTH(TODAY()),AND(AVANZA[[#This Row],[Dia_Reg]]>22,AVANZA[[#This Row],[Dia_Reg]]<31)),"SEMANA 4","")&IF(AVANZA[[#This Row],[Mes_Reg]]<>MONTH(TODAY()),"BOLSA MES ANTERIOR","")) -> bolsa mes anterior | D5: =LOWER(IFERROR(VLOOKUP(AVANZA[[#This Row],[ID_Peticion]],CANCELADAS[#All],2,0),"")) -> carrusel | E5: =LOWER(IFERROR(VLOOKUP(AVANZA[[#This Row],[ID_Peticion]],CANCELADAS[#All],3,0),"")) -> carrusel | F5: =LOWER(IF(AVANZA[[#This Row],[CEDULA CLIENTE]]<>""," CC: " & COUNTIFS(AVANZA[CEDULA CLIENTE],AVANZA[[#This Row],[CEDULA CLIENTE]]),"")& IF(AVANZA[[#This Row],[Direccion]]<>""," DIR: " & COUNTIFS(AVANZA[Direccion],AVANZA[[#This Row],[Direccion]]),"")) -> dir: 1 | G5: =IFERROR(VLOOKUP(AVANZA[[#This Row],[Cedula_Vendedor_Atis]],PLANTA[[#All],[CEDULA]:[LINEA]],3,0),"No Cruza") -> Marisol Avella | H5: =IFERROR(VLOOKUP(AVANZA[[#This Row],[Cedula_Vendedor_Atis]],PLANTA[[#All],[CEDULA]:[LINEA]],4,0),"No Cruza") -> Fija | I5: =LOWER(IF(AVANZA[[#This Row],[ATRIBUIBLE]]="",AVANZA[[#This Row],[Variable]],AVANZA[[#This Row],[ATRIBUIBLE]])) -> carrusel | J5: =IF(AVANZA[[#This Row],[Variable]]=AVANZA[[#Headers],[TERMINADA]],1,0) -> 0 | K5: =IF(AVANZA[[#This Row],[Variable]]=AVANZA[[#Headers],[ANULADA]],1,0) -> 1 | L5: =IF(AVANZA[[#This Row],[Variable]]=AVANZA[[#Headers],[PENDIENTE]],1,0) -> 0 | M5: =IF(AVANZA[[#This Row],[ESTADO AGENDA]]="AGENDADA",1,0) -> 0 | N5: =IF(AVANZA[[#This Row],[ESTADO AGENDA]]="PENDIENTE DE AGENDAR",1,0) -> 0 | O5: =IF(AVANZA[[#This Row],[ESTADO AGENDA]]="SUSPENDIDA",1,0) -> 0 | P5: {=_xlfn.XLOOKUP(AVANZA[[#This Row],[Num_Agrupacion_Pet_Atis]],Tabla1[[#All],[Numero_de_actuacion]],Tabla1[[#All],[Estado_de_la_orden]],"",0)} | Q5: {=_xlfn.XLOOKUP(AVANZA[[#This Row],[Num_Agrupacion_Pet_Atis]],Tabla1[[#All],[Numero_de_actuacion]],Tabla1[[#All],[Fecha_de_la_cita]],"",0)} | R5: {=_xlfn.XLOOKUP(AVANZA[[#This Row],[Num_Agrupacion_Pet_Atis]],Tabla1[[#All],[Numero_de_actuacion]],Tabla1[[#All],[Franja_horaria_de_la_cita]],"",0)} | S5: =IFERROR(DAY(AVANZA[[#This Row],[FECHA AGENDA]]),"") | T5: =IFERROR(MONTH(AVANZA[[#This Row],[FECHA AGENDA]]),"") | U5: {=_xlfn.XLOOKUP(AVANZA[[#This Row],[Num_Agrupacion_Pet_Atis]],Tabla1[[#All],[Numero_de_actuacion]],Tabla1[[#All],[Motivo_de_suspension]],"",0)} | V5: {=_xlfn.XLOOKUP(AVANZA[[#This Row],[Num_Agrupacion_Pet_Atis]],Tabla1[[#All],[Numero_de_actuacion]],Tabla1[[#All],[No_identificacion_cliente]],"",0)} | W5: {=_xlfn.XLOOKUP(AVANZA[[#This Row],[Num_Agrupacion_Pet_Atis]],Tabla1[[#All],[Numero_de_actuacion]],Tabla1[[#All],[Movil_de_contacto]],"",0)} | X5: =IF(OR(AVANZA[[#This Row],[ESTADO LEG]]="Legalizada grabacion",AVANZA[[#This Row],[ESTADO LEG]]="Legalizada aut"),1,0) -> 0 | Y5: =IF(OR(AVANZA[[#This Row],[ESTADO LEG]]="pdte legalizar",AVANZA[[#This Row],[ESTADO LEG]]="No cruza"),1,0) -> 0 | Z5: {=IF(AVANZA[[#This Row],[Variable]]="Terminada",LOWER(_xlfn.XLOOKUP(AVANZA[[#This Row],[ID_Peticion]],Tabla6[[#All],[NUM_PETICION]],Tabla6[[#All],[ESTADO_LEG]],"NO CRUZA",0)),AVANZA[[#This Row],[Variable]])} -> ANULADA | AA5: {=_xlfn.XLOOKUP(AVANZA[[#This Row],[ID_Peticion]],Tabla6[[#All],[NUM_PETICION]],Tabla6[[#All],[DIF_DIAS]],"",0)} | AB5: {=IFERROR(_xlfn.XLOOKUP(AVANZA[[#This Row],[ID_Peticion]],Tabla6[[#All],[NUM_PETICION]],Tabla6[[#All],[FEC_LEGAL]],"",0),"")} | AC5: =IF(AVANZA[[#This Row],[FECHA LEG]]<>0,IFERROR(AVANZA[[#This Row],[FECHA LEG]]-AVANZA[[#This Row],[FechaIniEstadoSubPetAtis]],0),TODAY()-AVANZA[[#This Row],[FechaIniEstadoSubPetAtis]]) -> 0 | AD5: =IF(AVANZA[[#This Row],[FINAL Vs LG]]<>0,IF(AVANZA[[#This Row],[FINAL Vs LG]]<7.1,"100%",IF(AND(AVANZA[[#This Row],[FINAL Vs LG]]>7.1,AVANZA[[#This Row],[FINAL Vs LG]]<11.1),"50%","0%")),0) -> 0 | AE5: =VLOOKUP(DAY(TODAY()),BACK!F:G,2,0) -> 14 | AF5: =BACK!$I$2 -> 24 | AG5: =IF(AVANZA[[#This Row],[Oferta_empaquetada_comisiones]]="SI",1,0) -> 0 | AH5: =IF(AVANZA[[#This Row],[Variable]]="TERMINADA",IFERROR(VLOOKUP(AVANZA[[#This Row],[SUPERVISOR]],Tabla2[#All],4,0),0),) -> 0 | AI5: =IF(AVANZA[[#This Row],[Producto]]="BA",1,0) -> 1 | AJ5: =IF(AVANZA[[#This Row],[Producto]]="DUO",1,0) -> 0 | AK5: =IF(AVANZA[[#This Row],[Producto]]="TRIO",1,0) -> 0 | AL5: 1760285521955967900 | AM5: -1 | AN5: -1 | AO5: 1784153960 | AP5: 46140.473 | AQ5: -1 | AR5: 2512683151 | AS5: -1 | AT5: -1 | AU5: -1 | AV5: -1 | AW5: -1 | AX5: FixedCreateSubscriber | AY5: -1 | AZ5: 2026 | BA5: 5 | BB5: 1 | BC5: -1 | BD5: Broadband Service | BE5: -1 | BF5: 20001619384694 | BG5: Plan Banda Ancha 900Mbps Solo Internet_Nac_25423 | BH5: 25423 | BJ5: -1 | BK5: -1 | BL5: -1 | BM5: ANULADA | BN5: Individual | BO5: 6108731113 | BP5: Gold | BQ5: 2026 | BR5: 4 | BS5: 28 | BT5: 46143.514 | BU5: OS80 | BV5: 46143 | BW5: Cancelled | CA5: BOGOTA, D.C. | CB5: BOGOTA, D.C. | CC5: KR 18 CL 15-36 SAN VICTORINO 36 TOR 2 APT 4016 LAT:4.60836197 LON:-74.08179765 | CD5: SAN VICTORINO | CE5: -1 | CF5: 11001000 | CG5: Bogota | CH5: ATACANTE | CI5: 1063565638 | CJ5: JOYNNER FERNANDO BRISENO OLIVIERI | CK5: CANAL ONLINE | CL5: TELEVENTAS | CM5: ATENTO COLOMBIA S.A. | CN5: CANAL ON LINE - ATENTO OUT BOUND | CT5: 3 | CU5: Broadband Service | CW5: Plan Banda Ancha 900Mbps Solo Internet_Nac_25423 | CX5: 25423 | CY5: Anulada fraude marcada por campo remark | DA5: SV | DB5: -1 | DF5: ANULADA FRAUDE - REMARK | DJ5: 900000 | DK5: Cliente Nuevo | DL5: Cliente Nuevo | DN5: BA | DR5: jbrisenool | DS5: JOYNNER FERNANDO BRISENO OLIVIERI | DT5: 1063565638 | DV5: 1 | DW5: BOGOTA | EB5: 1 | ED5: 46143 | EF5: 5 | EP5: 830065842-5 | FA5: CANAL ONLINE | FB5: Bogotá D.C | FD5: Bogotá D.C | FE5: Bogotá | FF5: Bogotá | FK5: ATENTO | FN5: CANAL ON LINE - ATENTO OUT BOUND | FO5: 9900202020034 | FR5: 0 | GB5: PON | GM5: 0 | GS5: FS | GU5: CENTRO EXP | GW5: No | GZ5: No Convergente | HE5: Individual | HF5: 460574080 | HR5: Asistido | HV5: 94990 | HW5: NO | HY5: 0 | HZ5: 0 | IA5: SI | IB5: NO | IC5: The Fraud order (Carrusel) is cancelled by SOM. | IE5: BOGOTA | IF5: BOGOTA | IG5: BOGOTA | IH5: Digital | II5: Fibra | IJ5: B2C | IK5: Asistido | IL5: Outbound | IM5: Atento | IN5: - | IP5: - | IQ5: Digital | IR5: 0 | IS5: ELECTRONICA | IY5: NO
A6: =DAY(AVANZA[[#This Row],[FechaSeguimiento]]) -> 1 | B6: =MONTH(AVANZA[[#This Row],[FechaSeguimiento]]) -> 5 | C6: =LOWER(IF(AND(AVANZA[[#This Row],[Mes_Reg]]=MONTH(TODAY()),AND(AVANZA[[#This Row],[Dia_Reg]]>0,AVANZA[[#This Row],[Dia_Reg]]<9)),"SEMANA 1","")&IF(AND(AVANZA[[#This Row],[Mes_Reg]]=MONTH(TODAY()),AND(AVANZA[[#This Row],[Dia_Reg]]>8,AVANZA[[#This Row],[Dia_Reg]]<16)),"SEMANA 2","")&IF(AND(AVANZA[[#This Row],[Mes_Reg]]=MONTH(TODAY()),AND(AVANZA[[#This Row],[Dia_Reg]]>15,AVANZA[[#This Row],[Dia_Reg]]<23)),"SEMANA 3","")&IF(AND(AVANZA[[#This Row],[Mes_Reg]]=MONTH(TODAY()),AND(AVANZA[[#This Row],[Dia_Reg]]>22,AVANZA[[#This Row],[Dia_Reg]]<31)),"SEMANA 4","")&IF(AVANZA[[#This Row],[Mes_Reg]]<>MONTH(TODAY()),"BOLSA MES ANTERIOR","")) -> bolsa mes anterior | D6: =LOWER(IFERROR(VLOOKUP(AVANZA[[#This Row],[ID_Peticion]],CANCELADAS[#All],2,0),"")) | E6: =LOWER(IFERROR(VLOOKUP(AVANZA[[#This Row],[ID_Peticion]],CANCELADAS[#All],3,0),"")) | F6: =LOWER(IF(AVANZA[[#This Row],[CEDULA CLIENTE]]<>""," CC: " & COUNTIFS(AVANZA[CEDULA CLIENTE],AVANZA[[#This Row],[CEDULA CLIENTE]]),"")& IF(AVANZA[[#This Row],[Direccion]]<>""," DIR: " & COUNTIFS(AVANZA[Direccion],AVANZA[[#This Row],[Direccion]]),"")) -> dir: 1 | G6: =IFERROR(VLOOKUP(AVANZA[[#This Row],[Cedula_Vendedor_Atis]],PLANTA[[#All],[CEDULA]:[LINEA]],3,0),"No Cruza") -> Marisol Avella | H6: =IFERROR(VLOOKUP(AVANZA[[#This Row],[Cedula_Vendedor_Atis]],PLANTA[[#All],[CEDULA]:[LINEA]],4,0),"No Cruza") -> Fija | I6: =LOWER(IF(AVANZA[[#This Row],[ATRIBUIBLE]]="",AVANZA[[#This Row],[Variable]],AVANZA[[#This Row],[ATRIBUIBLE]])) -> terminada | J6: =IF(AVANZA[[#This Row],[Variable]]=AVANZA[[#Headers],[TERMINADA]],1,0) -> 1 | K6: =IF(AVANZA[[#This Row],[Variable]]=AVANZA[[#Headers],[ANULADA]],1,0) -> 0 | L6: =IF(AVANZA[[#This Row],[Variable]]=AVANZA[[#Headers],[PENDIENTE]],1,0) -> 0 | M6: =IF(AVANZA[[#This Row],[ESTADO AGENDA]]="AGENDADA",1,0) -> 0 | N6: =IF(AVANZA[[#This Row],[ESTADO AGENDA]]="PENDIENTE DE AGENDAR",1,0) -> 0 | O6: =IF(AVANZA[[#This Row],[ESTADO AGENDA]]="SUSPENDIDA",1,0) -> 0 | P6: {=_xlfn.XLOOKUP(AVANZA[[#This Row],[Num_Agrupacion_Pet_Atis]],Tabla1[[#All],[Numero_de_actuacion]],Tabla1[[#All],[Estado_de_la_orden]],"",0)} | Q6: {=_xlfn.XLOOKUP(AVANZA[[#This Row],[Num_Agrupacion_Pet_Atis]],Tabla1[[#All],[Numero_de_actuacion]],Tabla1[[#All],[Fecha_de_la_cita]],"",0)} | R6: {=_xlfn.XLOOKUP(AVANZA[[#This Row],[Num_Agrupacion_Pet_Atis]],Tabla1[[#All],[Numero_de_actuacion]],Tabla1[[#All],[Franja_horaria_de_la_cita]],"",0)} | S6: =IFERROR(DAY(AVANZA[[#This Row],[FECHA AGENDA]]),"") | T6: =IFERROR(MONTH(AVANZA[[#This Row],[FECHA AGENDA]]),"") | U6: {=_xlfn.XLOOKUP(AVANZA[[#This Row],[Num_Agrupacion_Pet_Atis]],Tabla1[[#All],[Numero_de_actuacion]],Tabla1[[#All],[Motivo_de_suspension]],"",0)} | V6: {=_xlfn.XLOOKUP(AVANZA[[#This Row],[Num_Agrupacion_Pet_Atis]],Tabla1[[#All],[Numero_de_actuacion]],Tabla1[[#All],[No_identificacion_cliente]],"",0)} | W6: {=_xlfn.XLOOKUP(AVANZA[[#This Row],[Num_Agrupacion_Pet_Atis]],Tabla1[[#All],[Numero_de_actuacion]],Tabla1[[#All],[Movil_de_contacto]],"",0)} | X6: =IF(OR(AVANZA[[#This Row],[ESTADO LEG]]="Legalizada grabacion",AVANZA[[#This Row],[ESTADO LEG]]="Legalizada aut"),1,0) -> 1 | Y6: =IF(OR(AVANZA[[#This Row],[ESTADO LEG]]="pdte legalizar",AVANZA[[#This Row],[ESTADO LEG]]="No cruza"),1,0) -> 0 | Z6: {=IF(AVANZA[[#This Row],[Variable]]="Terminada",LOWER(_xlfn.XLOOKUP(AVANZA[[#This Row],[ID_Peticion]],Tabla6[[#All],[NUM_PETICION]],Tabla6[[#All],[ESTADO_LEG]],"NO CRUZA",0)),AVANZA[[#This Row],[Variable]])} -> legalizada grabacion | AA6: {=_xlfn.XLOOKUP(AVANZA[[#This Row],[ID_Peticion]],Tabla6[[#All],[NUM_PETICION]],Tabla6[[#All],[DIF_DIAS]],"",0)} -> 4 | AB6: {=IFERROR(_xlfn.XLOOKUP(AVANZA[[#This Row],[ID_Peticion]],Tabla6[[#All],[NUM_PETICION]],Tabla6[[#All],[FEC_LEGAL]],"",0),"")} -> 46147 | AC6: =IF(AVANZA[[#This Row],[FECHA LEG]]<>0,IFERROR(AVANZA[[#This Row],[FECHA LEG]]-AVANZA[[#This Row],[FechaIniEstadoSubPetAtis]],0),TODAY()-AVANZA[[#This Row],[FechaIniEstadoSubPetAtis]]) -> 4 | AD6: =IF(AVANZA[[#This Row],[FINAL Vs LG]]<>0,IF(AVANZA[[#This Row],[FINAL Vs LG]]<7.1,"100%",IF(AND(AVANZA[[#This Row],[FINAL Vs LG]]>7.1,AVANZA[[#This Row],[FINAL Vs LG]]<11.1),"50%","0%")),0) -> 100% | AE6: =VLOOKUP(DAY(TODAY()),BACK!F:G,2,0) -> 14 | AF6: =BACK!$I$2 -> 24 | AG6: =IF(AVANZA[[#This Row],[Oferta_empaquetada_comisiones]]="SI",1,0) -> 0 | AH6: =IF(AVANZA[[#This Row],[Variable]]="TERMINADA",IFERROR(VLOOKUP(AVANZA[[#This Row],[SUPERVISOR]],Tabla2[#All],4,0),0),) -> 3.5 | AI6: =IF(AVANZA[[#This Row],[Producto]]="BA",1,0) -> 0 | AJ6: =IF(AVANZA[[#This Row],[Producto]]="DUO",1,0) -> 0 | AK6: =IF(AVANZA[[#This Row],[Producto]]="TRIO",1,0) -> 1 | AL6: 53061857 | AM6: -1 | AN6: -1 | AO6: 1784753901 | AP6: 46141.485 | AQ6: -1 | AR6: 2512686193 | AS6: -1 | AT6: -1 | AU6: -1 | AV6: -1 | AW6: -1 | AX6: FixedCreateSubscriber | AY6: -1 | AZ6: 2026 | BA6: 5 | BB6: 1 | BC6: -1 | BD6: Broadband Service | BE6: -1 | BF6: 20001619901767 | BG6: Convergente_Plan Ancha 900Mbps_Mov Ilim_Trio_25422 | BH6: 25422 | BI6: FS202604291136541249 | BJ6: -1 | BK6: -1 | BL6: -1 | BM6: TERMINADA | BN6: Individual | BO6: 6082911402 | BP6: Movistar Total | BQ6: 2026 | BR6: 4 | BS6: 29 | BT6: 46143.555 | BU6: OS90 | BV6: 46143 | BW6: Completed | BX6: 46141 | BY6: 46143 | BZ6: Call Back To CRM | CA6: TURBACO | CB6: BOLIVAR | CC6: KR 32 CL 26-63 EL VALLE 63 APT 1 LAT:10.33987058 LON:-75.42307505 | CD6: EL VALLE | CE6: -1 | CF6: 13836000 | CG6: Bolivar - San Andres | CH6: ATACANTE | CI6: 53061857 | CJ6: NOHORA AMADO LONDONO | CK6: CANAL ONLINE | CL6: ON LINE | CM6: ATENTO COLOMBIA S.A. | CN6: CANAL ON LINE - ATENTO CLICK TO CALL | CT6: 3 | CU6: BA + LB + IPTV | CW6: MTotal_Trio_Voz Ilim Nal _Ba Ancha 900Mbps_IPTV_2_Decos_Mov Ilim_Nac_25425 | CX6: 25425 | DA6: SV | DB6: -1 | DF6: ALTA | DJ6: 900000 | DK6: Cliente Nuevo | DL6: Cliente Nuevo | DN6: TRIO | DR6: namadolo | DS6: NOHORA AMADO LONDONO | DT6: 53061857 | DV6: 1 | DW6: CARIBE | ED6: 46143 | EF6: 20 | EP6: 830065842-5 | ES6: Recreo | FA6: CANAL ONLINE | FB6: Bolívar | FD6: Bolívar | FE6: Turbaco | FF6: Turbaco | FK6: ATENTO | FL6: 13836000OH_BOLALTACO_I_7360_Turbaco_CentroCENTR-CT5-22-02SS5-22-02@13836000_OH_BOLALTACO_I_7360_Turbaco_Centro_CENTR-CT5-22-02_SS5-22-02 | FN6: CANAL ON LINE - ATENTO CLICK TO CALL | FO6: 9900202020033 | FR6: 113904 | GB6: PON | GC6: BA + LB + IPTV | GD6: 25188 | GF6: 2353 | GG6: 25422 | GI6: 87224 | GJ6: 25427 | GL6: 24327 | GM6: 135545 | GS6: FS | GT6: 45382 | GU6: CENTRO EXP | GV6: SIN EMAIL | GW6: Si | GX6: Convergente Solo Contrato | GY6: Convergente Solo Contrato | GZ6: Convergente Existente | HA6: ONNET | HB6: BOLIVAR (CARTAGENA/TURBACO) | HC6: TURBACO | HD6: CARIBE | HE6: Individual | HF6: 1033575420 | HG6: Venta Hogar (F) a cliente Movistar Total | HR6: Asistido | HV6: 118900 | HW6: SI | HX6: Migracion Pos-Pos | HY6: 131572 | HZ6: 17668 | IA6: SI | IB6: NO | ID6: >= 120 | IE6: BOGOTA | IF6: BOGOTA | IG6: BOGOTA | IH6: Digital | II6: Fibra | IJ6: B2C | IK6: Asistido | IL6: C2C | IM6: Atento | IN6: Alta | IP6: - | IQ6: Digital | IS6: ELECTRONICA | IY6: NO
A7: =DAY(AVANZA[[#This Row],[FechaSeguimiento]]) -> 1 | B7: =MONTH(AVANZA[[#This Row],[FechaSeguimiento]]) -> 5 | C7: =LOWER(IF(AND(AVANZA[[#This Row],[Mes_Reg]]=MONTH(TODAY()),AND(AVANZA[[#This Row],[Dia_Reg]]>0,AVANZA[[#This Row],[Dia_Reg]]<9)),"SEMANA 1","")&IF(AND(AVANZA[[#This Row],[Mes_Reg]]=MONTH(TODAY()),AND(AVANZA[[#This Row],[Dia_Reg]]>8,AVANZA[[#This Row],[Dia_Reg]]<16)),"SEMANA 2","")&IF(AND(AVANZA[[#This Row],[Mes_Reg]]=MONTH(TODAY()),AND(AVANZA[[#This Row],[Dia_Reg]]>15,AVANZA[[#This Row],[Dia_Reg]]<23)),"SEMANA 3","")&IF(AND(AVANZA[[#This Row],[Mes_Reg]]=MONTH(TODAY()),AND(AVANZA[[#This Row],[Dia_Reg]]>22,AVANZA[[#This Row],[Dia_Reg]]<31)),"SEMANA 4","")&IF(AVANZA[[#This Row],[Mes_Reg]]<>MONTH(TODAY()),"BOLSA MES ANTERIOR","")) -> bolsa mes anterior | D7: =LOWER(IFERROR(VLOOKUP(AVANZA[[#This Row],[ID_Peticion]],CANCELADAS[#All],2,0),"")) | E7: =LOWER(IFERROR(VLOOKUP(AVANZA[[#This Row],[ID_Peticion]],CANCELADAS[#All],3,0),"")) | F7: =LOWER(IF(AVANZA[[#This Row],[CEDULA CLIENTE]]<>""," CC: " & COUNTIFS(AVANZA[CEDULA CLIENTE],AVANZA[[#This Row],[CEDULA CLIENTE]]),"")& IF(AVANZA[[#This Row],[Direccion]]<>""," DIR: " & COUNTIFS(AVANZA[Direccion],AVANZA[[#This Row],[Direccion]]),"")) -> dir: 1 | G7: =IFERROR(VLOOKUP(AVANZA[[#This Row],[Cedula_Vendedor_Atis]],PLANTA[[#All],[CEDULA]:[LINEA]],3,0),"No Cruza") -> Marisol Avella | H7: =IFERROR(VLOOKUP(AVANZA[[#This Row],[Cedula_Vendedor_Atis]],PLANTA[[#All],[CEDULA]:[LINEA]],4,0),"No Cruza") -> Fija | I7: =LOWER(IF(AVANZA[[#This Row],[ATRIBUIBLE]]="",AVANZA[[#This Row],[Variable]],AVANZA[[#This Row],[ATRIBUIBLE]])) -> terminada | J7: =IF(AVANZA[[#This Row],[Variable]]=AVANZA[[#Headers],[TERMINADA]],1,0) -> 1 | K7: =IF(AVANZA[[#This Row],[Variable]]=AVANZA[[#Headers],[ANULADA]],1,0) -> 0 | L7: =IF(AVANZA[[#This Row],[Variable]]=AVANZA[[#Headers],[PENDIENTE]],1,0) -> 0 | M7: =IF(AVANZA[[#This Row],[ESTADO AGENDA]]="AGENDADA",1,0) -> 0 | N7: =IF(AVANZA[[#This Row],[ESTADO AGENDA]]="PENDIENTE DE AGENDAR",1,0) -> 0 | O7: =IF(AVANZA[[#This Row],[ESTADO AGENDA]]="SUSPENDIDA",1,0) -> 0 | P7: {=_xlfn.XLOOKUP(AVANZA[[#This Row],[Num_Agrupacion_Pet_Atis]],Tabla1[[#All],[Numero_de_actuacion]],Tabla1[[#All],[Estado_de_la_orden]],"",0)} | Q7: {=_xlfn.XLOOKUP(AVANZA[[#This Row],[Num_Agrupacion_Pet_Atis]],Tabla1[[#All],[Numero_de_actuacion]],Tabla1[[#All],[Fecha_de_la_cita]],"",0)} | R7: {=_xlfn.XLOOKUP(AVANZA[[#This Row],[Num_Agrupacion_Pet_Atis]],Tabla1[[#All],[Numero_de_actuacion]],Tabla1[[#All],[Franja_horaria_de_la_cita]],"",0)} | S7: =IFERROR(DAY(AVANZA[[#This Row],[FECHA AGENDA]]),"") | T7: =IFERROR(MONTH(AVANZA[[#This Row],[FECHA AGENDA]]),"") | U7: {=_xlfn.XLOOKUP(AVANZA[[#This Row],[Num_Agrupacion_Pet_Atis]],Tabla1[[#All],[Numero_de_actuacion]],Tabla1[[#All],[Motivo_de_suspension]],"",0)} | V7: {=_xlfn.XLOOKUP(AVANZA[[#This Row],[Num_Agrupacion_Pet_Atis]],Tabla1[[#All],[Numero_de_actuacion]],Tabla1[[#All],[No_identificacion_cliente]],"",0)} | W7: {=_xlfn.XLOOKUP(AVANZA[[#This Row],[Num_Agrupacion_Pet_Atis]],Tabla1[[#All],[Numero_de_actuacion]],Tabla1[[#All],[Movil_de_contacto]],"",0)} | X7: =IF(OR(AVANZA[[#This Row],[ESTADO LEG]]="Legalizada grabacion",AVANZA[[#This Row],[ESTADO LEG]]="Legalizada aut"),1,0) -> 1 | Y7: =IF(OR(AVANZA[[#This Row],[ESTADO LEG]]="pdte legalizar",AVANZA[[#This Row],[ESTADO LEG]]="No cruza"),1,0) -> 0 | Z7: {=IF(AVANZA[[#This Row],[Variable]]="Terminada",LOWER(_xlfn.XLOOKUP(AVANZA[[#This Row],[ID_Peticion]],Tabla6[[#All],[NUM_PETICION]],Tabla6[[#All],[ESTADO_LEG]],"NO CRUZA",0)),AVANZA[[#This Row],[Variable]])} -> legalizada grabacion | AA7: {=_xlfn.XLOOKUP(AVANZA[[#This Row],[ID_Peticion]],Tabla6[[#All],[NUM_PETICION]],Tabla6[[#All],[DIF_DIAS]],"",0)} -> 4 | AB7: {=IFERROR(_xlfn.XLOOKUP(AVANZA[[#This Row],[ID_Peticion]],Tabla6[[#All],[NUM_PETICION]],Tabla6[[#All],[FEC_LEGAL]],"",0),"")} -> 46147 | AC7: =IF(AVANZA[[#This Row],[FECHA LEG]]<>0,IFERROR(AVANZA[[#This Row],[FECHA LEG]]-AVANZA[[#This Row],[FechaIniEstadoSubPetAtis]],0),TODAY()-AVANZA[[#This Row],[FechaIniEstadoSubPetAtis]]) -> 4 | AD7: =IF(AVANZA[[#This Row],[FINAL Vs LG]]<>0,IF(AVANZA[[#This Row],[FINAL Vs LG]]<7.1,"100%",IF(AND(AVANZA[[#This Row],[FINAL Vs LG]]>7.1,AVANZA[[#This Row],[FINAL Vs LG]]<11.1),"50%","0%")),0) -> 100% | AE7: =VLOOKUP(DAY(TODAY()),BACK!F:G,2,0) -> 14 | AF7: =BACK!$I$2 -> 24 | AG7: =IF(AVANZA[[#This Row],[Oferta_empaquetada_comisiones]]="SI",1,0) -> 1 | AH7: =IF(AVANZA[[#This Row],[Variable]]="TERMINADA",IFERROR(VLOOKUP(AVANZA[[#This Row],[SUPERVISOR]],Tabla2[#All],4,0),0),) -> 3.5 | AI7: =IF(AVANZA[[#This Row],[Producto]]="BA",1,0) -> 0 | AJ7: =IF(AVANZA[[#This Row],[Producto]]="DUO",1,0) -> 0 | AK7: =IF(AVANZA[[#This Row],[Producto]]="TRIO",1,0) -> 1 | AL7: 1015443152 | AM7: -1 | AN7: -1 | AO7: 1784429146 | AP7: 46140.794 | AQ7: -1 | AR7: 2512685291 | AS7: -1 | AT7: -1 | AU7: -1 | AV7: -1 | AW7: -1 | AX7: FixedCreateSubscriber | AY7: -1 | AZ7: 2026 | BA7: 5 | BB7: 1 | BC7: -1 | BD7: Broadband Service | BE7: -1 | BF7: 20001619646227 | BG7: Convergente_Plan Ancha 900Mbps_Mov Ilim_Trio_25422 | BH7: 25422 | BI7: FS202604281902281085 | BJ7: -1 | BK7: -1 | BL7: -1 | BM7: TERMINADA | BN7: Individual | BO7: 6108727678 | BP7: Movistar Total | BQ7: 2026 | BR7: 4 | BS7: 28 | BT7: 46143.559 | BU7: OS90 | BV7: 46143 | BW7: Completed | BX7: 46140 | BY7: 46143 | BZ7: Call Back To CRM | CA7: BOGOTA, D.C. | CB7: BOGOTA, D.C. | CC7: CL 35 B S KR 73 B-23 SUPER MANZANA 3 23 APT 201 LAT:4.62043741 LON:-74.14649193 | CD7: SUPER MANZANA 3 | CE7: -1 | CF7: 11001000 | CG7: Bogota | CH7: ATACANTE | CI7: 1015443152 | CJ7: BRAYAN NICOLAS SIERRA RODRIGUEZ | CK7: CANAL ONLINE | CL7: TELEVENTAS | CM7: ATENTO COLOMBIA S.A. | CN7: CANAL ON LINE - ATENTO OUT BOUND | CT7: 3 | CU7: BA + LB + IPTV | CW7: MTotal_Trio_Voz Ilim Nal _Ba Ancha 900Mbps_IPTV_2_Decos_Mov Ilim_Nac_25425 | CX7: 25425 | DA7: SV | DB7: -1 | DF7: ALTA | DJ7: 900000 | DK7: Cliente Nuevo | DL7: Cliente Nuevo | DN7: TRIO | DR7: bnsierraro | DS7: BRAYAN NICOLAS SIERRA RODRIGUEZ | DT7: 1015443152 | DV7: 1 | DW7: BOGOTA | ED7: 46143 | EE7: Sur | EF7: 5 | EP7: 830065842-5 | ES7: 63 | EZ7: OLT#10.37.80.14 | FA7: CANAL ONLINE | FB7: Bogotá D.C | FD7: Bogotá D.C | FE7: Bogotá | FF7: Bogotá | FK7: ATENTO | FL7: 11001000158059110656999|11001000_158059110_CT6/7-32-20 | FN7: CANAL ON LINE - ATENTO OUT BOUND | FO7: 9900202020034 | FR7: 113904 | GB7: PON | GC7: BA + LB + IPTV | GD7: 25188 | GF7: 2353 | GG7: 25422 | GI7: 87224 | GJ7: 25427 | GL7: 24327 | GM7: 135545 | GS7: FS | GT7: 45716 | GU7: CENTRO EXP | GW7: Si | GX7: SV | GY7: Convergente Solo Contrato | GZ7: Convergente Nuevo | HA7: ATP | HC7: BOGOTA | HE7: Individual | HF7: 462074145 | HG7: Venta mismo mes (F+M) diferente Canal_diferente Al | HH7: 52976181 | HI7: 1. Radicadas | HJ7: 46145 | HK7: CENTROS DE EXPERIENCIA | HL7: CENTROS DE EXPERIENCIA | HM7: 9900100010031 | HN7: CE BOGOTA PLAZA DE LAS AMERICAS | HO7: JHON FREDY PARADA ALVAREZ | HP7: 1032368879 | HR7: Asistido | HV7: 118900 | HW7: SI | HX7: Radicada - No nato igual a NO | HY7: 131572 | HZ7: 17668 | IA7: SI | IB7: NO | IE7: BOGOTA | IF7: BOGOTA | IG7: BOGOTA | IH7: Digital | II7: Fibra | IJ7: B2C | IK7: Asistido | IL7: Outbound | IM7: Atento | IN7: Alta | IP7: - | IQ7: Digital | IS7: ELECTRONICA | IT7: Inbound | IY7: SI
A8: =DAY(AVANZA[[#This Row],[FechaSeguimiento]]) -> 1 | B8: =MONTH(AVANZA[[#This Row],[FechaSeguimiento]]) -> 5 | C8: =LOWER(IF(AND(AVANZA[[#This Row],[Mes_Reg]]=MONTH(TODAY()),AND(AVANZA[[#This Row],[Dia_Reg]]>0,AVANZA[[#This Row],[Dia_Reg]]<9)),"SEMANA 1","")&IF(AND(AVANZA[[#This Row],[Mes_Reg]]=MONTH(TODAY()),AND(AVANZA[[#This Row],[Dia_Reg]]>8,AVANZA[[#This Row],[Dia_Reg]]<16)),"SEMANA 2","")&IF(AND(AVANZA[[#This Row],[Mes_Reg]]=MONTH(TODAY()),AND(AVANZA[[#This Row],[Dia_Reg]]>15,AVANZA[[#This Row],[Dia_Reg]]<23)),"SEMANA 3","")&IF(AND(AVANZA[[#This Row],[Mes_Reg]]=MONTH(TODAY()),AND(AVANZA[[#This Row],[Dia_Reg]]>22,AVANZA[[#This Row],[Dia_Reg]]<31)),"SEMANA 4","")&IF(AVANZA[[#This Row],[Mes_Reg]]<>MONTH(TODAY()),"BOLSA MES ANTERIOR","")) -> bolsa mes anterior | D8: =LOWER(IFERROR(VLOOKUP(AVANZA[[#This Row],[ID_Peticion]],CANCELADAS[#All],2,0),"")) -> carrusel | E8: =LOWER(IFERROR(VLOOKUP(AVANZA[[#This Row],[ID_Peticion]],CANCELADAS[#All],3,0),"")) -> carrusel | F8: =LOWER(IF(AVANZA[[#This Row],[CEDULA CLIENTE]]<>""," CC: " & COUNTIFS(AVANZA[CEDULA CLIENTE],AVANZA[[#This Row],[CEDULA CLIENTE]]),"")& IF(AVANZA[[#This Row],[Direccion]]<>""," DIR: " & COUNTIFS(AVANZA[Direccion],AVANZA[[#This Row],[Direccion]]),"")) -> dir: 1 | G8: =IFERROR(VLOOKUP(AVANZA[[#This Row],[Cedula_Vendedor_Atis]],PLANTA[[#All],[CEDULA]:[LINEA]],3,0),"No Cruza") -> Marisol Avella | H8: =IFERROR(VLOOKUP(AVANZA[[#This Row],[Cedula_Vendedor_Atis]],PLANTA[[#All],[CEDULA]:[LINEA]],4,0),"No Cruza") -> Fija | I8: =LOWER(IF(AVANZA[[#This Row],[ATRIBUIBLE]]="",AVANZA[[#This Row],[Variable]],AVANZA[[#This Row],[ATRIBUIBLE]])) -> carrusel | J8: =IF(AVANZA[[#This Row],[Variable]]=AVANZA[[#Headers],[TERMINADA]],1,0) -> 0 | K8: =IF(AVANZA[[#This Row],[Variable]]=AVANZA[[#Headers],[ANULADA]],1,0) -> 1 | L8: =IF(AVANZA[[#This Row],[Variable]]=AVANZA[[#Headers],[PENDIENTE]],1,0) -> 0 | M8: =IF(AVANZA[[#This Row],[ESTADO AGENDA]]="AGENDADA",1,0) -> 0 | N8: =IF(AVANZA[[#This Row],[ESTADO AGENDA]]="PENDIENTE DE AGENDAR",1,0) -> 0 | O8: =IF(AVANZA[[#This Row],[ESTADO AGENDA]]="SUSPENDIDA",1,0) -> 0 | P8: {=_xlfn.XLOOKUP(AVANZA[[#This Row],[Num_Agrupacion_Pet_Atis]],Tabla1[[#All],[Numero_de_actuacion]],Tabla1[[#All],[Estado_de_la_orden]],"",0)} | Q8: {=_xlfn.XLOOKUP(AVANZA[[#This Row],[Num_Agrupacion_Pet_Atis]],Tabla1[[#All],[Numero_de_actuacion]],Tabla1[[#All],[Fecha_de_la_cita]],"",0)} | R8: {=_xlfn.XLOOKUP(AVANZA[[#This Row],[Num_Agrupacion_Pet_Atis]],Tabla1[[#All],[Numero_de_actuacion]],Tabla1[[#All],[Franja_horaria_de_la_cita]],"",0)} | S8: =IFERROR(DAY(AVANZA[[#This Row],[FECHA AGENDA]]),"") | T8: =IFERROR(MONTH(AVANZA[[#This Row],[FECHA AGENDA]]),"") | U8: {=_xlfn.XLOOKUP(AVANZA[[#This Row],[Num_Agrupacion_Pet_Atis]],Tabla1[[#All],[Numero_de_actuacion]],Tabla1[[#All],[Motivo_de_suspension]],"",0)} | V8: {=_xlfn.XLOOKUP(AVANZA[[#This Row],[Num_Agrupacion_Pet_Atis]],Tabla1[[#All],[Numero_de_actuacion]],Tabla1[[#All],[No_identificacion_cliente]],"",0)} | W8: {=_xlfn.XLOOKUP(AVANZA[[#This Row],[Num_Agrupacion_Pet_Atis]],Tabla1[[#All],[Numero_de_actuacion]],Tabla1[[#All],[Movil_de_contacto]],"",0)} | X8: =IF(OR(AVANZA[[#This Row],[ESTADO LEG]]="Legalizada grabacion",AVANZA[[#This Row],[ESTADO LEG]]="Legalizada aut"),1,0) -> 0 | Y8: =IF(OR(AVANZA[[#This Row],[ESTADO LEG]]="pdte legalizar",AVANZA[[#This Row],[ESTADO LEG]]="No cruza"),1,0) -> 0 | Z8: {=IF(AVANZA[[#This Row],[Variable]]="Terminada",LOWER(_xlfn.XLOOKUP(AVANZA[[#This Row],[ID_Peticion]],Tabla6[[#All],[NUM_PETICION]],Tabla6[[#All],[ESTADO_LEG]],"NO CRUZA",0)),AVANZA[[#This Row],[Variable]])} -> ANULADA | AA8: {=_xlfn.XLOOKUP(AVANZA[[#This Row],[ID_Peticion]],Tabla6[[#All],[NUM_PETICION]],Tabla6[[#All],[DIF_DIAS]],"",0)} | AB8: {=IFERROR(_xlfn.XLOOKUP(AVANZA[[#This Row],[ID_Peticion]],Tabla6[[#All],[NUM_PETICION]],Tabla6[[#All],[FEC_LEGAL]],"",0),"")} | AC8: =IF(AVANZA[[#This Row],[FECHA LEG]]<>0,IFERROR(AVANZA[[#This Row],[FECHA LEG]]-AVANZA[[#This Row],[FechaIniEstadoSubPetAtis]],0),TODAY()-AVANZA[[#This Row],[FechaIniEstadoSubPetAtis]]) -> 0 | AD8: =IF(AVANZA[[#This Row],[FINAL Vs LG]]<>0,IF(AVANZA[[#This Row],[FINAL Vs LG]]<7.1,"100%",IF(AND(AVANZA[[#This Row],[FINAL Vs LG]]>7.1,AVANZA[[#This Row],[FINAL Vs LG]]<11.1),"50%","0%")),0) -> 0 | AE8: =VLOOKUP(DAY(TODAY()),BACK!F:G,2,0) -> 14 | AF8: =BACK!$I$2 -> 24 | AG8: =IF(AVANZA[[#This Row],[Oferta_empaquetada_comisiones]]="SI",1,0) -> 0 | AH8: =IF(AVANZA[[#This Row],[Variable]]="TERMINADA",IFERROR(VLOOKUP(AVANZA[[#This Row],[SUPERVISOR]],Tabla2[#All],4,0),0),) -> 0 | AI8: =IF(AVANZA[[#This Row],[Producto]]="BA",1,0) -> 0 | AJ8: =IF(AVANZA[[#This Row],[Producto]]="DUO",1,0) -> 0 | AK8: =IF(AVANZA[[#This Row],[Producto]]="TRIO",1,0) -> 1 | AL8: 53061857 | AM8: -1 | AN8: -1 | AO8: 1785741102 | AP8: 46142.678 | AQ8: -1 | AR8: 2512690158 | AS8: -1 | AT8: -1 | AU8: -1 | AV8: -1 | AW8: -1 | AX8: FixedCreateSubscriber | AY8: -1 | AZ8: 2026 | BA8: 5 | BB8: 1 | BC8: -1 | BD8: Broadband Service | BE8: -1 | BF8: 20001620825343 | BG8: Convergente_Plan Ancha 900Mbps_Mov Ilim_Trio_25422 | BH8: 25422 | BJ8: -1 | BK8: -1 | BL8: -1 | BM8: ANULADA | BN8: Individual | BO8: 6108770235 | BP8: Gold | BQ8: 2026 | BR8: 4 | BS8: 30 | BT8: 46143.414 | BU8: OS80 | BV8: 46143 | BW8: Cancelled | CA8: DISTRITO ESPECIAL, INDUSTRIAL Y PORTUARIO DE BARRANQUILLA | CB8: ATLANTICO | CC8: KR 8 F CL 130-33 URB CIUDAD CARIBE 33 LAT:10.953894 LON:-74.85522699 | CD8: URB CIUDAD CARIBE | CE8: -1 | CF8: 08001000 | CG8: Atlantico | CH8: ATACANTE | CI8: 53061857 | CJ8: NOHORA AMADO LONDONO | CK8: CANAL ONLINE | CL8: ON LINE | CM8: ATENTO COLOMBIA S.A. | CN8: CANAL ON LINE - ATENTO CLICK TO CALL | CT8: 1 | CU8: BA + LB + IPTV | CW8: MTotal_Trio_Voz Ilim Nal _Ba Ancha 900Mbps_IPTV_2_Decos_Mov Ilim_Nac_25425 | CX8: 25425 | CY8: Anulada fraude marcada por campo remark | DA8: SV | DB8: -1 | DF8: ANULADA FRAUDE - REMARK | DJ8: 900000 | DK8: Cliente Nuevo | DL8: Cliente Nuevo | DN8: TRIO | DR8: namadolo | DS8: NOHORA AMADO LONDONO | DT8: 53061857 | DV8: 1 | DW8: CARIBE | ED8: 46143 | EF8: 9 | EP8: 830065842-5 | FA8: CANAL ONLINE | FB8: Atlántico | FD8: Atlántico | FE8: Barranquilla | FF8: Distrito Especial, Industrial Y Portuario De Barranquilla | FK8: ATENTO | FN8: CANAL ON LINE - ATENTO CLICK TO CALL | FO8: 9900202020033 | FR8: 0 | GB8: PON | GM8: 0 | GS8: FS | GU8: CENTRO EXP | GV8: VALIDADO | GW8: No | GZ8: No Convergente | HE8: Individual | HF8: 1095074855 | HR8: Asistido | HV8: 118900 | HW8: SI | HY8: 0 | HZ8: 0 | IA8: SI | IB8: NO | IC8: The Fraud order (Carrusel) is cancelled by SOM. | IE8: BOGOTA | IF8: BOGOTA | IG8: BOGOTA | IH8: Digital | II8: Fibra | IJ8: B2C | IK8: Asistido | IL8: C2C | IM8: Atento | IN8: - | IP8: - | IQ8: Digital | IS8: ELECTRONICA | IT8: Organico | IW8: Fibra-Fibra-web-CajadeProducto-LP_Hogar_Trio | IY8: NO
A9: =DAY(AVANZA[[#This Row],[FechaSeguimiento]]) -> 1 | B9: =MONTH(AVANZA[[#This Row],[FechaSeguimiento]]) -> 5 | C9: =LOWER(IF(AND(AVANZA[[#This Row],[Mes_Reg]]=MONTH(TODAY()),AND(AVANZA[[#This Row],[Dia_Reg]]>0,AVANZA[[#This Row],[Dia_Reg]]<9)),"SEMANA 1","")&IF(AND(AVANZA[[#This Row],[Mes_Reg]]=MONTH(TODAY()),AND(AVANZA[[#This Row],[Dia_Reg]]>8,AVANZA[[#This Row],[Dia_Reg]]<16)),"SEMANA 2","")&IF(AND(AVANZA[[#This Row],[Mes_Reg]]=MONTH(TODAY()),AND(AVANZA[[#This Row],[Dia_Reg]]>15,AVANZA[[#This Row],[Dia_Reg]]<23)),"SEMANA 3","")&IF(AND(AVANZA[[#This Row],[Mes_Reg]]=MONTH(TODAY()),AND(AVANZA[[#This Row],[Dia_Reg]]>22,AVANZA[[#This Row],[Dia_Reg]]<31)),"SEMANA 4","")&IF(AVANZA[[#This Row],[Mes_Reg]]<>MONTH(TODAY()),"BOLSA MES ANTERIOR","")) -> bolsa mes anterior | D9: =LOWER(IFERROR(VLOOKUP(AVANZA[[#This Row],[ID_Peticion]],CANCELADAS[#All],2,0),"")) | E9: =LOWER(IFERROR(VLOOKUP(AVANZA[[#This Row],[ID_Peticion]],CANCELADAS[#All],3,0),"")) | F9: =LOWER(IF(AVANZA[[#This Row],[CEDULA CLIENTE]]<>""," CC: " & COUNTIFS(AVANZA[CEDULA CLIENTE],AVANZA[[#This Row],[CEDULA CLIENTE]]),"")& IF(AVANZA[[#This Row],[Direccion]]<>""," DIR: " & COUNTIFS(AVANZA[Direccion],AVANZA[[#This Row],[Direccion]]),"")) -> dir: 1 | G9: =IFERROR(VLOOKUP(AVANZA[[#This Row],[Cedula_Vendedor_Atis]],PLANTA[[#All],[CEDULA]:[LINEA]],3,0),"No Cruza") -> Marisol Avella | H9: =IFERROR(VLOOKUP(AVANZA[[#This Row],[Cedula_Vendedor_Atis]],PLANTA[[#All],[CEDULA]:[LINEA]],4,0),"No Cruza") -> Fija | I9: =LOWER(IF(AVANZA[[#This Row],[ATRIBUIBLE]]="",AVANZA[[#This Row],[Variable]],AVANZA[[#This Row],[ATRIBUIBLE]])) -> terminada | J9: =IF(AVANZA[[#This Row],[Variable]]=AVANZA[[#Headers],[TERMINADA]],1,0) -> 1 | K9: =IF(AVANZA[[#This Row],[Variable]]=AVANZA[[#Headers],[ANULADA]],1,0) -> 0 | L9: =IF(AVANZA[[#This Row],[Variable]]=AVANZA[[#Headers],[PENDIENTE]],1,0) -> 0 | M9: =IF(AVANZA[[#This Row],[ESTADO AGENDA]]="AGENDADA",1,0) -> 0 | N9: =IF(AVANZA[[#This Row],[ESTADO AGENDA]]="PENDIENTE DE AGENDAR",1,0) -> 0 | O9: =IF(AVANZA[[#This Row],[ESTADO AGENDA]]="SUSPENDIDA",1,0) -> 0 | P9: {=_xlfn.XLOOKUP(AVANZA[[#This Row],[Num_Agrupacion_Pet_Atis]],Tabla1[[#All],[Numero_de_actuacion]],Tabla1[[#All],[Estado_de_la_orden]],"",0)} | Q9: {=_xlfn.XLOOKUP(AVANZA[[#This Row],[Num_Agrupacion_Pet_Atis]],Tabla1[[#All],[Numero_de_actuacion]],Tabla1[[#All],[Fecha_de_la_cita]],"",0)} | R9: {=_xlfn.XLOOKUP(AVANZA[[#This Row],[Num_Agrupacion_Pet_Atis]],Tabla1[[#All],[Numero_de_actuacion]],Tabla1[[#All],[Franja_horaria_de_la_cita]],"",0)} | S9: =IFERROR(DAY(AVANZA[[#This Row],[FECHA AGENDA]]),"") | T9: =IFERROR(MONTH(AVANZA[[#This Row],[FECHA AGENDA]]),"") | U9: {=_xlfn.XLOOKUP(AVANZA[[#This Row],[Num_Agrupacion_Pet_Atis]],Tabla1[[#All],[Numero_de_actuacion]],Tabla1[[#All],[Motivo_de_suspension]],"",0)} | V9: {=_xlfn.XLOOKUP(AVANZA[[#This Row],[Num_Agrupacion_Pet_Atis]],Tabla1[[#All],[Numero_de_actuacion]],Tabla1[[#All],[No_identificacion_cliente]],"",0)} | W9: {=_xlfn.XLOOKUP(AVANZA[[#This Row],[Num_Agrupacion_Pet_Atis]],Tabla1[[#All],[Numero_de_actuacion]],Tabla1[[#All],[Movil_de_contacto]],"",0)} | X9: =IF(OR(AVANZA[[#This Row],[ESTADO LEG]]="Legalizada grabacion",AVANZA[[#This Row],[ESTADO LEG]]="Legalizada aut"),1,0) -> 1 | Y9: =IF(OR(AVANZA[[#This Row],[ESTADO LEG]]="pdte legalizar",AVANZA[[#This Row],[ESTADO LEG]]="No cruza"),1,0) -> 0 | Z9: {=IF(AVANZA[[#This Row],[Variable]]="Terminada",LOWER(_xlfn.XLOOKUP(AVANZA[[#This Row],[ID_Peticion]],Tabla6[[#All],[NUM_PETICION]],Tabla6[[#All],[ESTADO_LEG]],"NO CRUZA",0)),AVANZA[[#This Row],[Variable]])} -> legalizada grabacion | AA9: {=_xlfn.XLOOKUP(AVANZA[[#This Row],[ID_Peticion]],Tabla6[[#All],[NUM_PETICION]],Tabla6[[#All],[DIF_DIAS]],"",0)} -> 4 | AB9: {=IFERROR(_xlfn.XLOOKUP(AVANZA[[#This Row],[ID_Peticion]],Tabla6[[#All],[NUM_PETICION]],Tabla6[[#All],[FEC_LEGAL]],"",0),"")} -> 46147 | AC9: =IF(AVANZA[[#This Row],[FECHA LEG]]<>0,IFERROR(AVANZA[[#This Row],[FECHA LEG]]-AVANZA[[#This Row],[FechaIniEstadoSubPetAtis]],0),TODAY()-AVANZA[[#This Row],[FechaIniEstadoSubPetAtis]]) -> 4 | AD9: =IF(AVANZA[[#This Row],[FINAL Vs LG]]<>0,IF(AVANZA[[#This Row],[FINAL Vs LG]]<7.1,"100%",IF(AND(AVANZA[[#This Row],[FINAL Vs LG]]>7.1,AVANZA[[#This Row],[FINAL Vs LG]]<11.1),"50%","0%")),0) -> 100% | AE9: =VLOOKUP(DAY(TODAY()),BACK!F:G,2,0) -> 14 | AF9: =BACK!$I$2 -> 24 | AG9: =IF(AVANZA[[#This Row],[Oferta_empaquetada_comisiones]]="SI",1,0) -> 0 | AH9: =IF(AVANZA[[#This Row],[Variable]]="TERMINADA",IFERROR(VLOOKUP(AVANZA[[#This Row],[SUPERVISOR]],Tabla2[#All],4,0),0),) -> 3.5 | AI9: =IF(AVANZA[[#This Row],[Producto]]="BA",1,0) -> 1 | AJ9: =IF(AVANZA[[#This Row],[Producto]]="DUO",1,0) -> 0 | AK9: =IF(AVANZA[[#This Row],[Producto]]="TRIO",1,0) -> 0 | AL9: 1760282673650856597 | AM9: -1 | AN9: -1 | AO9: 1785003360 | AP9: 46141.786 | AQ9: -1 | AR9: 2512688178 | AS9: -1 | AT9: -1 | AU9: -1 | AV9: -1 | AW9: -1 | AX9: FixedCreateSubscriber | AY9: -1 | AZ9: 2026 | BA9: 5 | BB9: 1 | BC9: -1 | BD9: Broadband Service | BE9: -1 | BF9: 20001620138602 | BG9: Plan Banda Ancha 900Mbps Solo Internet_Nac_25423 | BH9: 25423 | BI9: FS202604291851090953 | BJ9: -1 | BK9: -1 | BL9: -1 | BM9: TERMINADA | BN9: Individual | BO9: 6108761445 | BP9: Gold | BQ9: 2026 | BR9: 4 | BS9: 29 | BT9: 46143.537 | BU9: OS90 | BV9: 46143 | BW9: Completed | BX9: 46141 | BY9: 46143 | BZ9: Call Back To CRM | CA9: BOGOTA, D.C. | CB9: BOGOTA, D.C. | CC9: KR 14 CL 90-16 EL CHICO 16 LAT:4.672646 LON:-74.05154415 | CD9: EL CHICO | CE9: -1 | CF9: 11001000 | CG9: Bogota | CH9: ATACANTE | CI9: 1022940376 | CJ9: DAVID ALEJANDRO SUAREZ LOZADA | CK9: CANAL ONLINE | CL9: TELEVENTAS | CM9: ATENTO COLOMBIA S.A. | CN9: CANAL ON LINE - ATENTO OUT BOUND | CT9: 6 | CU9: Broadband Service | CW9: Plan Banda Ancha 900Mbps Solo Internet_Nac_25423 | CX9: 25423 | DA9: SV | DB9: -1 | DF9: ALTA | DJ9: 900000 | DK9: Cliente Nuevo | DL9: Cliente Existente | DN9: BA | DR9: dsuarezlo2 | DS9: DAVID ALEJANDRO SUAREZ LOZADA | DT9: 1022940376 | DV9: 1 | DW9: BOGOTA | ED9: 46143 | EE9: Norte | EF9: 5 | EP9: 830065842-5 | ES9: 7 | EZ9: OLT#10.37.70.2 | FA9: CANAL ONLINE | FB9: Bogotá D.C | FD9: Bogotá D.C | FE9: Bogotá | FF9: Bogotá | FK9: ATENTO | FL9: 11001000104580037103450|11001000_103450_CT2-18-13 | FN9: CANAL ON LINE - ATENTO OUT BOUND | FO9: 9900202020034 | FR9: 79824 | GB9: PON | GC9: Broadband Service | GD9: 0 | GF9: 0 | GG9: 25423 | GI9: 79824 | GJ9: 0 | GL9: 0 | GM9: 94990 | GS9: FS | GT9: 44012 | GU9: CENTRO EXP | GV9: VALIDADO | GW9: No | GZ9: No Convergente | HA9: ATC | HC9: BOGOTA 4 | HE9: Individual | HF9: 467074050 | HR9: Asistido | HV9: 94990 | HW9: NO | HY9: 0 | HZ9: 0 | IA9: NO | IB9: NO | IE9: BOGOTA | IF9: BOGOTA | IG9: BOGOTA | IH9: Digital | II9: Fibra | IJ9: B2C | IK9: Asistido | IL9: Outbound | IM9: Atento | IN9: Alta | IP9: - | IQ9: Digital | IS9: ELECTRONICA | IT9: Googleads_Oferta | IU9: CO_MARCA_COL-PUREBRAND-B2C_22-02-16_SEM_LDS-WEB_AON_RMKT_BRAND | IV9: SEM_SEM_CPL | IW9: Fija-Fibra-web-CajadeProducto-LP-pauta-fibra | IY9: NO
A10: =DAY(AVANZA[[#This Row],[FechaSeguimiento]]) -> 1 | B10: =MONTH(AVANZA[[#This Row],[FechaSeguimiento]]) -> 5 | C10: =LOWER(IF(AND(AVANZA[[#This Row],[Mes_Reg]]=MONTH(TODAY()),AND(AVANZA[[#This Row],[Dia_Reg]]>0,AVANZA[[#This Row],[Dia_Reg]]<9)),"SEMANA 1","")&IF(AND(AVANZA[[#This Row],[Mes_Reg]]=MONTH(TODAY()),AND(AVANZA[[#This Row],[Dia_Reg]]>8,AVANZA[[#This Row],[Dia_Reg]]<16)),"SEMANA 2","")&IF(AND(AVANZA[[#This Row],[Mes_Reg]]=MONTH(TODAY()),AND(AVANZA[[#This Row],[Dia_Reg]]>15,AVANZA[[#This Row],[Dia_Reg]]<23)),"SEMANA 3","")&IF(AND(AVANZA[[#This Row],[Mes_Reg]]=MONTH(TODAY()),AND(AVANZA[[#This Row],[Dia_Reg]]>22,AVANZA[[#This Row],[Dia_Reg]]<31)),"SEMANA 4","")&IF(AVANZA[[#This Row],[Mes_Reg]]<>MONTH(TODAY()),"BOLSA MES ANTERIOR","")) -> bolsa mes anterior | D10: =LOWER(IFERROR(VLOOKUP(AVANZA[[#This Row],[ID_Peticion]],CANCELADAS[#All],2,0),"")) | E10: =LOWER(IFERROR(VLOOKUP(AVANZA[[#This Row],[ID_Peticion]],CANCELADAS[#All],3,0),"")) | F10: =LOWER(IF(AVANZA[[#This Row],[CEDULA CLIENTE]]<>""," CC: " & COUNTIFS(AVANZA[CEDULA CLIENTE],AVANZA[[#This Row],[CEDULA CLIENTE]]),"")& IF(AVANZA[[#This Row],[Direccion]]<>""," DIR: " & COUNTIFS(AVANZA[Direccion],AVANZA[[#This Row],[Direccion]]),"")) -> dir: 1 | G10: =IFERROR(VLOOKUP(AVANZA[[#This Row],[Cedula_Vendedor_Atis]],PLANTA[[#All],[CEDULA]:[LINEA]],3,0),"No Cruza") -> Marisol Avella | H10: =IFERROR(VLOOKUP(AVANZA[[#This Row],[Cedula_Vendedor_Atis]],PLANTA[[#All],[CEDULA]:[LINEA]],4,0),"No Cruza") -> Fija | I10: =LOWER(IF(AVANZA[[#This Row],[ATRIBUIBLE]]="",AVANZA[[#This Row],[Variable]],AVANZA[[#This Row],[ATRIBUIBLE]])) -> terminada | J10: =IF(AVANZA[[#This Row],[Variable]]=AVANZA[[#Headers],[TERMINADA]],1,0) -> 1 | K10: =IF(AVANZA[[#This Row],[Variable]]=AVANZA[[#Headers],[ANULADA]],1,0) -> 0 | L10: =IF(AVANZA[[#This Row],[Variable]]=AVANZA[[#Headers],[PENDIENTE]],1,0) -> 0 | M10: =IF(AVANZA[[#This Row],[ESTADO AGENDA]]="AGENDADA",1,0) -> 0 | N10: =IF(AVANZA[[#This Row],[ESTADO AGENDA]]="PENDIENTE DE AGENDAR",1,0) -> 0 | O10: =IF(AVANZA[[#This Row],[ESTADO AGENDA]]="SUSPENDIDA",1,0) -> 0 | P10: {=_xlfn.XLOOKUP(AVANZA[[#This Row],[Num_Agrupacion_Pet_Atis]],Tabla1[[#All],[Numero_de_actuacion]],Tabla1[[#All],[Estado_de_la_orden]],"",0)} | Q10: {=_xlfn.XLOOKUP(AVANZA[[#This Row],[Num_Agrupacion_Pet_Atis]],Tabla1[[#All],[Numero_de_actuacion]],Tabla1[[#All],[Fecha_de_la_cita]],"",0)} | R10: {=_xlfn.XLOOKUP(AVANZA[[#This Row],[Num_Agrupacion_Pet_Atis]],Tabla1[[#All],[Numero_de_actuacion]],Tabla1[[#All],[Franja_horaria_de_la_cita]],"",0)} | S10: =IFERROR(DAY(AVANZA[[#This Row],[FECHA AGENDA]]),"") | T10: =IFERROR(MONTH(AVANZA[[#This Row],[FECHA AGENDA]]),"") | U10: {=_xlfn.XLOOKUP(AVANZA[[#This Row],[Num_Agrupacion_Pet_Atis]],Tabla1[[#All],[Numero_de_actuacion]],Tabla1[[#All],[Motivo_de_suspension]],"",0)} | V10: {=_xlfn.XLOOKUP(AVANZA[[#This Row],[Num_Agrupacion_Pet_Atis]],Tabla1[[#All],[Numero_de_actuacion]],Tabla1[[#All],[No_identificacion_cliente]],"",0)} | W10: {=_xlfn.XLOOKUP(AVANZA[[#This Row],[Num_Agrupacion_Pet_Atis]],Tabla1[[#All],[Numero_de_actuacion]],Tabla1[[#All],[Movil_de_contacto]],"",0)} | X10: =IF(OR(AVANZA[[#This Row],[ESTADO LEG]]="Legalizada grabacion",AVANZA[[#This Row],[ESTADO LEG]]="Legalizada aut"),1,0) -> 1 | Y10: =IF(OR(AVANZA[[#This Row],[ESTADO LEG]]="pdte legalizar",AVANZA[[#This Row],[ESTADO LEG]]="No cruza"),1,0) -> 0 | Z10: {=IF(AVANZA[[#This Row],[Variable]]="Terminada",LOWER(_xlfn.XLOOKUP(AVANZA[[#This Row],[ID_Peticion]],Tabla6[[#All],[NUM_PETICION]],Tabla6[[#All],[ESTADO_LEG]],"NO CRUZA",0)),AVANZA[[#This Row],[Variable]])} -> legalizada grabacion | AA10: {=_xlfn.XLOOKUP(AVANZA[[#This Row],[ID_Peticion]],Tabla6[[#All],[NUM_PETICION]],Tabla6[[#All],[DIF_DIAS]],"",0)} -> 4 | AB10: {=IFERROR(_xlfn.XLOOKUP(AVANZA[[#This Row],[ID_Peticion]],Tabla6[[#All],[NUM_PETICION]],Tabla6[[#All],[FEC_LEGAL]],"",0),"")} -> 46147 | AC10: =IF(AVANZA[[#This Row],[FECHA LEG]]<>0,IFERROR(AVANZA[[#This Row],[FECHA LEG]]-AVANZA[[#This Row],[FechaIniEstadoSubPetAtis]],0),TODAY()-AVANZA[[#This Row],[FechaIniEstadoSubPetAtis]]) -> 4 | AD10: =IF(AVANZA[[#This Row],[FINAL Vs LG]]<>0,IF(AVANZA[[#This Row],[FINAL Vs LG]]<7.1,"100%",IF(AND(AVANZA[[#This Row],[FINAL Vs LG]]>7.1,AVANZA[[#This Row],[FINAL Vs LG]]<11.1),"50%","0%")),0) -> 100% | AE10: =VLOOKUP(DAY(TODAY()),BACK!F:G,2,0) -> 14 | AF10: =BACK!$I$2 -> 24 | AG10: =IF(AVANZA[[#This Row],[Oferta_empaquetada_comisiones]]="SI",1,0) -> 0 | AH10: =IF(AVANZA[[#This Row],[Variable]]="TERMINADA",IFERROR(VLOOKUP(AVANZA[[#This Row],[SUPERVISOR]],Tabla2[#All],4,0),0),) -> 3.5 | AI10: =IF(AVANZA[[#This Row],[Producto]]="BA",1,0) -> 0 | AJ10: =IF(AVANZA[[#This Row],[Producto]]="DUO",1,0) -> 0 | AK10: =IF(AVANZA[[#This Row],[Producto]]="TRIO",1,0) -> 1 | AL10: 53061857 | AM10: -1 | AN10: -1 | AO10: 1784946246 | AP10: 46141.683 | AQ10: -1 | AR10: 2512687376 | AS10: -1 | AT10: -1 | AU10: -1 | AV10: -1 | AW10: -1 | AX10: FixedCreateSubscriber | AY10: -1 | AZ10: 2026 | BA10: 5 | BB10: 1 | BC10: -1 | BD10: Broadband Service | BE10: -1 | BF10: 20001620119110 | BG10: Plan Banda Ancha 900Mbps_IPTV_1_Decos_Trio_25424 | BH10: 25424 | BI10: FS202604291620351345 | BJ10: -1 | BK10: -1 | BL10: -1 | BM10: TERMINADA | BN10: Individual | BO10: 6108766297 | BP10: Gold | BQ10: 2026 | BR10: 4 | BS10: 29 | BT10: 46143.53 | BU10: OS90 | BV10: 46143 | BW10: Completed | BX10: 46142 | BY10: 46143 | BZ10: Call Back To CRM | CA10: BOGOTA, D.C. | CB10: BOGOTA, D.C. | CC10: KR 13 CL 118-48 SANTA BARBARA CENTR 48 LCA 1 LAT:4.69775148 LON:-74.03962925 | CD10: SANTA BARBARA CENTR | CE10: -1 | CF10: 11001000 | CG10: Bogota | CH10: ATACANTE | CI10: 53061857 | CJ10: NOHORA AMADO LONDONO | CK10: CANAL ONLINE | CL10: ON LINE | CM10: ATENTO COLOMBIA S.A. | CN10: CANAL ON LINE - ATENTO CLICK TO CALL | CT10: 6 | CU10: BA + LB + IPTV | CW10: Trio Voz Ilimitada Nacional 200 Min LDI Banda Ancha 900Mbps_IPTV_1_Decos_Nac_25426 | CX10: 25426 | DA10: SV | DB10: -1 | DF10: ALTA | DJ10: 900000 | DK10: Cliente Nuevo | DL10: Cliente Nuevo | DN10: TRIO | DR10: namadolo | DS10: NOHORA AMADO LONDONO | DT10: 53061857 | DV10: 1 | DW10: BOGOTA | ED10: 46143 | EE10: Norte | EF10: 5 | EP10: 830065842-5 | ES10: 4 | EZ10: OLT#10.37.70.10 | FA10: CANAL ONLINE | FB10: Bogotá D.C | FD10: Bogotá D.C | FE10: Bogotá | FF10: Bogotá | FK10: ATENTO | FL10: 11001000103395425100711|11001000_103395425_CT2-62-03 | FN10: CANAL ON LINE - ATENTO CLICK TO CALL | FO10: 9900202020033 | FR10: 110915 | GB10: PON | GC10: BA + LB + IPTV | GD10: 25016 | GF10: 2353 | GG10: 25424 | GI10: 84235 | GJ10: 25242 | GL10: 24327 | GM10: 131988 | GS10: FS | GT10: 43982 | GU10: CENTRO EXP | GV10: VALIDADO | GW10: No | GZ10: No Convergente | HA10: ATC | HC10: BOGOTA 4 | HE10: Individual | HF10: 469574035 | HR10: Asistido | HV10: 131990 | HW10: NO | HY10: 0 | HZ10: 0 | IA10: SI | IB10: NO | IE10: BOGOTA | IF10: BOGOTA | IG10: BOGOTA | IH10: Digital | II10: Fibra | IJ10: B2C | IK10: Asistido | IL10: C2C | IM10: Atento | IN10: Alta | IP10: - | IQ10: Digital | IS10: ELECTRONICA | IT10: Googleads_Oferta | IU10: CO_MARCA_COL-PUREBRAND-B2C_21-01-01_SEM_LDS-WEB_AON_ABT_BRAND | IV10: SEM_SEM_CPL | IW10: Fija-Fibra-web-CajadeProducto-LP-pauta-fibra | IY10: NO
A11: =DAY(AVANZA[[#This Row],[FechaSeguimiento]]) -> 1 | B11: =MONTH(AVANZA[[#This Row],[FechaSeguimiento]]) -> 5 | C11: =LOWER(IF(AND(AVANZA[[#This Row],[Mes_Reg]]=MONTH(TODAY()),AND(AVANZA[[#This Row],[Dia_Reg]]>0,AVANZA[[#This Row],[Dia_Reg]]<9)),"SEMANA 1","")&IF(AND(AVANZA[[#This Row],[Mes_Reg]]=MONTH(TODAY()),AND(AVANZA[[#This Row],[Dia_Reg]]>8,AVANZA[[#This Row],[Dia_Reg]]<16)),"SEMANA 2","")&IF(AND(AVANZA[[#This Row],[Mes_Reg]]=MONTH(TODAY()),AND(AVANZA[[#This Row],[Dia_Reg]]>15,AVANZA[[#This Row],[Dia_Reg]]<23)),"SEMANA 3","")&IF(AND(AVANZA[[#This Row],[Mes_Reg]]=MONTH(TODAY()),AND(AVANZA[[#This Row],[Dia_Reg]]>22,AVANZA[[#This Row],[Dia_Reg]]<31)),"SEMANA 4","")&IF(AVANZA[[#This Row],[Mes_Reg]]<>MONTH(TODAY()),"BOLSA MES ANTERIOR","")) -> bolsa mes anterior | D11: =LOWER(IFERROR(VLOOKUP(AVANZA[[#This Row],[ID_Peticion]],CANCELADAS[#All],2,0),"")) | E11: =LOWER(IFERROR(VLOOKUP(AVANZA[[#This Row],[ID_Peticion]],CANCELADAS[#All],3,0),"")) | F11: =LOWER(IF(AVANZA[[#This Row],[CEDULA CLIENTE]]<>""," CC: " & COUNTIFS(AVANZA[CEDULA CLIENTE],AVANZA[[#This Row],[CEDULA CLIENTE]]),"")& IF(AVANZA[[#This Row],[Direccion]]<>""," DIR: " & COUNTIFS(AVANZA[Direccion],AVANZA[[#This Row],[Direccion]]),"")) -> dir: 1 | G11: =IFERROR(VLOOKUP(AVANZA[[#This Row],[Cedula_Vendedor_Atis]],PLANTA[[#All],[CEDULA]:[LINEA]],3,0),"No Cruza") -> Marisol Avella | H11: =IFERROR(VLOOKUP(AVANZA[[#This Row],[Cedula_Vendedor_Atis]],PLANTA[[#All],[CEDULA]:[LINEA]],4,0),"No Cruza") -> Fija | I11: =LOWER(IF(AVANZA[[#This Row],[ATRIBUIBLE]]="",AVANZA[[#This Row],[Variable]],AVANZA[[#This Row],[ATRIBUIBLE]])) -> terminada | J11: =IF(AVANZA[[#This Row],[Variable]]=AVANZA[[#Headers],[TERMINADA]],1,0) -> 1 | K11: =IF(AVANZA[[#This Row],[Variable]]=AVANZA[[#Headers],[ANULADA]],1,0) -> 0 | L11: =IF(AVANZA[[#This Row],[Variable]]=AVANZA[[#Headers],[PENDIENTE]],1,0) -> 0 | M11: =IF(AVANZA[[#This Row],[ESTADO AGENDA]]="AGENDADA",1,0) -> 0 | N11: =IF(AVANZA[[#This Row],[ESTADO AGENDA]]="PENDIENTE DE AGENDAR",1,0) -> 0 | O11: =IF(AVANZA[[#This Row],[ESTADO AGENDA]]="SUSPENDIDA",1,0) -> 0 | P11: {=_xlfn.XLOOKUP(AVANZA[[#This Row],[Num_Agrupacion_Pet_Atis]],Tabla1[[#All],[Numero_de_actuacion]],Tabla1[[#All],[Estado_de_la_orden]],"",0)} | Q11: {=_xlfn.XLOOKUP(AVANZA[[#This Row],[Num_Agrupacion_Pet_Atis]],Tabla1[[#All],[Numero_de_actuacion]],Tabla1[[#All],[Fecha_de_la_cita]],"",0)} | R11: {=_xlfn.XLOOKUP(AVANZA[[#This Row],[Num_Agrupacion_Pet_Atis]],Tabla1[[#All],[Numero_de_actuacion]],Tabla1[[#All],[Franja_horaria_de_la_cita]],"",0)} | S11: =IFERROR(DAY(AVANZA[[#This Row],[FECHA AGENDA]]),"") | T11: =IFERROR(MONTH(AVANZA[[#This Row],[FECHA AGENDA]]),"") | U11: {=_xlfn.XLOOKUP(AVANZA[[#This Row],[Num_Agrupacion_Pet_Atis]],Tabla1[[#All],[Numero_de_actuacion]],Tabla1[[#All],[Motivo_de_suspension]],"",0)} | V11: {=_xlfn.XLOOKUP(AVANZA[[#This Row],[Num_Agrupacion_Pet_Atis]],Tabla1[[#All],[Numero_de_actuacion]],Tabla1[[#All],[No_identificacion_cliente]],"",0)} | W11: {=_xlfn.XLOOKUP(AVANZA[[#This Row],[Num_Agrupacion_Pet_Atis]],Tabla1[[#All],[Numero_de_actuacion]],Tabla1[[#All],[Movil_de_contacto]],"",0)} | X11: =IF(OR(AVANZA[[#This Row],[ESTADO LEG]]="Legalizada grabacion",AVANZA[[#This Row],[ESTADO LEG]]="Legalizada aut"),1,0) -> 1 | Y11: =IF(OR(AVANZA[[#This Row],[ESTADO LEG]]="pdte legalizar",AVANZA[[#This Row],[ESTADO LEG]]="No cruza"),1,0) -> 0 | Z11: {=IF(AVANZA[[#This Row],[Variable]]="Terminada",LOWER(_xlfn.XLOOKUP(AVANZA[[#This Row],[ID_Peticion]],Tabla6[[#All],[NUM_PETICION]],Tabla6[[#All],[ESTADO_LEG]],"NO CRUZA",0)),AVANZA[[#This Row],[Variable]])} -> legalizada grabacion | AA11: {=_xlfn.XLOOKUP(AVANZA[[#This Row],[ID_Peticion]],Tabla6[[#All],[NUM_PETICION]],Tabla6[[#All],[DIF_DIAS]],"",0)} -> 4 | AB11: {=IFERROR(_xlfn.XLOOKUP(AVANZA[[#This Row],[ID_Peticion]],Tabla6[[#All],[NUM_PETICION]],Tabla6[[#All],[FEC_LEGAL]],"",0),"")} -> 46147 | AC11: =IF(AVANZA[[#This Row],[FECHA LEG]]<>0,IFERROR(AVANZA[[#This Row],[FECHA LEG]]-AVANZA[[#This Row],[FechaIniEstadoSubPetAtis]],0),TODAY()-AVANZA[[#This Row],[FechaIniEstadoSubPetAtis]]) -> 4 | AD11: =IF(AVANZA[[#This Row],[FINAL Vs LG]]<>0,IF(AVANZA[[#This Row],[FINAL Vs LG]]<7.1,"100%",IF(AND(AVANZA[[#This Row],[FINAL Vs LG]]>7.1,AVANZA[[#This Row],[FINAL Vs LG]]<11.1),"50%","0%")),0) -> 100% | AE11: =VLOOKUP(DAY(TODAY()),BACK!F:G,2,0) -> 14 | AF11: =BACK!$I$2 -> 24 | AG11: =IF(AVANZA[[#This Row],[Oferta_empaquetada_comisiones]]="SI",1,0) -> 0 | AH11: =IF(AVANZA[[#This Row],[Variable]]="TERMINADA",IFERROR(VLOOKUP(AVANZA[[#This Row],[SUPERVISOR]],Tabla2[#All],4,0),0),) -> 3.5 | AI11: =IF(AVANZA[[#This Row],[Producto]]="BA",1,0) -> 1 | AJ11: =IF(AVANZA[[#This Row],[Producto]]="DUO",1,0) -> 0 | AK11: =IF(AVANZA[[#This Row],[Producto]]="TRIO",1,0) -> 0 | AL11: 1526683800046962252 | AM11: -1 | AN11: -1 | AO11: 1774846586 | AP11: 46126.445 | AQ11: -1 | AR11: 2512647869 | AS11: -1 | AT11: -1 | AU11: -1 | AV11: -1 | AW11: -1 | AX11: FixedCreateSubscriber | AY11: -1 | AZ11: 2026 | BA11: 5 | BB11: 1 | BC11: -1 | BD11: Broadband Service | BE11: -1 | BF11: 20001611107095 | BG11: Convergente_MTotal_Single_Voz Ilim Nal _Ba Ancha 900Mbps_Mov Ilim_Nac_25421 | BH11: 25421 | BI11: FS202604141040505598 | BJ11: -1 | BK11: -1 | BL11: -1 | BM11: TERMINADA | BN11: Individual | BO11: 6089834761 | BP11: Movistar Total | BQ11: 2026 | BR11: 4 | BS11: 14 | BT11: 46143.62 | BU11: OS90 | BV11: 46143 | BW11: Completed | BX11: 46126 | BY11: 46143 | BZ11: Call Back To CRM | CA11: DISTRITO ESPECIAL, INDUSTRIAL Y PORTUARIO DE BARRANQUILLA | CB11: ATLANTICO | CC11: CL 69 KR 44-58 COLOMBIA 58 LAT:10.9907883 LON:-74.80242242 | CD11: COLOMBIA | CE11: -1 | CF11: 08001000 | CG11: Atlantico | CH11: ATACANTE | CI11: 73211780 | CJ11: WALTER BERRIO GONZALEZ | CK11: CANAL ONLINE | CL11: ON LINE | CM11: ATENTO COLOMBIA S.A. | CN11: CANAL ON LINE - ATENTO IN BOUND | CT11: 4 | CU11: Broadband Service | CW11: Convergente_MTotal_Single_Voz Ilim Nal _Ba Ancha 900Mbps_Mov Ilim_Nac_25421 | CX11: 25421 | DA11: SV | DB11: -1 | DF11: ALTA | DJ11: 900000 | DK11: Cliente Nuevo | DL11: Cliente Existente | DN11: BA | DR11: wberriogo | DS11: WALTER BERRIO GONZALEZ | DT11: 73211780 | DV11: 1 | DW11: CARIBE | ED11: 46143 | EF11: 23 | EP11: 830065842-5 | ES11: Cluster 7 | FA11: CANAL ONLINE | FB11: Atlántico | FD11: Atlántico | FE11: Barranquilla | FF11: Distrito Especial, Industrial Y Portuario De Barranquilla | FK11: ATENTO | FL11: 8001000OH_ATLHICTRB_I_5800_Barranquilla_Centro_2CENTR-CT7-93-01SS7-93-01@8001000_OH_ATLHICTRB_I_5800_Barranquilla_Centro_2_CENTR-CT7-93-01_SS7-93-01 | FN11: CANAL ON LINE - ATENTO IN BOUND | FO11: 9900202020035 | FR11: 72185 | GB11: PON | GC11: Broadband Service | GD11: 0 | GF11: 0 | GG11: 25421 | GI11: 72185 | GJ11: 0 | GL11: 0 | GM11: 85900 | GS11: FS | GT11: 44895 | GU11: CENTRO EXP | GV11: VALIDADO | GW11: Si | GX11: Solo Movil | GY11: Convergente Solo Contrato | GZ11: Convergente Nuevo | HA11: ONNET | HB11: BARRANQUILLA | HC11: BARRANQUILLA | HD11: CARIBE | HE11: Individual | HF11: 1099074800 | HG11: Venta Hogar (F) a cliente Pospago | HR11: Asistido | HV11: 85900 | HW11: SI | HX11: Migracion Pos-Pos | HY11: 89853 | HZ11: 17668 | IA11: SI | IB11: NO | ID11: >= 120 | IE11: BOGOTA | IF11: BOGOTA | IG11: BOGOTA | IH11: Digital | II11: Fibra | IJ11: B2C | IK11: Asistido | IL11: Inbound | IM11: Atento | IN11: Alta | IP11: - | IQ11: Digital | IS11: ELECTRONICA | IY11: NO
A12: =DAY(AVANZA[[#This Row],[FechaSeguimiento]]) -> 1 | B12: =MONTH(AVANZA[[#This Row],[FechaSeguimiento]]) -> 5 | C12: =LOWER(IF(AND(AVANZA[[#This Row],[Mes_Reg]]=MONTH(TODAY()),AND(AVANZA[[#This Row],[Dia_Reg]]>0,AVANZA[[#This Row],[Dia_Reg]]<9)),"SEMANA 1","")&IF(AND(AVANZA[[#This Row],[Mes_Reg]]=MONTH(TODAY()),AND(AVANZA[[#This Row],[Dia_Reg]]>8,AVANZA[[#This Row],[Dia_Reg]]<16)),"SEMANA 2","")&IF(AND(AVANZA[[#This Row],[Mes_Reg]]=MONTH(TODAY()),AND(AVANZA[[#This Row],[Dia_Reg]]>15,AVANZA[[#This Row],[Dia_Reg]]<23)),"SEMANA 3","")&IF(AND(AVANZA[[#This Row],[Mes_Reg]]=MONTH(TODAY()),AND(AVANZA[[#This Row],[Dia_Reg]]>22,AVANZA[[#This Row],[Dia_Reg]]<31)),"SEMANA 4","")&IF(AVANZA[[#This Row],[Mes_Reg]]<>MONTH(TODAY()),"BOLSA MES ANTERIOR","")) -> bolsa mes anterior | D12: =LOWER(IFERROR(VLOOKUP(AVANZA[[#This Row],[ID_Peticion]],CANCELADAS[#All],2,0),"")) | E12: =LOWER(IFERROR(VLOOKUP(AVANZA[[#This Row],[ID_Peticion]],CANCELADAS[#All],3,0),"")) | F12: =LOWER(IF(AVANZA[[#This Row],[CEDULA CLIENTE]]<>""," CC: " & COUNTIFS(AVANZA[CEDULA CLIENTE],AVANZA[[#This Row],[CEDULA CLIENTE]]),"")& IF(AVANZA[[#This Row],[Direccion]]<>""," DIR: " & COUNTIFS(AVANZA[Direccion],AVANZA[[#This Row],[Direccion]]),"")) -> dir: 1 | G12: =IFERROR(VLOOKUP(AVANZA[[#This Row],[Cedula_Vendedor_Atis]],PLANTA[[#All],[CEDULA]:[LINEA]],3,0),"No Cruza") -> Marisol Avella | H12: =IFERROR(VLOOKUP(AVANZA[[#This Row],[Cedula_Vendedor_Atis]],PLANTA[[#All],[CEDULA]:[LINEA]],4,0),"No Cruza") -> Fija | I12: =LOWER(IF(AVANZA[[#This Row],[ATRIBUIBLE]]="",AVANZA[[#This Row],[Variable]],AVANZA[[#This Row],[ATRIBUIBLE]])) -> terminada | J12: =IF(AVANZA[[#This Row],[Variable]]=AVANZA[[#Headers],[TERMINADA]],1,0) -> 1 | K12: =IF(AVANZA[[#This Row],[Variable]]=AVANZA[[#Headers],[ANULADA]],1,0) -> 0 | L12: =IF(AVANZA[[#This Row],[Variable]]=AVANZA[[#Headers],[PENDIENTE]],1,0) -> 0 | M12: =IF(AVANZA[[#This Row],[ESTADO AGENDA]]="AGENDADA",1,0) -> 0 | N12: =IF(AVANZA[[#This Row],[ESTADO AGENDA]]="PENDIENTE DE AGENDAR",1,0) -> 0 | O12: =IF(AVANZA[[#This Row],[ESTADO AGENDA]]="SUSPENDIDA",1,0) -> 0 | P12: {=_xlfn.XLOOKUP(AVANZA[[#This Row],[Num_Agrupacion_Pet_Atis]],Tabla1[[#All],[Numero_de_actuacion]],Tabla1[[#All],[Estado_de_la_orden]],"",0)} | Q12: {=_xlfn.XLOOKUP(AVANZA[[#This Row],[Num_Agrupacion_Pet_Atis]],Tabla1[[#All],[Numero_de_actuacion]],Tabla1[[#All],[Fecha_de_la_cita]],"",0)} | R12: {=_xlfn.XLOOKUP(AVANZA[[#This Row],[Num_Agrupacion_Pet_Atis]],Tabla1[[#All],[Numero_de_actuacion]],Tabla1[[#All],[Franja_horaria_de_la_cita]],"",0)} | S12: =IFERROR(DAY(AVANZA[[#This Row],[FECHA AGENDA]]),"") | T12: =IFERROR(MONTH(AVANZA[[#This Row],[FECHA AGENDA]]),"") | U12: {=_xlfn.XLOOKUP(AVANZA[[#This Row],[Num_Agrupacion_Pet_Atis]],Tabla1[[#All],[Numero_de_actuacion]],Tabla1[[#All],[Motivo_de_suspension]],"",0)} | V12: {=_xlfn.XLOOKUP(AVANZA[[#This Row],[Num_Agrupacion_Pet_Atis]],Tabla1[[#All],[Numero_de_actuacion]],Tabla1[[#All],[No_identificacion_cliente]],"",0)} | W12: {=_xlfn.XLOOKUP(AVANZA[[#This Row],[Num_Agrupacion_Pet_Atis]],Tabla1[[#All],[Numero_de_actuacion]],Tabla1[[#All],[Movil_de_contacto]],"",0)} | X12: =IF(OR(AVANZA[[#This Row],[ESTADO LEG]]="Legalizada grabacion",AVANZA[[#This Row],[ESTADO LEG]]="Legalizada aut"),1,0) -> 1 | Y12: =IF(OR(AVANZA[[#This Row],[ESTADO LEG]]="pdte legalizar",AVANZA[[#This Row],[ESTADO LEG]]="No cruza"),1,0) -> 0 | Z12: {=IF(AVANZA[[#This Row],[Variable]]="Terminada",LOWER(_xlfn.XLOOKUP(AVANZA[[#This Row],[ID_Peticion]],Tabla6[[#All],[NUM_PETICION]],Tabla6[[#All],[ESTADO_LEG]],"NO CRUZA",0)),AVANZA[[#This Row],[Variable]])} -> legalizada grabacion | AA12: {=_xlfn.XLOOKUP(AVANZA[[#This Row],[ID_Peticion]],Tabla6[[#All],[NUM_PETICION]],Tabla6[[#All],[DIF_DIAS]],"",0)} -> 4 | AB12: {=IFERROR(_xlfn.XLOOKUP(AVANZA[[#This Row],[ID_Peticion]],Tabla6[[#All],[NUM_PETICION]],Tabla6[[#All],[FEC_LEGAL]],"",0),"")} -> 46147 | AC12: =IF(AVANZA[[#This Row],[FECHA LEG]]<>0,IFERROR(AVANZA[[#This Row],[FECHA LEG]]-AVANZA[[#This Row],[FechaIniEstadoSubPetAtis]],0),TODAY()-AVANZA[[#This Row],[FechaIniEstadoSubPetAtis]]) -> 4 | AD12: =IF(AVANZA[[#This Row],[FINAL Vs LG]]<>0,IF(AVANZA[[#This Row],[FINAL Vs LG]]<7.1,"100%",IF(AND(AVANZA[[#This Row],[FINAL Vs LG]]>7.1,AVANZA[[#This Row],[FINAL Vs LG]]<11.1),"50%","0%")),0) -> 100% | AE12: =VLOOKUP(DAY(TODAY()),BACK!F:G,2,0) -> 14 | AF12: =BACK!$I$2 -> 24 | AG12: =IF(AVANZA[[#This Row],[Oferta_empaquetada_comisiones]]="SI",1,0) -> 1 | AH12: =IF(AVANZA[[#This Row],[Variable]]="TERMINADA",IFERROR(VLOOKUP(AVANZA[[#This Row],[SUPERVISOR]],Tabla2[#All],4,0),0),) -> 3.5 | AI12: =IF(AVANZA[[#This Row],[Producto]]="BA",1,0) -> 0 | AJ12: =IF(AVANZA[[#This Row],[Producto]]="DUO",1,0) -> 0 | AK12: =IF(AVANZA[[#This Row],[Producto]]="TRIO",1,0) -> 1 | AL12: 1760282673650856597 | AM12: -1 | AN12: -1 | AO12: 1785795323 | AP12: 46142.749 | AQ12: -1 | AR12: 2512690872 | AS12: -1 | AT12: -1 | AU12: -1 | AV12: -1 | AW12: -1 | AX12: FixedCreateSubscriber | AY12: -1 | AZ12: 2026 | BA12: 5 | BB12: 1 | BC12: -1 | BD12: Broadband Service | BE12: -1 | BF12: 20001620890929 | BG12: Convergente_Plan Ancha 900Mbps_Mov Ilim_Trio_25422 | BH12: 25422 | BI12: FS202604301757571596 | BJ12: -1 | BK12: -1 | BL12: -1 | BM12: TERMINADA | BN12: Individual | BO12: 6108772318 | BP12: Movistar Total | BQ12: 2026 | BR12: 4 | BS12: 30 | BT12: 46143.627 | BU12: OS90 | BV12: 46143 | BW12: Completed | BX12: 46142 | BY12: 46143 | BZ12: Call Back To CRM | CA12: DISTRITO ESPECIAL, INDUSTRIAL Y PORTUARIO DE BARRANQUILLA | CB12: ATLANTICO | CC12: KR 17 B CL 65 C-42 EL VALLE 42 LAT:10.9669331 LON:-74.81025101 | CD12: EL VALLE | CE12: -1 | CF12: 08001000 | CG12: Atlantico | CH12: ATACANTE | CI12: 1022940376 | CJ12: DAVID ALEJANDRO SUAREZ LOZADA | CK12: CANAL ONLINE | CL12: TELEVENTAS | CM12: ATENTO COLOMBIA S.A. | CN12: CANAL ON LINE - ATENTO OUT BOUND | CT12: 2 | CU12: BA + LB + IPTV | CW12: MTotal_Trio_Voz Ilim Nal _Ba Ancha 900Mbps_IPTV_2_Decos_Mov Ilim_Nac_25425 | CX12: 25425 | DA12: SV | DB12: -1 | DF12: ALTA | DJ12: 900000 | DK12: Cliente Nuevo | DL12: Cliente Nuevo | DN12: TRIO | DR12: dsuarezlo2 | DS12: DAVID ALEJANDRO SUAREZ LOZADA | DT12: 1022940376 | DV12: 1 | DW12: CARIBE | ED12: 46143 | EF12: 9 | EP12: 830065842-5 | ES12: BQU1 | FA12: CANAL ONLINE | FB12: Atlántico | FD12: Atlántico | FE12: Barranquilla | FF12: Distrito Especial, Industrial Y Portuario De Barranquilla | FK12: ATENTO | FL12: 8001000OH_ATLHIDIAC_I_5800_Barraquilla_Delicias_3DELIC-CT2-39-05SS2-39-05@8001000_OH_ATLHIDIAC_I_5800_Barraquilla_Delicias_3_DELIC-CT2-39-05_SS2-39-05 | FN12: CANAL ON LINE - ATENTO OUT BOUND | FO12: 9900202020034 | FR12: 113904 | GB12: PON | GC12: BA + LB + IPTV | GD12: 25188 | GF12: 2353 | GG12: 25422 | GI12: 87224 | GJ12: 25427 | GL12: 24327 | GM12: 135545 | GS12: FS | GT12: 44804 | GU12: CENTRO EXP | GV12: VALIDADO | GW12: Si | GX12: SV | GY12: Convergente Solo Contrato | GZ12: Convergente Nuevo | HA12: ONNET | HB12: BARRANQUILLA | HC12: BARRANQUILLA | HD12: CARIBE | HE12: Individual | HF12: 1096574810 | HG12: Venta mismo mes (F+M) mismo Canal_mismo Aliado | HH12: 32774182 | HI12: 1. Radicadas | HJ12: 46149 | HK12: ATENTO COLOMBIA S.A. | HL12: CANAL ONLINE | HM12: 9900202020034 | HN12: CANAL ON LINE - ATENTO OUT BOUND | HO12: DAVID ALEJANDRO SUAREZ LOZADA | HP12: 1022940376 | HR12: Asistido | HV12: 118900 | HW12: SI | HX12: Radicada - No nato igual a NO | HY12: 131572 | HZ12: 17668 | IA12: SI | IB12: NO | IE12: BOGOTA | IF12: BOGOTA | IG12: BOGOTA | IH12: Digital | II12: Fibra | IJ12: B2C | IK12: Asistido | IL12: Outbound | IM12: Atento | IN12: Alta | IP12: - | IQ12: Digital | IS12: ELECTRONICA | IT12: Googleads_Oferta | IU12: CO_HOGAR_COL-FIBRA-ASISTIDA-AI-V2-B2C_25-12-11_SEM_LDS-WEB_AON_ABT_BRAND | IV12: SEM_SEM_CPL | IW12: Fija-Fibra-web-CajadeProducto-LP-pauta-fibra | IY12: SI
A13: =DAY(AVANZA[[#This Row],[FechaSeguimiento]]) -> 1 | B13: =MONTH(AVANZA[[#This Row],[FechaSeguimiento]]) -> 5 | C13: =LOWER(IF(AND(AVANZA[[#This Row],[Mes_Reg]]=MONTH(TODAY()),AND(AVANZA[[#This Row],[Dia_Reg]]>0,AVANZA[[#This Row],[Dia_Reg]]<9)),"SEMANA 1","")&IF(AND(AVANZA[[#This Row],[Mes_Reg]]=MONTH(TODAY()),AND(AVANZA[[#This Row],[Dia_Reg]]>8,AVANZA[[#This Row],[Dia_Reg]]<16)),"SEMANA 2","")&IF(AND(AVANZA[[#This Row],[Mes_Reg]]=MONTH(TODAY()),AND(AVANZA[[#This Row],[Dia_Reg]]>15,AVANZA[[#This Row],[Dia_Reg]]<23)),"SEMANA 3","")&IF(AND(AVANZA[[#This Row],[Mes_Reg]]=MONTH(TODAY()),AND(AVANZA[[#This Row],[Dia_Reg]]>22,AVANZA[[#This Row],[Dia_Reg]]<31)),"SEMANA 4","")&IF(AVANZA[[#This Row],[Mes_Reg]]<>MONTH(TODAY()),"BOLSA MES ANTERIOR","")) -> bolsa mes anterior | D13: =LOWER(IFERROR(VLOOKUP(AVANZA[[#This Row],[ID_Peticion]],CANCELADAS[#All],2,0),"")) | E13: =LOWER(IFERROR(VLOOKUP(AVANZA[[#This Row],[ID_Peticion]],CANCELADAS[#All],3,0),"")) | F13: =LOWER(IF(AVANZA[[#This Row],[CEDULA CLIENTE]]<>""," CC: " & COUNTIFS(AVANZA[CEDULA CLIENTE],AVANZA[[#This Row],[CEDULA CLIENTE]]),"")& IF(AVANZA[[#This Row],[Direccion]]<>""," DIR: " & COUNTIFS(AVANZA[Direccion],AVANZA[[#This Row],[Direccion]]),"")) -> dir: 1 | G13: =IFERROR(VLOOKUP(AVANZA[[#This Row],[Cedula_Vendedor_Atis]],PLANTA[[#All],[CEDULA]:[LINEA]],3,0),"No Cruza") -> Marisol Avella | H13: =IFERROR(VLOOKUP(AVANZA[[#This Row],[Cedula_Vendedor_Atis]],PLANTA[[#All],[CEDULA]:[LINEA]],4,0),"No Cruza") -> Fija | I13: =LOWER(IF(AVANZA[[#This Row],[ATRIBUIBLE]]="",AVANZA[[#This Row],[Variable]],AVANZA[[#This Row],[ATRIBUIBLE]])) -> terminada | J13: =IF(AVANZA[[#This Row],[Variable]]=AVANZA[[#Headers],[TERMINADA]],1,0) -> 1 | K13: =IF(AVANZA[[#This Row],[Variable]]=AVANZA[[#Headers],[ANULADA]],1,0) -> 0 | L13: =IF(AVANZA[[#This Row],[Variable]]=AVANZA[[#Headers],[PENDIENTE]],1,0) -> 0 | M13: =IF(AVANZA[[#This Row],[ESTADO AGENDA]]="AGENDADA",1,0) -> 0 | N13: =IF(AVANZA[[#This Row],[ESTADO AGENDA]]="PENDIENTE DE AGENDAR",1,0) -> 0 | O13: =IF(AVANZA[[#This Row],[ESTADO AGENDA]]="SUSPENDIDA",1,0) -> 0 | P13: {=_xlfn.XLOOKUP(AVANZA[[#This Row],[Num_Agrupacion_Pet_Atis]],Tabla1[[#All],[Numero_de_actuacion]],Tabla1[[#All],[Estado_de_la_orden]],"",0)} | Q13: {=_xlfn.XLOOKUP(AVANZA[[#This Row],[Num_Agrupacion_Pet_Atis]],Tabla1[[#All],[Numero_de_actuacion]],Tabla1[[#All],[Fecha_de_la_cita]],"",0)} | R13: {=_xlfn.XLOOKUP(AVANZA[[#This Row],[Num_Agrupacion_Pet_Atis]],Tabla1[[#All],[Numero_de_actuacion]],Tabla1[[#All],[Franja_horaria_de_la_cita]],"",0)} | S13: =IFERROR(DAY(AVANZA[[#This Row],[FECHA AGENDA]]),"") | T13: =IFERROR(MONTH(AVANZA[[#This Row],[FECHA AGENDA]]),"") | U13: {=_xlfn.XLOOKUP(AVANZA[[#This Row],[Num_Agrupacion_Pet_Atis]],Tabla1[[#All],[Numero_de_actuacion]],Tabla1[[#All],[Motivo_de_suspension]],"",0)} | V13: {=_xlfn.XLOOKUP(AVANZA[[#This Row],[Num_Agrupacion_Pet_Atis]],Tabla1[[#All],[Numero_de_actuacion]],Tabla1[[#All],[No_identificacion_cliente]],"",0)} | W13: {=_xlfn.XLOOKUP(AVANZA[[#This Row],[Num_Agrupacion_Pet_Atis]],Tabla1[[#All],[Numero_de_actuacion]],Tabla1[[#All],[Movil_de_contacto]],"",0)} | X13: =IF(OR(AVANZA[[#This Row],[ESTADO LEG]]="Legalizada grabacion",AVANZA[[#This Row],[ESTADO LEG]]="Legalizada aut"),1,0) -> 1 | Y13: =IF(OR(AVANZA[[#This Row],[ESTADO LEG]]="pdte legalizar",AVANZA[[#This Row],[ESTADO LEG]]="No cruza"),1,0) -> 0 | Z13: {=IF(AVANZA[[#This Row],[Variable]]="Terminada",LOWER(_xlfn.XLOOKUP(AVANZA[[#This Row],[ID_Peticion]],Tabla6[[#All],[NUM_PETICION]],Tabla6[[#All],[ESTADO_LEG]],"NO CRUZA",0)),AVANZA[[#This Row],[Variable]])} -> legalizada grabacion | AA13: {=_xlfn.XLOOKUP(AVANZA[[#This Row],[ID_Peticion]],Tabla6[[#All],[NUM_PETICION]],Tabla6[[#All],[DIF_DIAS]],"",0)} -> 4 | AB13: {=IFERROR(_xlfn.XLOOKUP(AVANZA[[#This Row],[ID_Peticion]],Tabla6[[#All],[NUM_PETICION]],Tabla6[[#All],[FEC_LEGAL]],"",0),"")} -> 46147 | AC13: =IF(AVANZA[[#This Row],[FECHA LEG]]<>0,IFERROR(AVANZA[[#This Row],[FECHA LEG]]-AVANZA[[#This Row],[FechaIniEstadoSubPetAtis]],0),TODAY()-AVANZA[[#This Row],[FechaIniEstadoSubPetAtis]]) -> 4 | AD13: =IF(AVANZA[[#This Row],[FINAL Vs LG]]<>0,IF(AVANZA[[#This Row],[FINAL Vs LG]]<7.1,"100%",IF(AND(AVANZA[[#This Row],[FINAL Vs LG]]>7.1,AVANZA[[#This Row],[FINAL Vs LG]]<11.1),"50%","0%")),0) -> 100% | AE13: =VLOOKUP(DAY(TODAY()),BACK!F:G,2,0) -> 14 | AF13: =BACK!$I$2 -> 24 | AG13: =IF(AVANZA[[#This Row],[Oferta_empaquetada_comisiones]]="SI",1,0) -> 0 | AH13: =IF(AVANZA[[#This Row],[Variable]]="TERMINADA",IFERROR(VLOOKUP(AVANZA[[#This Row],[SUPERVISOR]],Tabla2[#All],4,0),0),) -> 3.5 | AI13: =IF(AVANZA[[#This Row],[Producto]]="BA",1,0) -> 1 | AJ13: =IF(AVANZA[[#This Row],[Producto]]="DUO",1,0) -> 0 | AK13: =IF(AVANZA[[#This Row],[Producto]]="TRIO",1,0) -> 0 | AL13: 1676645258217257870 | AM13: -1 | AN13: -1 | AO13: 1785628184 | AP13: 46142.582 | AQ13: -1 | AR13: 2512689481 | AS13: -1 | AT13: -1 | AU13: -1 | AV13: -1 | AW13: -1 | AX13: FixedCreateSubscriber | AY13: -1 | AZ13: 2026 | BA13: 5 | BB13: 1 | BC13: -1 | BD13: Broadband Service | BE13: -1 | BF13: 20001620720105 | BG13: Plan Banda Ancha 900Mbps Solo Internet_Nac_25423 | BH13: 25423 | BI13: FS202604301358272393 | BJ13: -1 | BK13: -1 | BL13: -1 | BM13: TERMINADA | BN13: Individual | BO13: 6108777949 | BP13: Bronce Prepago | BQ13: 2026 | BR13: 4 | BS13: 30 | BT13: 46143.539 | BU13: OS90 | BV13: 46143 | BW13: Completed | BX13: 46142 | BY13: 46143 | BZ13: Call Back To CRM | CA13: DISTRITO TURISTICO,CULTURAL E HISTORICO DE SANTA MARTA | CB13: MAGDALENA | CC13: MZA 25 CAS 26 URB NUEVA ANDREA CAROLINA-26 URB ANDREA CAROLINA 26 CAS 26 LAT:11.2128958 LON:-74.17672504 | CD13: URB ANDREA CAROLINA | CE13: -1 | CF13: 47001000 | CG13: Magdalena - Cesar - Guajira | CH13: INCUMBENTE | CI13: 1098100287 | CJ13: JOHAN SEBASTIAN DUARTE CORREA | CK13: CANAL ONLINE | CL13: ON LINE | CM13: ATENTO COLOMBIA S.A. | CN13: CANAL ON LINE - ATENTO CLICK TO CALL | CT13: 3 | CU13: Broadband Service | CW13: Plan Banda Ancha 900Mbps Solo Internet_Nac_25423 | CX13: 25423 | DA13: SV | DB13: -1 | DF13: ALTA | DJ13: 900000 | DK13: Cliente Nuevo | DL13: Cliente Existente | DN13: BA | DR13: jduarteco | DS13: JOHAN SEBASTIAN DUARTE CORREA | DT13: 1098100287 | DV13: 1 | DW13: CARIBE | ED13: 46143 | EF13: 9 | EP13: 830065842-5 | ES13: Urb. Villa Carolina | FA13: CANAL ONLINE | FB13: Magdalena | FD13: Magdalena | FE13: Santa Marta | FF13: Distrito Turístico,Cultural E Histórico De Santa Marta | FK13: ATENTO | FL13: 47001000OH_MAGHICELA_I_5800_SantaMarta_CiudadelaCIUDA-CT2-30-01SS2-30-01@47001000_OH_MAGHICELA_I_5800_SantaMarta_Ciudadela_CIUDA-CT2-30-01_SS2-30-01 | FN13: CANAL ON LINE - ATENTO CLICK TO CALL | FO13: 9900202020033 | FR13: 94990 | GB13: PON | GC13: Broadband Service | GD13: 0 | GF13: 0 | GG13: 25423 | GI13: 94990 | GJ13: 0 | GL13: 0 | GM13: 113038 | GS13: FS | GT13: 43434 | GU13: CENTRO EXP | GV13: SIN EMAIL | GW13: No | GZ13: No Convergente | HA13: PRE-ONNET | HB13: MAGDALENA (SANTA MARTA) | HC13: SANTA MARTA | HD13: CARIBE | HE13: Individual | HF13: 1121074175 | HR13: Asistido | HV13: 94990 | HW13: NO | HY13: 0 | HZ13: 0 | IA13: NO | IB13: NO | IE13: BOGOTA | IF13: BOGOTA | IG13: BOGOTA | IH13: Digital | II13: Fibra | IJ13: B2C | IK13: Asistido | IL13: C2C | IM13: Atento | IN13: Alta | IP13: - | IQ13: Digital | IS13: FISICA | IT13: Organico | IW13: Fibra-Fibra-web-CajadeProducto-LP_Hogar_Naked | IY13: NO
A14: =DAY(AVANZA[[#This Row],[FechaSeguimiento]]) -> 1 | B14: =MONTH(AVANZA[[#This Row],[FechaSeguimiento]]) -> 5 | C14: =LOWER(IF(AND(AVANZA[[#This Row],[Mes_Reg]]=MONTH(TODAY()),AND(AVANZA[[#This Row],[Dia_Reg]]>0,AVANZA[[#This Row],[Dia_Reg]]<9)),"SEMANA 1","")&IF(AND(AVANZA[[#This Row],[Mes_Reg]]=MONTH(TODAY()),AND(AVANZA[[#This Row],[Dia_Reg]]>8,AVANZA[[#This Row],[Dia_Reg]]<16)),"SEMANA 2","")&IF(AND(AVANZA[[#This Row],[Mes_Reg]]=MONTH(TODAY()),AND(AVANZA[[#This Row],[Dia_Reg]]>15,AVANZA[[#This Row],[Dia_Reg]]<23)),"SEMANA 3","")&IF(AND(AVANZA[[#This Row],[Mes_Reg]]=MONTH(TODAY()),AND(AVANZA[[#This Row],[Dia_Reg]]>22,AVANZA[[#This Row],[Dia_Reg]]<31)),"SEMANA 4","")&IF(AVANZA[[#This Row],[Mes_Reg]]<>MONTH(TODAY()),"BOLSA MES ANTERIOR","")) -> semana 1 | D14: =LOWER(IFERROR(VLOOKUP(AVANZA[[#This Row],[ID_Peticion]],CANCELADAS[#All],2,0),"")) | E14: =LOWER(IFERROR(VLOOKUP(AVANZA[[#This Row],[ID_Peticion]],CANCELADAS[#All],3,0),"")) | F14: =LOWER(IF(AVANZA[[#This Row],[CEDULA CLIENTE]]<>""," CC: " & COUNTIFS(AVANZA[CEDULA CLIENTE],AVANZA[[#This Row],[CEDULA CLIENTE]]),"")& IF(AVANZA[[#This Row],[Direccion]]<>""," DIR: " & COUNTIFS(AVANZA[Direccion],AVANZA[[#This Row],[Direccion]]),"")) -> dir: 1 | G14: =IFERROR(VLOOKUP(AVANZA[[#This Row],[Cedula_Vendedor_Atis]],PLANTA[[#All],[CEDULA]:[LINEA]],3,0),"No Cruza") -> Marisol Avella | H14: =IFERROR(VLOOKUP(AVANZA[[#This Row],[Cedula_Vendedor_Atis]],PLANTA[[#All],[CEDULA]:[LINEA]],4,0),"No Cruza") -> Fija | I14: =LOWER(IF(AVANZA[[#This Row],[ATRIBUIBLE]]="",AVANZA[[#This Row],[Variable]],AVANZA[[#This Row],[ATRIBUIBLE]])) -> terminada | J14: =IF(AVANZA[[#This Row],[Variable]]=AVANZA[[#Headers],[TERMINADA]],1,0) -> 1 | K14: =IF(AVANZA[[#This Row],[Variable]]=AVANZA[[#Headers],[ANULADA]],1,0) -> 0 | L14: =IF(AVANZA[[#This Row],[Variable]]=AVANZA[[#Headers],[PENDIENTE]],1,0) -> 0 | M14: =IF(AVANZA[[#This Row],[ESTADO AGENDA]]="AGENDADA",1,0) -> 0 | N14: =IF(AVANZA[[#This Row],[ESTADO AGENDA]]="PENDIENTE DE AGENDAR",1,0) -> 0 | O14: =IF(AVANZA[[#This Row],[ESTADO AGENDA]]="SUSPENDIDA",1,0) -> 0 | P14: {=_xlfn.XLOOKUP(AVANZA[[#This Row],[Num_Agrupacion_Pet_Atis]],Tabla1[[#All],[Numero_de_actuacion]],Tabla1[[#All],[Estado_de_la_orden]],"",0)} | Q14: {=_xlfn.XLOOKUP(AVANZA[[#This Row],[Num_Agrupacion_Pet_Atis]],Tabla1[[#All],[Numero_de_actuacion]],Tabla1[[#All],[Fecha_de_la_cita]],"",0)} | R14: {=_xlfn.XLOOKUP(AVANZA[[#This Row],[Num_Agrupacion_Pet_Atis]],Tabla1[[#All],[Numero_de_actuacion]],Tabla1[[#All],[Franja_horaria_de_la_cita]],"",0)} | S14: =IFERROR(DAY(AVANZA[[#This Row],[FECHA AGENDA]]),"") | T14: =IFERROR(MONTH(AVANZA[[#This Row],[FECHA AGENDA]]),"") | U14: {=_xlfn.XLOOKUP(AVANZA[[#This Row],[Num_Agrupacion_Pet_Atis]],Tabla1[[#All],[Numero_de_actuacion]],Tabla1[[#All],[Motivo_de_suspension]],"",0)} | V14: {=_xlfn.XLOOKUP(AVANZA[[#This Row],[Num_Agrupacion_Pet_Atis]],Tabla1[[#All],[Numero_de_actuacion]],Tabla1[[#All],[No_identificacion_cliente]],"",0)} | W14: {=_xlfn.XLOOKUP(AVANZA[[#This Row],[Num_Agrupacion_Pet_Atis]],Tabla1[[#All],[Numero_de_actuacion]],Tabla1[[#All],[Movil_de_contacto]],"",0)} | X14: =IF(OR(AVANZA[[#This Row],[ESTADO LEG]]="Legalizada grabacion",AVANZA[[#This Row],[ESTADO LEG]]="Legalizada aut"),1,0) -> 1 | Y14: =IF(OR(AVANZA[[#This Row],[ESTADO LEG]]="pdte legalizar",AVANZA[[#This Row],[ESTADO LEG]]="No cruza"),1,0) -> 0 | Z14: {=IF(AVANZA[[#This Row],[Variable]]="Terminada",LOWER(_xlfn.XLOOKUP(AVANZA[[#This Row],[ID_Peticion]],Tabla6[[#All],[NUM_PETICION]],Tabla6[[#All],[ESTADO_LEG]],"NO CRUZA",0)),AVANZA[[#This Row],[Variable]])} -> legalizada grabacion | AA14: {=_xlfn.XLOOKUP(AVANZA[[#This Row],[ID_Peticion]],Tabla6[[#All],[NUM_PETICION]],Tabla6[[#All],[DIF_DIAS]],"",0)} -> 4 | AB14: {=IFERROR(_xlfn.XLOOKUP(AVANZA[[#This Row],[ID_Peticion]],Tabla6[[#All],[NUM_PETICION]],Tabla6[[#All],[FEC_LEGAL]],"",0),"")} -> 46147 | AC14: =IF(AVANZA[[#This Row],[FECHA LEG]]<>0,IFERROR(AVANZA[[#This Row],[FECHA LEG]]-AVANZA[[#This Row],[FechaIniEstadoSubPetAtis]],0),TODAY()-AVANZA[[#This Row],[FechaIniEstadoSubPetAtis]]) -> 4 | AD14: =IF(AVANZA[[#This Row],[FINAL Vs LG]]<>0,IF(AVANZA[[#This Row],[FINAL Vs LG]]<7.1,"100%",IF(AND(AVANZA[[#This Row],[FINAL Vs LG]]>7.1,AVANZA[[#This Row],[FINAL Vs LG]]<11.1),"50%","0%")),0) -> 100% | AE14: =VLOOKUP(DAY(TODAY()),BACK!F:G,2,0) -> 14 | AF14: =BACK!$I$2 -> 24 | AG14: =IF(AVANZA[[#This Row],[Oferta_empaquetada_comisiones]]="SI",1,0) -> 0 | AH14: =IF(AVANZA[[#This Row],[Variable]]="TERMINADA",IFERROR(VLOOKUP(AVANZA[[#This Row],[SUPERVISOR]],Tabla2[#All],4,0),0),) -> 3.5 | AI14: =IF(AVANZA[[#This Row],[Producto]]="BA",1,0) -> 1 | AJ14: =IF(AVANZA[[#This Row],[Producto]]="DUO",1,0) -> 0 | AK14: =IF(AVANZA[[#This Row],[Producto]]="TRIO",1,0) -> 0 | AL14: 1539198969229010498 | AM14: -1 | AN14: -1 | AO14: 1785854417 | AP14: 46143.43 | AQ14: -1 | AR14: 2512691088 | AS14: -1 | AT14: -1 | AU14: -1 | AV14: -1 | AW14: -1 | AX14: FixedCreateSubscriber | AY14: -1 | AZ14: 2026 | BA14: 5 | BB14: 1 | BC14: -1 | BD14: Broadband Service | BE14: -1 | BF14: 20001621064993 | BG14: Convergente_MTotal_Single_Voz Ilim Nal _Ba Ancha 900Mbps_Mov Ilim_Nac_25421 | BH14: 25421 | BI14: FS202605011018441062 | BJ14: -1 | BK14: -1 | BL14: -1 | BM14: TERMINADA | BN14: Individual | BO14: 6077945441 | BP14: Movistar Total | BQ14: 2026 | BR14: 5 | BS14: 1 | BT14: 46143.703 | BU14: OS90 | BV14: 46143 | BW14: Completed | BX14: 46143 | BY14: 46143 | BZ14: Call Back To CRM | CA14: BOGOTA, D.C. | CB14: BOGOTA, D.C. | CC14: CL 130 F KR 98 A-57 AURES 57 LAT:4.7318179 LON:-74.09482917 | CD14: AURES | CE14: -1 | CF14: 11001000 | CG14: Bogota | CH14: ATACANTE | CI14: 22999736 | CJ14: VIVIANA PATRICIA BENAVIDES ZUNIGA | CK14: CANAL ONLINE | CL14: ON LINE | CM14: ATENTO COLOMBIA S.A. | CN14: CANAL ON LINE - ATENTO IN BOUND | CT14: 2 | CU14: Broadband Service | CW14: Convergente_MTotal_Single_Voz Ilim Nal _Ba Ancha 900Mbps_Mov Ilim_Nac_25421 | CX14: 25421 | DA14: SV | DB14: -1 | DF14: ALTA | DJ14: 900000 | DK14: Cliente Nuevo | DL14: Cliente Existente | DN14: BA | DR14: vpbenavidezu | DS14: VIVIANA PATRICIA BENAVIDES ZUNIGA | DT14: 22999736 | DV14: 1 | DW14: BOGOTA | ED14: 46143 | EE14: Norte | EF14: 20 | EP14: 830065842-5 | ES14: 141 | FA14: CANAL ONLINE | FB14: Bogotá D.C | FD14: Bogotá D.C | FE14: Bogotá | FF14: Bogotá | FK14: ATENTO | FL14: 11001000OH_BOGHIVRID_I_5800_VillaMaria_23000_4VIMAR-CT7-64-09SS7-64-09@11001000_OH_BOGHIVRID_I_5800_VillaMaria_23000_4_VIMAR-CT7-64-09_SS7-64-09 | FN14: CANAL ON LINE - ATENTO IN BOUND | FO14: 9900202020035 | FR14: 85900 | GB14: PON | GC14: Broadband Service | GD14: 0 | GF14: 0 | GG14: 25421 | GI14: 85900 | GJ14: 0 | GL14: 0 | GM14: 102221 | GS14: FS | GT14: 44587 | GU14: CENTRO EXP | GV14: NO VALIDADO | GW14: Si | GX14: Solo Movil | GY14: Convergente Solo Contrato | GZ14: Convergente Nuevo | HA14: ONNET | HB14: BOGOTA 1 | HC14: BOGOTA 1 | HD14: BOGOTA NORTE | HE14: Individual | HF14: 473074090 | HG14: Venta Hogar (F) a cliente Pospago | HR14: Asistido | HV14: 85900 | HW14: SI | HX14: Migracion Pos-Pos | HY14: 103568 | HZ14: 17668 | IA14: SI | IB14: NO | ID14: >= 120 | IE14: BOGOTA | IF14: BOGOTA | IG14: BOGOTA | IH14: Digital | II14: Fibra | IJ14: B2C | IK14: Asistido | IL14: Inbound | IM14: Atento | IN14: Alta | IP14: - | IQ14: Digital | IS14: ELECTRONICA | IT14: App | IU14: app_gif_fibra_asistido | IV14: app_gif_fibra | IW14: Fija-Fibra-web-CajadeProducto-LP-pauta-fibra | IY14: NO
A15: =DAY(AVANZA[[#This Row],[FechaSeguimiento]]) -> 2 | B15: =MONTH(AVANZA[[#This Row],[FechaSeguimiento]]) -> 5 | C15: =LOWER(IF(AND(AVANZA[[#This Row],[Mes_Reg]]=MONTH(TODAY()),AND(AVANZA[[#This Row],[Dia_Reg]]>0,AVANZA[[#This Row],[Dia_Reg]]<9)),"SEMANA 1","")&IF(AND(AVANZA[[#This Row],[Mes_Reg]]=MONTH(TODAY()),AND(AVANZA[[#This Row],[Dia_Reg]]>8,AVANZA[[#This Row],[Dia_Reg]]<16)),"SEMANA 2","")&IF(AND(AVANZA[[#This Row],[Mes_Reg]]=MONTH(TODAY()),AND(AVANZA[[#This Row],[Dia_Reg]]>15,AVANZA[[#This Row],[Dia_Reg]]<23)),"SEMANA 3","")&IF(AND(AVANZA[[#This Row],[Mes_Reg]]=MONTH(TODAY()),AND(AVANZA[[#This Row],[Dia_Reg]]>22,AVANZA[[#This Row],[Dia_Reg]]<31)),"SEMANA 4","")&IF(AVANZA[[#This Row],[Mes_Reg]]<>MONTH(TODAY()),"BOLSA MES ANTERIOR","")) -> semana 1 | D15: =LOWER(IFERROR(VLOOKUP(AVANZA[[#This Row],[ID_Peticion]],CANCELADAS[#All],2,0),"")) -> carrusel | E15: =LOWER(IFERROR(VLOOKUP(AVANZA[[#This Row],[ID_Peticion]],CANCELADAS[#All],3,0),"")) -> carrusel | F15: =LOWER(IF(AVANZA[[#This Row],[CEDULA CLIENTE]]<>""," CC: " & COUNTIFS(AVANZA[CEDULA CLIENTE],AVANZA[[#This Row],[CEDULA CLIENTE]]),"")& IF(AVANZA[[#This Row],[Direccion]]<>""," DIR: " & COUNTIFS(AVANZA[Direccion],AVANZA[[#This Row],[Direccion]]),"")) -> dir: 1 | G15: =IFERROR(VLOOKUP(AVANZA[[#This Row],[Cedula_Vendedor_Atis]],PLANTA[[#All],[CEDULA]:[LINEA]],3,0),"No Cruza") -> Marisol Avella | H15: =IFERROR(VLOOKUP(AVANZA[[#This Row],[Cedula_Vendedor_Atis]],PLANTA[[#All],[CEDULA]:[LINEA]],4,0),"No Cruza") -> Fija | I15: =LOWER(IF(AVANZA[[#This Row],[ATRIBUIBLE]]="",AVANZA[[#This Row],[Variable]],AVANZA[[#This Row],[ATRIBUIBLE]])) -> carrusel | J15: =IF(AVANZA[[#This Row],[Variable]]=AVANZA[[#Headers],[TERMINADA]],1,0) -> 0 | K15: =IF(AVANZA[[#This Row],[Variable]]=AVANZA[[#Headers],[ANULADA]],1,0) -> 1 | L15: =IF(AVANZA[[#This Row],[Variable]]=AVANZA[[#Headers],[PENDIENTE]],1,0) -> 0 | M15: =IF(AVANZA[[#This Row],[ESTADO AGENDA]]="AGENDADA",1,0) -> 0 | N15: =IF(AVANZA[[#This Row],[ESTADO AGENDA]]="PENDIENTE DE AGENDAR",1,0) -> 0 | O15: =IF(AVANZA[[#This Row],[ESTADO AGENDA]]="SUSPENDIDA",1,0) -> 0 | P15: {=_xlfn.XLOOKUP(AVANZA[[#This Row],[Num_Agrupacion_Pet_Atis]],Tabla1[[#All],[Numero_de_actuacion]],Tabla1[[#All],[Estado_de_la_orden]],"",0)} | Q15: {=_xlfn.XLOOKUP(AVANZA[[#This Row],[Num_Agrupacion_Pet_Atis]],Tabla1[[#All],[Numero_de_actuacion]],Tabla1[[#All],[Fecha_de_la_cita]],"",0)} | R15: {=_xlfn.XLOOKUP(AVANZA[[#This Row],[Num_Agrupacion_Pet_Atis]],Tabla1[[#All],[Numero_de_actuacion]],Tabla1[[#All],[Franja_horaria_de_la_cita]],"",0)} | S15: =IFERROR(DAY(AVANZA[[#This Row],[FECHA AGENDA]]),"") | T15: =IFERROR(MONTH(AVANZA[[#This Row],[FECHA AGENDA]]),"") | U15: {=_xlfn.XLOOKUP(AVANZA[[#This Row],[Num_Agrupacion_Pet_Atis]],Tabla1[[#All],[Numero_de_actuacion]],Tabla1[[#All],[Motivo_de_suspension]],"",0)} | V15: {=_xlfn.XLOOKUP(AVANZA[[#This Row],[Num_Agrupacion_Pet_Atis]],Tabla1[[#All],[Numero_de_actuacion]],Tabla1[[#All],[No_identificacion_cliente]],"",0)} | W15: {=_xlfn.XLOOKUP(AVANZA[[#This Row],[Num_Agrupacion_Pet_Atis]],Tabla1[[#All],[Numero_de_actuacion]],Tabla1[[#All],[Movil_de_contacto]],"",0)} | X15: =IF(OR(AVANZA[[#This Row],[ESTADO LEG]]="Legalizada grabacion",AVANZA[[#This Row],[ESTADO LEG]]="Legalizada aut"),1,0) -> 0 | Y15: =IF(OR(AVANZA[[#This Row],[ESTADO LEG]]="pdte legalizar",AVANZA[[#This Row],[ESTADO LEG]]="No cruza"),1,0) -> 0 | Z15: {=IF(AVANZA[[#This Row],[Variable]]="Terminada",LOWER(_xlfn.XLOOKUP(AVANZA[[#This Row],[ID_Peticion]],Tabla6[[#All],[NUM_PETICION]],Tabla6[[#All],[ESTADO_LEG]],"NO CRUZA",0)),AVANZA[[#This Row],[Variable]])} -> ANULADA | AA15: {=_xlfn.XLOOKUP(AVANZA[[#This Row],[ID_Peticion]],Tabla6[[#All],[NUM_PETICION]],Tabla6[[#All],[DIF_DIAS]],"",0)} | AB15: {=IFERROR(_xlfn.XLOOKUP(AVANZA[[#This Row],[ID_Peticion]],Tabla6[[#All],[NUM_PETICION]],Tabla6[[#All],[FEC_LEGAL]],"",0),"")} | AC15: =IF(AVANZA[[#This Row],[FECHA LEG]]<>0,IFERROR(AVANZA[[#This Row],[FECHA LEG]]-AVANZA[[#This Row],[FechaIniEstadoSubPetAtis]],0),TODAY()-AVANZA[[#This Row],[FechaIniEstadoSubPetAtis]]) -> 0 | AD15: =IF(AVANZA[[#This Row],[FINAL Vs LG]]<>0,IF(AVANZA[[#This Row],[FINAL Vs LG]]<7.1,"100%",IF(AND(AVANZA[[#This Row],[FINAL Vs LG]]>7.1,AVANZA[[#This Row],[FINAL Vs LG]]<11.1),"50%","0%")),0) -> 0 | AE15: =VLOOKUP(DAY(TODAY()),BACK!F:G,2,0) -> 14 | AF15: =BACK!$I$2 -> 24 | AG15: =IF(AVANZA[[#This Row],[Oferta_empaquetada_comisiones]]="SI",1,0) -> 0 | AH15: =IF(AVANZA[[#This Row],[Variable]]="TERMINADA",IFERROR(VLOOKUP(AVANZA[[#This Row],[SUPERVISOR]],Tabla2[#All],4,0),0),) -> 0 | AI15: =IF(AVANZA[[#This Row],[Producto]]="BA",1,0) -> 1 | AJ15: =IF(AVANZA[[#This Row],[Producto]]="DUO",1,0) -> 0 | AK15: =IF(AVANZA[[#This Row],[Producto]]="TRIO",1,0) -> 0 | AL15: 1651508247288716261 | AM15: -1 | AN15: -1 | AO15: 1785901363 | AP15: 46143.52 | AQ15: -1 | AR15: 2512691135 | AS15: -1 | AT15: -1 | AU15: -1 | AV15: -1 | AW15: -1 | AX15: FixedCreateSubscriber | AY15: -1 | AZ15: 2026 | BA15: 5 | BB15: 2 | BC15: -1 | BD15: Broadband Service | BE15: -1 | BF15: 20001621104074 | BG15: Convergente_MTotal_Single_Voz Ilim Nal _Ba Ancha 900Mbps_Mov Ilim_Nac_25421 | BH15: 25421 | BJ15: -1 | BK15: -1 | BL15: -1 | BM15: ANULADA | BN15: Individual | BO15: 6108217105 | BP15: Movistar Total | BQ15: 2026 | BR15: 5 | BS15: 1 | BT15: 46144.405 | BU15: OS80 | BV15: 46144 | BW15: Cancelled | CA15: BOGOTA, D.C. | CB15: BOGOTA, D.C. | CC15: KR 7 A CL 30 C S-18 SERAFINA II SEC 18 APT 201 LAT:4.56749424 LON:-74.09780629 | CD15: SERAFINA II SEC | CE15: -1 | CF15: 11001000 | CG15: Bogota | CH15: ATACANTE | CI15: 1000857923 | CJ15: SERGIO ANDREY RICO DIAZ | CK15: CANAL ONLINE | CL15: ON LINE | CM15: ATENTO COLOMBIA S.A. | CN15: CANAL ON LINE - ATENTO CLICK TO CALL | CT15: 3 | CU15: Broadband Service | CW15: Convergente_MTotal_Single_Voz Ilim Nal _Ba Ancha 900Mbps_Mov Ilim_Nac_25421 | CX15: 25421 | CY15: Anulada fraude marcada por campo remark | DA15: SV | DB15: -1 | DF15: ANULADA FRAUDE - REMARK | DJ15: 900000 | DK15: Cliente Nuevo | DL15: Cliente Nuevo | DN15: BA | DR15: saricodi | DS15: SERGIO ANDREY RICO DIAZ | DT15: 1000857923 | DV15: 1 | DW15: BOGOTA | ED15: 46144 | EF15: 9 | EP15: 830065842-5 | FA15: CANAL ONLINE | FB15: Bogotá D.C | FD15: Bogotá D.C | FE15: Bogotá | FF15: Bogotá | FK15: ATENTO | FN15: CANAL ON LINE - ATENTO CLICK TO CALL | FO15: 9900202020033 | FR15: 0 | GB15: PON | GM15: 0 | GS15: FS | GU15: CENTRO EXP | GV15: SIN EMAIL | GW15: Si | GX15: Solo Movil | GY15: Convergente Solo Contrato | GZ15: Convergente Nuevo | HE15: Individual | HF15: 456574095 | HR15: Asistido | HV15: 85900 | HW15: SI | HY15: 0 | HZ15: 0 | IA15: SI | IB15: NO | IC15: The Fraud order (Carrusel) is cancelled by SOM. | IE15: BOGOTA | IF15: BOGOTA | IG15: BOGOTA | IH15: Digital | II15: Fibra | IJ15: B2C | IK15: Asistido | IL15: Inbound | IM15: Atento | IN15: - | IP15: - | IQ15: Digital | IS15: ELECTRONICA | IT15: Inbound | IY15: NO
A16: =DAY(AVANZA[[#This Row],[FechaSeguimiento]]) -> 2 | B16: =MONTH(AVANZA[[#This Row],[FechaSeguimiento]]) -> 5 | C16: =LOWER(IF(AND(AVANZA[[#This Row],[Mes_Reg]]=MONTH(TODAY()),AND(AVANZA[[#This Row],[Dia_Reg]]>0,AVANZA[[#This Row],[Dia_Reg]]<9)),"SEMANA 1","")&IF(AND(AVANZA[[#This Row],[Mes_Reg]]=MONTH(TODAY()),AND(AVANZA[[#This Row],[Dia_Reg]]>8,AVANZA[[#This Row],[Dia_Reg]]<16)),"SEMANA 2","")&IF(AND(AVANZA[[#This Row],[Mes_Reg]]=MONTH(TODAY()),AND(AVANZA[[#This Row],[Dia_Reg]]>15,AVANZA[[#This Row],[Dia_Reg]]<23)),"SEMANA 3","")&IF(AND(AVANZA[[#This Row],[Mes_Reg]]=MONTH(TODAY()),AND(AVANZA[[#This Row],[Dia_Reg]]>22,AVANZA[[#This Row],[Dia_Reg]]<31)),"SEMANA 4","")&IF(AVANZA[[#This Row],[Mes_Reg]]<>MONTH(TODAY()),"BOLSA MES ANTERIOR","")) -> bolsa mes anterior | D16: =LOWER(IFERROR(VLOOKUP(AVANZA[[#This Row],[ID_Peticion]],CANCELADAS[#All],2,0),"")) | E16: =LOWER(IFERROR(VLOOKUP(AVANZA[[#This Row],[ID_Peticion]],CANCELADAS[#All],3,0),"")) | F16: =LOWER(IF(AVANZA[[#This Row],[CEDULA CLIENTE]]<>""," CC: " & COUNTIFS(AVANZA[CEDULA CLIENTE],AVANZA[[#This Row],[CEDULA CLIENTE]]),"")& IF(AVANZA[[#This Row],[Direccion]]<>""," DIR: " & COUNTIFS(AVANZA[Direccion],AVANZA[[#This Row],[Direccion]]),"")) -> dir: 1 | G16: =IFERROR(VLOOKUP(AVANZA[[#This Row],[Cedula_Vendedor_Atis]],PLANTA[[#All],[CEDULA]:[LINEA]],3,0),"No Cruza") -> Marisol Avella | H16: =IFERROR(VLOOKUP(AVANZA[[#This Row],[Cedula_Vendedor_Atis]],PLANTA[[#All],[CEDULA]:[LINEA]],4,0),"No Cruza") -> Fija | I16: =LOWER(IF(AVANZA[[#This Row],[ATRIBUIBLE]]="",AVANZA[[#This Row],[Variable]],AVANZA[[#This Row],[ATRIBUIBLE]])) -> terminada | J16: =IF(AVANZA[[#This Row],[Variable]]=AVANZA[[#Headers],[TERMINADA]],1,0) -> 1 | K16: =IF(AVANZA[[#This Row],[Variable]]=AVANZA[[#Headers],[ANULADA]],1,0) -> 0 | L16: =IF(AVANZA[[#This Row],[Variable]]=AVANZA[[#Headers],[PENDIENTE]],1,0) -> 0 | M16: =IF(AVANZA[[#This Row],[ESTADO AGENDA]]="AGENDADA",1,0) -> 0 | N16: =IF(AVANZA[[#This Row],[ESTADO AGENDA]]="PENDIENTE DE AGENDAR",1,0) -> 0 | O16: =IF(AVANZA[[#This Row],[ESTADO AGENDA]]="SUSPENDIDA",1,0) -> 0 | P16: {=_xlfn.XLOOKUP(AVANZA[[#This Row],[Num_Agrupacion_Pet_Atis]],Tabla1[[#All],[Numero_de_actuacion]],Tabla1[[#All],[Estado_de_la_orden]],"",0)} | Q16: {=_xlfn.XLOOKUP(AVANZA[[#This Row],[Num_Agrupacion_Pet_Atis]],Tabla1[[#All],[Numero_de_actuacion]],Tabla1[[#All],[Fecha_de_la_cita]],"",0)} | R16: {=_xlfn.XLOOKUP(AVANZA[[#This Row],[Num_Agrupacion_Pet_Atis]],Tabla1[[#All],[Numero_de_actuacion]],Tabla1[[#All],[Franja_horaria_de_la_cita]],"",0)} | S16: =IFERROR(DAY(AVANZA[[#This Row],[FECHA AGENDA]]),"") | T16: =IFERROR(MONTH(AVANZA[[#This Row],[FECHA AGENDA]]),"") | U16: {=_xlfn.XLOOKUP(AVANZA[[#This Row],[Num_Agrupacion_Pet_Atis]],Tabla1[[#All],[Numero_de_actuacion]],Tabla1[[#All],[Motivo_de_suspension]],"",0)} | V16: {=_xlfn.XLOOKUP(AVANZA[[#This Row],[Num_Agrupacion_Pet_Atis]],Tabla1[[#All],[Numero_de_actuacion]],Tabla1[[#All],[No_identificacion_cliente]],"",0)} | W16: {=_xlfn.XLOOKUP(AVANZA[[#This Row],[Num_Agrupacion_Pet_Atis]],Tabla1[[#All],[Numero_de_actuacion]],Tabla1[[#All],[Movil_de_contacto]],"",0)} | X16: =IF(OR(AVANZA[[#This Row],[ESTADO LEG]]="Legalizada grabacion",AVANZA[[#This Row],[ESTADO LEG]]="Legalizada aut"),1,0) -> 1 | Y16: =IF(OR(AVANZA[[#This Row],[ESTADO LEG]]="pdte legalizar",AVANZA[[#This Row],[ESTADO LEG]]="No cruza"),1,0) -> 0 | Z16: {=IF(AVANZA[[#This Row],[Variable]]="Terminada",LOWER(_xlfn.XLOOKUP(AVANZA[[#This Row],[ID_Peticion]],Tabla6[[#All],[NUM_PETICION]],Tabla6[[#All],[ESTADO_LEG]],"NO CRUZA",0)),AVANZA[[#This Row],[Variable]])} -> legalizada grabacion | AA16: {=_xlfn.XLOOKUP(AVANZA[[#This Row],[ID_Peticion]],Tabla6[[#All],[NUM_PETICION]],Tabla6[[#All],[DIF_DIAS]],"",0)} -> 4 | AB16: {=IFERROR(_xlfn.XLOOKUP(AVANZA[[#This Row],[ID_Peticion]],Tabla6[[#All],[NUM_PETICION]],Tabla6[[#All],[FEC_LEGAL]],"",0),"")} -> 46148 | AC16: =IF(AVANZA[[#This Row],[FECHA LEG]]<>0,IFERROR(AVANZA[[#This Row],[FECHA LEG]]-AVANZA[[#This Row],[FechaIniEstadoSubPetAtis]],0),TODAY()-AVANZA[[#This Row],[FechaIniEstadoSubPetAtis]]) -> 4 | AD16: =IF(AVANZA[[#This Row],[FINAL Vs LG]]<>0,IF(AVANZA[[#This Row],[FINAL Vs LG]]<7.1,"100%",IF(AND(AVANZA[[#This Row],[FINAL Vs LG]]>7.1,AVANZA[[#This Row],[FINAL Vs LG]]<11.1),"50%","0%")),0) -> 100% | AE16: =VLOOKUP(DAY(TODAY()),BACK!F:G,2,0) -> 14 | AF16: =BACK!$I$2 -> 24 | AG16: =IF(AVANZA[[#This Row],[Oferta_empaquetada_comisiones]]="SI",1,0) -> 0 | AH16: =IF(AVANZA[[#This Row],[Variable]]="TERMINADA",IFERROR(VLOOKUP(AVANZA[[#This Row],[SUPERVISOR]],Tabla2[#All],4,0),0),) -> 3.5 | AI16: =IF(AVANZA[[#This Row],[Producto]]="BA",1,0) -> 0 | AJ16: =IF(AVANZA[[#This Row],[Producto]]="DUO",1,0) -> 0 | AK16: =IF(AVANZA[[#This Row],[Producto]]="TRIO",1,0) -> 1 | AL16: 1760276618585267782 | AM16: -1 | AN16: -1 | AO16: 1784843900 | AP16: 46141.591 | AQ16: -1 | AR16: 2512687132 | AS16: -1 | AT16: -1 | AU16: -1 | AV16: -1 | AW16: -1 | AX16: FixedCreateSubscriber | AY16: -1 | AZ16: 2026 | BA16: 5 | BB16: 2 | BC16: -1 | BD16: Broadband Service | BE16: -1 | BF16: 20001620025919 | BG16: Convergente_Plan Ancha 900Mbps_Mov Ilim_Trio_25422 | BH16: 25422 | BI16: FS202604291409471199 | BJ16: -1 | BK16: -1 | BL16: -1 | BM16: TERMINADA | BN16: Individual | BO16: 6108767071 | BP16: Movistar Total | BQ16: 2026 | BR16: 4 | BS16: 29 | BT16: 46144.627 | BU16: OS90 | BV16: 46144 | BW16: Completed | BX16: 46141 | BY16: 46144 | BZ16: Call Back To CRM | CA16: SABANETA | CB16: ANTIOQUIA | CC16: CL 67 S KR 46-10 CALLE DEL BANCO 10 TOR 2 APT 1505 LAT:6.15402202 LON:-75.61478305 | CD16: CALLE DEL BANCO | CE16: -1 | CF16: 05631000 | CG16: Antioquia - Choco | CH16: SIN PRESENCIA | CI16: 1053346599 | CJ16: JULIAN ALEXANDER CASTELLANOS CASTELLANOS | CK16: CANAL ONLINE | CL16: TELEVENTAS | CM16: ATENTO COLOMBIA S.A. | CN16: CANAL ON LINE - ATENTO OUT BOUND | CT16: 2 | CU16: BA + LB + IPTV | CW16: MTotal_Trio_Voz Ilim Nal _Ba Ancha 900Mbps_IPTV_2_Decos_Mov Ilim_Nac_25425 | CX16: 25425 | DA16: SV | DB16: -1 | DF16: ALTA | DJ16: 900000 | DK16: Cliente Nuevo | DL16: Cliente Nuevo | DN16: TRIO | DR16: jcastellaca1 | DS16: JULIAN ALEXANDER CASTELLANOS CASTELLANOS | DT16: 1053346599 | DV16: 1 | DW16: NOROCCIDENTE | ED16: 46144 | EE16: Sur | EF16: 5 | EP16: 830065842-5 | ES16: SABANETA5 | EZ16: OLT#10.37.80.174 | FA16: CANAL ONLINE | FB16: Antioquia | FD16: Antioquia | FE16: Sabaneta | FF16: Sabaneta | FK16: ATENTO | FL16: 5631000121709318728268|5631000_121709318_PC7-7-05 | FN16: CANAL ON LINE - ATENTO OUT BOUND | FO16: 9900202020034 | FR16: 113904 | GB16: PON | GC16: BA + LB + IPTV | GD16: 25188 | GF16: 2353 | GG16: 25422 | GI16: 87224 | GJ16: 25427 | GL16: 24327 | GM16: 135545 | GS16: FS | GT16: 45077 | GU16: CENTRO EXP | GV16: SIN EMAIL | GW16: Si | GX16: Solo Movil | GY16: Convergente Solo Contrato | GZ16: Convergente Nuevo | HA16: ATP | HE16: Individual | HF16: 615075610 | HG16: Venta Hogar (F) a cliente Pospago | HR16: Asistido | HV16: 118900 | HW16: SI | HX16: Sin movil | HY16: 113921.67 | HZ16: 17.668 | IA16: SI | IB16: NO | IE16: BOGOTA | IF16: BOGOTA | IG16: BOGOTA | IH16: Digital | II16: Fibra | IJ16: B2C | IK16: Asistido | IL16: Outbound | IM16: Atento | IN16: Alta | IP16: - | IQ16: Digital | IS16: ELECTRONICA | IT16: Organico | IW16: Fibra-MovistarTotal-web-BarraFija-LP_MovistarTotal_BarraFija_Asistido | IY16: NO
A17: =DAY(AVANZA[[#This Row],[FechaSeguimiento]]) -> 2 | B17: =MONTH(AVANZA[[#This Row],[FechaSeguimiento]]) -> 5 | C17: =LOWER(IF(AND(AVANZA[[#This Row],[Mes_Reg]]=MONTH(TODAY()),AND(AVANZA[[#This Row],[Dia_Reg]]>0,AVANZA[[#This Row],[Dia_Reg]]<9)),"SEMANA 1","")&IF(AND(AVANZA[[#This Row],[Mes_Reg]]=MONTH(TODAY()),AND(AVANZA[[#This Row],[Dia_Reg]]>8,AVANZA[[#This Row],[Dia_Reg]]<16)),"SEMANA 2","")&IF(AND(AVANZA[[#This Row],[Mes_Reg]]=MONTH(TODAY()),AND(AVANZA[[#This Row],[Dia_Reg]]>15,AVANZA[[#This Row],[Dia_Reg]]<23)),"SEMANA 3","")&IF(AND(AVANZA[[#This Row],[Mes_Reg]]=MONTH(TODAY()),AND(AVANZA[[#This Row],[Dia_Reg]]>22,AVANZA[[#This Row],[Dia_Reg]]<31)),"SEMANA 4","")&IF(AVANZA[[#This Row],[Mes_Reg]]<>MONTH(TODAY()),"BOLSA MES ANTERIOR","")) -> semana 1 | D17: =LOWER(IFERROR(VLOOKUP(AVANZA[[#This Row],[ID_Peticion]],CANCELADAS[#All],2,0),"")) | E17: =LOWER(IFERROR(VLOOKUP(AVANZA[[#This Row],[ID_Peticion]],CANCELADAS[#All],3,0),"")) | F17: =LOWER(IF(AVANZA[[#This Row],[CEDULA CLIENTE]]<>""," CC: " & COUNTIFS(AVANZA[CEDULA CLIENTE],AVANZA[[#This Row],[CEDULA CLIENTE]]),"")& IF(AVANZA[[#This Row],[Direccion]]<>""," DIR: " & COUNTIFS(AVANZA[Direccion],AVANZA[[#This Row],[Direccion]]),"")) -> dir: 1 | G17: =IFERROR(VLOOKUP(AVANZA[[#This Row],[Cedula_Vendedor_Atis]],PLANTA[[#All],[CEDULA]:[LINEA]],3,0),"No Cruza") -> Marisol Avella | H17: =IFERROR(VLOOKUP(AVANZA[[#This Row],[Cedula_Vendedor_Atis]],PLANTA[[#All],[CEDULA]:[LINEA]],4,0),"No Cruza") -> Fija | I17: =LOWER(IF(AVANZA[[#This Row],[ATRIBUIBLE]]="",AVANZA[[#This Row],[Variable]],AVANZA[[#This Row],[ATRIBUIBLE]])) -> terminada | J17: =IF(AVANZA[[#This Row],[Variable]]=AVANZA[[#Headers],[TERMINADA]],1,0) -> 1 | K17: =IF(AVANZA[[#This Row],[Variable]]=AVANZA[[#Headers],[ANULADA]],1,0) -> 0 | L17: =IF(AVANZA[[#This Row],[Variable]]=AVANZA[[#Headers],[PENDIENTE]],1,0) -> 0 | M17: =IF(AVANZA[[#This Row],[ESTADO AGENDA]]="AGENDADA",1,0) -> 0 | N17: =IF(AVANZA[[#This Row],[ESTADO AGENDA]]="PENDIENTE DE AGENDAR",1,0) -> 0 | O17: =IF(AVANZA[[#This Row],[ESTADO AGENDA]]="SUSPENDIDA",1,0) -> 0 | P17: {=_xlfn.XLOOKUP(AVANZA[[#This Row],[Num_Agrupacion_Pet_Atis]],Tabla1[[#All],[Numero_de_actuacion]],Tabla1[[#All],[Estado_de_la_orden]],"",0)} | Q17: {=_xlfn.XLOOKUP(AVANZA[[#This Row],[Num_Agrupacion_Pet_Atis]],Tabla1[[#All],[Numero_de_actuacion]],Tabla1[[#All],[Fecha_de_la_cita]],"",0)} | R17: {=_xlfn.XLOOKUP(AVANZA[[#This Row],[Num_Agrupacion_Pet_Atis]],Tabla1[[#All],[Numero_de_actuacion]],Tabla1[[#All],[Franja_horaria_de_la_cita]],"",0)} | S17: =IFERROR(DAY(AVANZA[[#This Row],[FECHA AGENDA]]),"") | T17: =IFERROR(MONTH(AVANZA[[#This Row],[FECHA AGENDA]]),"") | U17: {=_xlfn.XLOOKUP(AVANZA[[#This Row],[Num_Agrupacion_Pet_Atis]],Tabla1[[#All],[Numero_de_actuacion]],Tabla1[[#All],[Motivo_de_suspension]],"",0)} | V17: {=_xlfn.XLOOKUP(AVANZA[[#This Row],[Num_Agrupacion_Pet_Atis]],Tabla1[[#All],[Numero_de_actuacion]],Tabla1[[#All],[No_identificacion_cliente]],"",0)} | W17: {=_xlfn.XLOOKUP(AVANZA[[#This Row],[Num_Agrupacion_Pet_Atis]],Tabla1[[#All],[Numero_de_actuacion]],Tabla1[[#All],[Movil_de_contacto]],"",0)} | X17: =IF(OR(AVANZA[[#This Row],[ESTADO LEG]]="Legalizada grabacion",AVANZA[[#This Row],[ESTADO LEG]]="Legalizada aut"),1,0) -> 1 | Y17: =IF(OR(AVANZA[[#This Row],[ESTADO LEG]]="pdte legalizar",AVANZA[[#This Row],[ESTADO LEG]]="No cruza"),1,0) -> 0 | Z17: {=IF(AVANZA[[#This Row],[Variable]]="Terminada",LOWER(_xlfn.XLOOKUP(AVANZA[[#This Row],[ID_Peticion]],Tabla6[[#All],[NUM_PETICION]],Tabla6[[#All],[ESTADO_LEG]],"NO CRUZA",0)),AVANZA[[#This Row],[Variable]])} -> legalizada grabacion | AA17: {=_xlfn.XLOOKUP(AVANZA[[#This Row],[ID_Peticion]],Tabla6[[#All],[NUM_PETICION]],Tabla6[[#All],[DIF_DIAS]],"",0)} -> 4 | AB17: {=IFERROR(_xlfn.XLOOKUP(AVANZA[[#This Row],[ID_Peticion]],Tabla6[[#All],[NUM_PETICION]],Tabla6[[#All],[FEC_LEGAL]],"",0),"")} -> 46148 | AC17: =IF(AVANZA[[#This Row],[FECHA LEG]]<>0,IFERROR(AVANZA[[#This Row],[FECHA LEG]]-AVANZA[[#This Row],[FechaIniEstadoSubPetAtis]],0),TODAY()-AVANZA[[#This Row],[FechaIniEstadoSubPetAtis]]) -> 4 | AD17: =IF(AVANZA[[#This Row],[FINAL Vs LG]]<>0,IF(AVANZA[[#This Row],[FINAL Vs LG]]<7.1,"100%",IF(AND(AVANZA[[#This Row],[FINAL Vs LG]]>7.1,AVANZA[[#This Row],[FINAL Vs LG]]<11.1),"50%","0%")),0) -> 100% | AE17: =VLOOKUP(DAY(TODAY()),BACK!F:G,2,0) -> 14 | AF17: =BACK!$I$2 -> 24 | AG17: =IF(AVANZA[[#This Row],[Oferta_empaquetada_comisiones]]="SI",1,0) -> 0 | AH17: =IF(AVANZA[[#This Row],[Variable]]="TERMINADA",IFERROR(VLOOKUP(AVANZA[[#This Row],[SUPERVISOR]],Tabla2[#All],4,0),0),) -> 3.5 | AI17: =IF(AVANZA[[#This Row],[Producto]]="BA",1,0) -> 1 | AJ17: =IF(AVANZA[[#This Row],[Producto]]="DUO",1,0) -> 0 | AK17: =IF(AVANZA[[#This Row],[Producto]]="TRIO",1,0) -> 0 | AL17: 1526683800046962252 | AM17: -1 | AN17: -1 | AO17: 1786059022 | AP17: 46143.603 | AQ17: -1 | AR17: 2512690901 | AS17: -1 | AT17: -1 | AU17: -1 | AV17: -1 | AW17: -1 | AX17: FixedCreateSubscriber | AY17: -1 | AZ17: 2026 | BA17: 5 | BB17: 2 | BC17: -1 | BD17: Broadband Service | BE17: -1 | BF17: 20001621098286 | BG17: Plan Banda Ancha 900Mbps Solo Internet_Nac_25423 | BH17: 25423 | BI17: FS202605011426551793 | BJ17: -1 | BK17: -1 | BL17: -1 | BM17: TERMINADA | BN17: Individual | BO17: 6108779209 | BP17: Gold | BQ17: 2026 | BR17: 5 | BS17: 1 | BT17: 46144.699 | BU17: OS90 | BV17: 46144 | BW17: Completed | BX17: 46143 | BY17: 46144 | BZ17: Call Back To CRM | CA17: BOGOTA, D.C. | CB17: BOGOTA, D.C. | CC17: CL 22 KR 100-82 SANTANDER-FONTIBON 82 APT 301 LAT:4.6773914 LON:-74.14143339 | CD17: SANTANDER-FONTIBON | CE17: -1 | CF17: 11001000 | CG17: Bogota | CH17: ATACANTE | CI17: 73211780 | CJ17: WALTER BERRIO GONZALEZ | CK17: CANAL ONLINE | CL17: ON LINE | CM17: ATENTO COLOMBIA S.A. | CN17: CANAL ON LINE - ATENTO IN BOUND | CT17: 3 | CU17: Broadband Service | CW17: Plan Banda Ancha 900Mbps Solo Internet_Nac_25423 | CX17: 25423 | DA17: SV | DB17: -1 | DF17: ALTA | DJ17: 900000 | DK17: Cliente Nuevo | DL17: Cliente Existente | DN17: BA | DR17: wberriogo | DS17: WALTER BERRIO GONZALEZ | DT17: 73211780 | DV17: 1 | DW17: BOGOTA | ED17: 46144 | EE17: Occidente | EF17: 9 | EP17: 830065842-5 | ES17: 139 | FA17: CANAL ONLINE | FB17: Bogotá D.C | FD17: Bogotá D.C | FE17: Bogotá | FF17: Bogotá | FK17: ATENTO | FL17: 11001000OH_BOGALCGOS_I_7360_32030_BogotaColfrigosCOLFR-CT2/3-29-02SS2-29-02@11001000_OH_BOGALCGOS_I_7360_32030_BogotaColfrigos_COLFR-CT2/3-29-02_SS2-29- | FN17: CANAL ON LINE - ATENTO IN BOUND | FO17: 9900202020035 | FR17: 94990 | GB17: PON | GC17: Broadband Service | GD17: 0 | GF17: 0 | GG17: 25423 | GI17: 94990 | GJ17: 0 | GL17: 0 | GM17: 113038 | GS17: FS | GT17: 45199 | GU17: CENTRO EXP | GV17: SIN EMAIL | GW17: No | GZ17: No Convergente | HA17: ONNET | HB17: BOGOTA 1 | HC17: BOGOTA 1 | HD17: BOGOTA NORTE | HE17: Individual | HF17: 467574140 | HR17: Asistido | HV17: 94990 | HW17: NO | HY17: 0 | HZ17: 0 | IA17: NO | IB17: NO | IE17: BOGOTA | IF17: BOGOTA | IG17: BOGOTA | IH17: Digital | II17: Fibra | IJ17: B2C | IK17: Asistido | IL17: Inbound | IM17: Atento | IN17: Alta | IP17: - | IQ17: Digital | IS17: ELECTRONICA | IT17: Googleads_Oferta | IU17: CO_MARCA_COL-PUREBRAND-B2C_22-02-16_SEM_LDS-WEB_AON_RMKT_BRAND | IV17: SEM_SEM_CPL | IW17: Fija-Fibra-web-CajadeProducto-LP-pauta-fibra | IY17: NO
A18: =DAY(AVANZA[[#This Row],[FechaSeguimiento]]) -> 2 | B18: =MONTH(AVANZA[[#This Row],[FechaSeguimiento]]) -> 5 | C18: =LOWER(IF(AND(AVANZA[[#This Row],[Mes_Reg]]=MONTH(TODAY()),AND(AVANZA[[#This Row],[Dia_Reg]]>0,AVANZA[[#This Row],[Dia_Reg]]<9)),"SEMANA 1","")&IF(AND(AVANZA[[#This Row],[Mes_Reg]]=MONTH(TODAY()),AND(AVANZA[[#This Row],[Dia_Reg]]>8,AVANZA[[#This Row],[Dia_Reg]]<16)),"SEMANA 2","")&IF(AND(AVANZA[[#This Row],[Mes_Reg]]=MONTH(TODAY()),AND(AVANZA[[#This Row],[Dia_Reg]]>15,AVANZA[[#This Row],[Dia_Reg]]<23)),"SEMANA 3","")&IF(AND(AVANZA[[#This Row],[Mes_Reg]]=MONTH(TODAY()),AND(AVANZA[[#This Row],[Dia_Reg]]>22,AVANZA[[#This Row],[Dia_Reg]]<31)),"SEMANA 4","")&IF(AVANZA[[#This Row],[Mes_Reg]]<>MONTH(TODAY()),"BOLSA MES ANTERIOR","")) -> bolsa mes anterior | D18: =LOWER(IFERROR(VLOOKUP(AVANZA[[#This Row],[ID_Peticion]],CANCELADAS[#All],2,0),"")) | E18: =LOWER(IFERROR(VLOOKUP(AVANZA[[#This Row],[ID_Peticion]],CANCELADAS[#All],3,0),"")) | F18: =LOWER(IF(AVANZA[[#This Row],[CEDULA CLIENTE]]<>""," CC: " & COUNTIFS(AVANZA[CEDULA CLIENTE],AVANZA[[#This Row],[CEDULA CLIENTE]]),"")& IF(AVANZA[[#This Row],[Direccion]]<>""," DIR: " & COUNTIFS(AVANZA[Direccion],AVANZA[[#This Row],[Direccion]]),"")) -> dir: 1 | G18: =IFERROR(VLOOKUP(AVANZA[[#This Row],[Cedula_Vendedor_Atis]],PLANTA[[#All],[CEDULA]:[LINEA]],3,0),"No Cruza") -> Marisol Avella | H18: =IFERROR(VLOOKUP(AVANZA[[#This Row],[Cedula_Vendedor_Atis]],PLANTA[[#All],[CEDULA]:[LINEA]],4,0),"No Cruza") -> Fija | I18: =LOWER(IF(AVANZA[[#This Row],[ATRIBUIBLE]]="",AVANZA[[#This Row],[Variable]],AVANZA[[#This Row],[ATRIBUIBLE]])) -> terminada | J18: =IF(AVANZA[[#This Row],[Variable]]=AVANZA[[#Headers],[TERMINADA]],1,0) -> 1 | K18: =IF(AVANZA[[#This Row],[Variable]]=AVANZA[[#Headers],[ANULADA]],1,0) -> 0 | L18: =IF(AVANZA[[#This Row],[Variable]]=AVANZA[[#Headers],[PENDIENTE]],1,0) -> 0 | M18: =IF(AVANZA[[#This Row],[ESTADO AGENDA]]="AGENDADA",1,0) -> 0 | N18: =IF(AVANZA[[#This Row],[ESTADO AGENDA]]="PENDIENTE DE AGENDAR",1,0) -> 0 | O18: =IF(AVANZA[[#This Row],[ESTADO AGENDA]]="SUSPENDIDA",1,0) -> 0 | P18: {=_xlfn.XLOOKUP(AVANZA[[#This Row],[Num_Agrupacion_Pet_Atis]],Tabla1[[#All],[Numero_de_actuacion]],Tabla1[[#All],[Estado_de_la_orden]],"",0)} | Q18: {=_xlfn.XLOOKUP(AVANZA[[#This Row],[Num_Agrupacion_Pet_Atis]],Tabla1[[#All],[Numero_de_actuacion]],Tabla1[[#All],[Fecha_de_la_cita]],"",0)} | R18: {=_xlfn.XLOOKUP(AVANZA[[#This Row],[Num_Agrupacion_Pet_Atis]],Tabla1[[#All],[Numero_de_actuacion]],Tabla1[[#All],[Franja_horaria_de_la_cita]],"",0)} | S18: =IFERROR(DAY(AVANZA[[#This Row],[FECHA AGENDA]]),"") | T18: =IFERROR(MONTH(AVANZA[[#This Row],[FECHA AGENDA]]),"") | U18: {=_xlfn.XLOOKUP(AVANZA[[#This Row],[Num_Agrupacion_Pet_Atis]],Tabla1[[#All],[Numero_de_actuacion]],Tabla1[[#All],[Motivo_de_suspension]],"",0)} | V18: {=_xlfn.XLOOKUP(AVANZA[[#This Row],[Num_Agrupacion_Pet_Atis]],Tabla1[[#All],[Numero_de_actuacion]],Tabla1[[#All],[No_identificacion_cliente]],"",0)} | W18: {=_xlfn.XLOOKUP(AVANZA[[#This Row],[Num_Agrupacion_Pet_Atis]],Tabla1[[#All],[Numero_de_actuacion]],Tabla1[[#All],[Movil_de_contacto]],"",0)} | X18: =IF(OR(AVANZA[[#This Row],[ESTADO LEG]]="Legalizada grabacion",AVANZA[[#This Row],[ESTADO LEG]]="Legalizada aut"),1,0) -> 1 | Y18: =IF(OR(AVANZA[[#This Row],[ESTADO LEG]]="pdte legalizar",AVANZA[[#This Row],[ESTADO LEG]]="No cruza"),1,0) -> 0 | Z18: {=IF(AVANZA[[#This Row],[Variable]]="Terminada",LOWER(_xlfn.XLOOKUP(AVANZA[[#This Row],[ID_Peticion]],Tabla6[[#All],[NUM_PETICION]],Tabla6[[#All],[ESTADO_LEG]],"NO CRUZA",0)),AVANZA[[#This Row],[Variable]])} -> legalizada grabacion | AA18: {=_xlfn.XLOOKUP(AVANZA[[#This Row],[ID_Peticion]],Tabla6[[#All],[NUM_PETICION]],Tabla6[[#All],[DIF_DIAS]],"",0)} -> 4 | AB18: {=IFERROR(_xlfn.XLOOKUP(AVANZA[[#This Row],[ID_Peticion]],Tabla6[[#All],[NUM_PETICION]],Tabla6[[#All],[FEC_LEGAL]],"",0),"")} -> 46148 | AC18: =IF(AVANZA[[#This Row],[FECHA LEG]]<>0,IFERROR(AVANZA[[#This Row],[FECHA LEG]]-AVANZA[[#This Row],[FechaIniEstadoSubPetAtis]],0),TODAY()-AVANZA[[#This Row],[FechaIniEstadoSubPetAtis]]) -> 4 | AD18: =IF(AVANZA[[#This Row],[FINAL Vs LG]]<>0,IF(AVANZA[[#This Row],[FINAL Vs LG]]<7.1,"100%",IF(AND(AVANZA[[#This Row],[FINAL Vs LG]]>7.1,AVANZA[[#This Row],[FINAL Vs LG]]<11.1),"50%","0%")),0) -> 100% | AE18: =VLOOKUP(DAY(TODAY()),BACK!F:G,2,0) -> 14 | AF18: =BACK!$I$2 -> 24 | AG18: =IF(AVANZA[[#This Row],[Oferta_empaquetada_comisiones]]="SI",1,0) -> 0 | AH18: =IF(AVANZA[[#This Row],[Variable]]="TERMINADA",IFERROR(VLOOKUP(AVANZA[[#This Row],[SUPERVISOR]],Tabla2[#All],4,0),0),) -> 3.5 | AI18: =IF(AVANZA[[#This Row],[Producto]]="BA",1,0) -> 1 | AJ18: =IF(AVANZA[[#This Row],[Producto]]="DUO",1,0) -> 0 | AK18: =IF(AVANZA[[#This Row],[Producto]]="TRIO",1,0) -> 0 | AL18: 1015443152 | AM18: -1 | AN18: -1 | AO18: 1785012343 | AP18: 46141.812 | AQ18: -1 | AR18: 2512687821 | AS18: -1 | AT18: -1 | AU18: -1 | AV18: -1 | AW18: -1 | AX18: FixedCreateSubscriber | AY18: -1 | AZ18: 2026 | BA18: 5 | BB18: 2 | BC18: -1 | BD18: Broadband Service | BE18: -1 | BF18: 20001620142695 | BG18: Plan Banda Ancha 900Mbps Solo Internet_Nac_25423 | BH18: 25423 | BI18: FS202604291928041389 | BJ18: -1 | BK18: -1 | BL18: -1 | BM18: TERMINADA | BN18: Individual | BO18: 6108749638 | BP18: Gold | BQ18: 2026 | BR18: 4 | BS18: 29 | BT18: 46144.439 | BU18: OS90 | BV18: 46144 | BW18: Completed | BX18: 46141 | BY18: 46144 | BZ18: Call Back To CRM | CA18: BOGOTA, D.C. | CB18: BOGOTA, D.C. | CC18: KR 28 CL 68-83 ALCAZARES 83 LCA 101 LAT:4.66238502 LON:-74.07239626 | CD18: ALCAZARES | CE18: -1 | CF18: 11001000 | CG18: Bogota | CH18: ATACANTE | CI18: 1015443152 | CJ18: BRAYAN NICOLAS SIERRA RODRIGUEZ | CK18: CANAL ONLINE | CL18: TELEVENTAS | CM18: ATENTO COLOMBIA S.A. | CN18: CANAL ON LINE - ATENTO OUT BOUND | CT18: 3 | CU18: Broadband Service | CW18: Plan Banda Ancha 900Mbps Solo Internet_Nac_25423 | CX18: 25423 | DA18: SV | DB18: -1 | DF18: ALTA | DJ18: 900000 | DK18: Cliente Nuevo | DL18: Cliente Existente | DN18: BA | DR18: bnsierraro | DS18: BRAYAN NICOLAS SIERRA RODRIGUEZ | DT18: 1015443152 | DV18: 1 | DW18: BOGOTA | ED18: 46144 | EE18: Occidente | EF18: 5 | EP18: 830065842-5 | ES18: 37 | EZ18: OLT#10.37.80.46 | FA18: CANAL ONLINE | FB18: Bogotá D.C | FD18: Bogotá D.C | FE18: Bogotá | FF18: Bogotá | FK18: ATENTO | FL18: 11001000113171044181634|11001000_181634_CT5/6-42-07 | FN18: CANAL ON LINE - ATENTO OUT BOUND | FO18: 9900202020034 | FR18: 94990 | GB18: PON | GC18: Broadband Service | GD18: 0 | GF18: 0 | GG18: 25423 | GI18: 94990 | GJ18: 0 | GL18: 0 | GM18: 113038 | GS18: FS | GT18: 44469 | GU18: CENTRO EXP | GV18: SIN EMAIL | GW18: No | GZ18: No Convergente | HA18: ATP | HE18: Individual | HF18: 466074070 | HR18: Asistido | HV18: 94990 | HW18: NO | HY18: 0 | HZ18: 0 | IA18: SI | IB18: NO | IE18: BOGOTA | IF18: BOGOTA | IG18: BOGOTA | IH18: Digital | II18: Fibra | IJ18: B2C | IK18: Asistido | IL18: Inbound | IM18: Atento | IN18: Alta | IP18: - | IQ18: Digital | IS18: ELECTRONICA | IT18: Inbound | IY18: NO
A19: =DAY(AVANZA[[#This Row],[FechaSeguimiento]]) -> 2 | B19: =MONTH(AVANZA[[#This Row],[FechaSeguimiento]]) -> 5 | C19: =LOWER(IF(AND(AVANZA[[#This Row],[Mes_Reg]]=MONTH(TODAY()),AND(AVANZA[[#This Row],[Dia_Reg]]>0,AVANZA[[#This Row],[Dia_Reg]]<9)),"SEMANA 1","")&IF(AND(AVANZA[[#This Row],[Mes_Reg]]=MONTH(TODAY()),AND(AVANZA[[#This Row],[Dia_Reg]]>8,AVANZA[[#This Row],[Dia_Reg]]<16)),"SEMANA 2","")&IF(AND(AVANZA[[#This Row],[Mes_Reg]]=MONTH(TODAY()),AND(AVANZA[[#This Row],[Dia_Reg]]>15,AVANZA[[#This Row],[Dia_Reg]]<23)),"SEMANA 3","")&IF(AND(AVANZA[[#This Row],[Mes_Reg]]=MONTH(TODAY()),AND(AVANZA[[#This Row],[Dia_Reg]]>22,AVANZA[[#This Row],[Dia_Reg]]<31)),"SEMANA 4","")&IF(AVANZA[[#This Row],[Mes_Reg]]<>MONTH(TODAY()),"BOLSA MES ANTERIOR","")) -> semana 1 | D19: =LOWER(IFERROR(VLOOKUP(AVANZA[[#This Row],[ID_Peticion]],CANCELADAS[#All],2,0),"")) | E19: =LOWER(IFERROR(VLOOKUP(AVANZA[[#This Row],[ID_Peticion]],CANCELADAS[#All],3,0),"")) | F19: =LOWER(IF(AVANZA[[#This Row],[CEDULA CLIENTE]]<>""," CC: " & COUNTIFS(AVANZA[CEDULA CLIENTE],AVANZA[[#This Row],[CEDULA CLIENTE]]),"")& IF(AVANZA[[#This Row],[Direccion]]<>""," DIR: " & COUNTIFS(AVANZA[Direccion],AVANZA[[#This Row],[Direccion]]),"")) -> dir: 1 | G19: =IFERROR(VLOOKUP(AVANZA[[#This Row],[Cedula_Vendedor_Atis]],PLANTA[[#All],[CEDULA]:[LINEA]],3,0),"No Cruza") -> Marisol Avella | H19: =IFERROR(VLOOKUP(AVANZA[[#This Row],[Cedula_Vendedor_Atis]],PLANTA[[#All],[CEDULA]:[LINEA]],4,0),"No Cruza") -> Fija | I19: =LOWER(IF(AVANZA[[#This Row],[ATRIBUIBLE]]="",AVANZA[[#This Row],[Variable]],AVANZA[[#This Row],[ATRIBUIBLE]])) -> terminada | J19: =IF(AVANZA[[#This Row],[Variable]]=AVANZA[[#Headers],[TERMINADA]],1,0) -> 1 | K19: =IF(AVANZA[[#This Row],[Variable]]=AVANZA[[#Headers],[ANULADA]],1,0) -> 0 | L19: =IF(AVANZA[[#This Row],[Variable]]=AVANZA[[#Headers],[PENDIENTE]],1,0) -> 0 | M19: =IF(AVANZA[[#This Row],[ESTADO AGENDA]]="AGENDADA",1,0) -> 0 | N19: =IF(AVANZA[[#This Row],[ESTADO AGENDA]]="PENDIENTE DE AGENDAR",1,0) -> 0 | O19: =IF(AVANZA[[#This Row],[ESTADO AGENDA]]="SUSPENDIDA",1,0) -> 0 | P19: {=_xlfn.XLOOKUP(AVANZA[[#This Row],[Num_Agrupacion_Pet_Atis]],Tabla1[[#All],[Numero_de_actuacion]],Tabla1[[#All],[Estado_de_la_orden]],"",0)} | Q19: {=_xlfn.XLOOKUP(AVANZA[[#This Row],[Num_Agrupacion_Pet_Atis]],Tabla1[[#All],[Numero_de_actuacion]],Tabla1[[#All],[Fecha_de_la_cita]],"",0)} | R19: {=_xlfn.XLOOKUP(AVANZA[[#This Row],[Num_Agrupacion_Pet_Atis]],Tabla1[[#All],[Numero_de_actuacion]],Tabla1[[#All],[Franja_horaria_de_la_cita]],"",0)} | S19: =IFERROR(DAY(AVANZA[[#This Row],[FECHA AGENDA]]),"") | T19: =IFERROR(MONTH(AVANZA[[#This Row],[FECHA AGENDA]]),"") | U19: {=_xlfn.XLOOKUP(AVANZA[[#This Row],[Num_Agrupacion_Pet_Atis]],Tabla1[[#All],[Numero_de_actuacion]],Tabla1[[#All],[Motivo_de_suspension]],"",0)} | V19: {=_xlfn.XLOOKUP(AVANZA[[#This Row],[Num_Agrupacion_Pet_Atis]],Tabla1[[#All],[Numero_de_actuacion]],Tabla1[[#All],[No_identificacion_cliente]],"",0)} | W19: {=_xlfn.XLOOKUP(AVANZA[[#This Row],[Num_Agrupacion_Pet_Atis]],Tabla1[[#All],[Numero_de_actuacion]],Tabla1[[#All],[Movil_de_contacto]],"",0)} | X19: =IF(OR(AVANZA[[#This Row],[ESTADO LEG]]="Legalizada grabacion",AVANZA[[#This Row],[ESTADO LEG]]="Legalizada aut"),1,0) -> 1 | Y19: =IF(OR(AVANZA[[#This Row],[ESTADO LEG]]="pdte legalizar",AVANZA[[#This Row],[ESTADO LEG]]="No cruza"),1,0) -> 0 | Z19: {=IF(AVANZA[[#This Row],[Variable]]="Terminada",LOWER(_xlfn.XLOOKUP(AVANZA[[#This Row],[ID_Peticion]],Tabla6[[#All],[NUM_PETICION]],Tabla6[[#All],[ESTADO_LEG]],"NO CRUZA",0)),AVANZA[[#This Row],[Variable]])} -> legalizada grabacion | AA19: {=_xlfn.XLOOKUP(AVANZA[[#This Row],[ID_Peticion]],Tabla6[[#All],[NUM_PETICION]],Tabla6[[#All],[DIF_DIAS]],"",0)} -> 4 | AB19: {=IFERROR(_xlfn.XLOOKUP(AVANZA[[#This Row],[ID_Peticion]],Tabla6[[#All],[NUM_PETICION]],Tabla6[[#All],[FEC_LEGAL]],"",0),"")} -> 46148 | AC19: =IF(AVANZA[[#This Row],[FECHA LEG]]<>0,IFERROR(AVANZA[[#This Row],[FECHA LEG]]-AVANZA[[#This Row],[FechaIniEstadoSubPetAtis]],0),TODAY()-AVANZA[[#This Row],[FechaIniEstadoSubPetAtis]]) -> 4 | AD19: =IF(AVANZA[[#This Row],[FINAL Vs LG]]<>0,IF(AVANZA[[#This Row],[FINAL Vs LG]]<7.1,"100%",IF(AND(AVANZA[[#This Row],[FINAL Vs LG]]>7.1,AVANZA[[#This Row],[FINAL Vs LG]]<11.1),"50%","0%")),0) -> 100% | AE19: =VLOOKUP(DAY(TODAY()),BACK!F:G,2,0) -> 14 | AF19: =BACK!$I$2 -> 24 | AG19: =IF(AVANZA[[#This Row],[Oferta_empaquetada_comisiones]]="SI",1,0) -> 0 | AH19: =IF(AVANZA[[#This Row],[Variable]]="TERMINADA",IFERROR(VLOOKUP(AVANZA[[#This Row],[SUPERVISOR]],Tabla2[#All],4,0),0),) -> 3.5 | AI19: =IF(AVANZA[[#This Row],[Producto]]="BA",1,0) -> 1 | AJ19: =IF(AVANZA[[#This Row],[Producto]]="DUO",1,0) -> 0 | AK19: =IF(AVANZA[[#This Row],[Producto]]="TRIO",1,0) -> 0 | AL19: 53061857 | AM19: -1 | AN19: -1 | AO19: 1785868483 | AP19: 46143.491 | AQ19: -1 | AR19: 2512691189 | AS19: -1 | AT19: -1 | AU19: -1 | AV19: -1 | AW19: -1 | AX19: FixedCreateSubscriber | AY19: -1 | AZ19: 2026 | BA19: 5 | BB19: 2 | BC19: -1 | BD19: Broadband Service | BE19: -1 | BF19: 20001621113968 | BG19: Plan Banda Ancha 900Mbps Solo Internet_Nac_25423 | BH19: 25423 | BI19: FS202605011147221818 | BJ19: -1 | BK19: -1 | BL19: -1 | BM19: TERMINADA | BN19: Individual | BO19: 6108780226 | BP19: Gold | BQ19: 2026 | BR19: 5 | BS19: 1 | BT19: 46144.456 | BU19: OS90 | BV19: 46144 | BW19: Completed | BX19: 46143 | BY19: 46144 | BZ19: Call Back To CRM | CA19: PIEDECUESTA | CB19: SANTANDER | CC19: CL 4 A N KR 1 W-57 EL REFUGIO 57 LAT:6.99458745 LON:-73.06377832 | CD19: EL REFUGIO | CE19: -1 | CF19: 68547000 | CG19: Arauca - Santander | CH19: INCUMBENTE COMPETITIVO | CI19: 53061857 | CJ19: NOHORA AMADO LONDONO | CK19: CANAL ONLINE | CL19: ON LINE | CM19: ATENTO COLOMBIA S.A. | CN19: CANAL ON LINE - ATENTO CLICK TO CALL | CT19: 2 | CU19: Broadband Service | CW19: Plan Banda Ancha 900Mbps Solo Internet_Nac_25423 | CX19: 25423 | DA19: SV | DB19: -1 | DF19: ALTA | DJ19: 900000 | DK19: Cliente Nuevo | DL19: Cliente Existente | DN19: BA | DR19: namadolo | DS19: NOHORA AMADO LONDONO | DT19: 53061857 | DV19: 1 | DW19: ORIENTE | ED19: 46144 | EF19: 9 | EP19: 830065842-5 | ES19: GUATIGUARA | FA19: CANAL ONLINE | FB19: Santander | FD19: Santander | FE19: Piedecuesta | FF19: Piedecuesta | FK19: ATENTO | FL19: 68547000OH_SANALPSTC_I_7360_Piedecuesta_3PIEDE-CT1-44-08SS1-44-08@68547000_OH_SANALPSTC_I_7360_Piedecuesta_3_PIEDE-CT1-44-08_SS1-44-08 | FN19: CANAL ON LINE - ATENTO CLICK TO CALL | FO19: 9900202020033 | FR19: 94990 | GB19: PON | GC19: Broadband Service | GD19: 0 | GF19: 0 | GG19: 25423 | GI19: 94990 | GJ19: 0 | GL19: 0 | GM19: 113038 | GS19: FS | GT19: 45077 | GU19: CENTRO EXP | GV19: VALIDADO | GW19: No | GZ19: No Convergente | HA19: ONNET | HB19: SANTANDER (AREA METROPOLITANA 1) | HC19: PIEDECUESTA | HD19: ORIENTE | HE19: Individual | HF19: 699073060 | HR19: Asistido | HV19: 94990 | HW19: NO | HY19: 0 | HZ19: 0 | IA19: NO | IB19: NO | IE19: BOGOTA | IF19: BOGOTA | IG19: BOGOTA | IH19: Digital | II19: Fibra | IJ19: B2C | IK19: Asistido | IL19: C2C | IM19: Atento | IN19: Alta | IP19: - | IQ19: Digital | IS19: ELECTRONICA | IT19: WhatsApp Bot | IY19: NO
A20: =DAY(AVANZA[[#This Row],[FechaSeguimiento]]) -> 2 | B20: =MONTH(AVANZA[[#This Row],[FechaSeguimiento]]) -> 5 | C20: =LOWER(IF(AND(AVANZA[[#This Row],[Mes_Reg]]=MONTH(TODAY()),AND(AVANZA[[#This Row],[Dia_Reg]]>0,AVANZA[[#This Row],[Dia_Reg]]<9)),"SEMANA 1","")&IF(AND(AVANZA[[#This Row],[Mes_Reg]]=MONTH(TODAY()),AND(AVANZA[[#This Row],[Dia_Reg]]>8,AVANZA[[#This Row],[Dia_Reg]]<16)),"SEMANA 2","")&IF(AND(AVANZA[[#This Row],[Mes_Reg]]=MONTH(TODAY()),AND(AVANZA[[#This Row],[Dia_Reg]]>15,AVANZA[[#This Row],[Dia_Reg]]<23)),"SEMANA 3","")&IF(AND(AVANZA[[#This Row],[Mes_Reg]]=MONTH(TODAY()),AND(AVANZA[[#This Row],[Dia_Reg]]>22,AVANZA[[#This Row],[Dia_Reg]]<31)),"SEMANA 4","")&IF(AVANZA[[#This Row],[Mes_Reg]]<>MONTH(TODAY()),"BOLSA MES ANTERIOR","")) -> semana 1 | D20: =LOWER(IFERROR(VLOOKUP(AVANZA[[#This Row],[ID_Peticion]],CANCELADAS[#All],2,0),"")) | E20: =LOWER(IFERROR(VLOOKUP(AVANZA[[#This Row],[ID_Peticion]],CANCELADAS[#All],3,0),"")) | F20: =LOWER(IF(AVANZA[[#This Row],[CEDULA CLIENTE]]<>""," CC: " & COUNTIFS(AVANZA[CEDULA CLIENTE],AVANZA[[#This Row],[CEDULA CLIENTE]]),"")& IF(AVANZA[[#This Row],[Direccion]]<>""," DIR: " & COUNTIFS(AVANZA[Direccion],AVANZA[[#This Row],[Direccion]]),"")) -> dir: 1 | G20: =IFERROR(VLOOKUP(AVANZA[[#This Row],[Cedula_Vendedor_Atis]],PLANTA[[#All],[CEDULA]:[LINEA]],3,0),"No Cruza") -> Marisol Avella | H20: =IFERROR(VLOOKUP(AVANZA[[#This Row],[Cedula_Vendedor_Atis]],PLANTA[[#All],[CEDULA]:[LINEA]],4,0),"No Cruza") -> Fija | I20: =LOWER(IF(AVANZA[[#This Row],[ATRIBUIBLE]]="",AVANZA[[#This Row],[Variable]],AVANZA[[#This Row],[ATRIBUIBLE]])) -> terminada | J20: =IF(AVANZA[[#This Row],[Variable]]=AVANZA[[#Headers],[TERMINADA]],1,0) -> 1 | K20: =IF(AVANZA[[#This Row],[Variable]]=AVANZA[[#Headers],[ANULADA]],1,0) -> 0 | L20: =IF(AVANZA[[#This Row],[Variable]]=AVANZA[[#Headers],[PENDIENTE]],1,0) -> 0 | M20: =IF(AVANZA[[#This Row],[ESTADO AGENDA]]="AGENDADA",1,0) -> 0 | N20: =IF(AVANZA[[#This Row],[ESTADO AGENDA]]="PENDIENTE DE AGENDAR",1,0) -> 0 | O20: =IF(AVANZA[[#This Row],[ESTADO AGENDA]]="SUSPENDIDA",1,0) -> 0 | P20: {=_xlfn.XLOOKUP(AVANZA[[#This Row],[Num_Agrupacion_Pet_Atis]],Tabla1[[#All],[Numero_de_actuacion]],Tabla1[[#All],[Estado_de_la_orden]],"",0)} | Q20: {=_xlfn.XLOOKUP(AVANZA[[#This Row],[Num_Agrupacion_Pet_Atis]],Tabla1[[#All],[Numero_de_actuacion]],Tabla1[[#All],[Fecha_de_la_cita]],"",0)} | R20: {=_xlfn.XLOOKUP(AVANZA[[#This Row],[Num_Agrupacion_Pet_Atis]],Tabla1[[#All],[Numero_de_actuacion]],Tabla1[[#All],[Franja_horaria_de_la_cita]],"",0)} | S20: =IFERROR(DAY(AVANZA[[#This Row],[FECHA AGENDA]]),"") | T20: =IFERROR(MONTH(AVANZA[[#This Row],[FECHA AGENDA]]),"") | U20: {=_xlfn.XLOOKUP(AVANZA[[#This Row],[Num_Agrupacion_Pet_Atis]],Tabla1[[#All],[Numero_de_actuacion]],Tabla1[[#All],[Motivo_de_suspension]],"",0)} | V20: {=_xlfn.XLOOKUP(AVANZA[[#This Row],[Num_Agrupacion_Pet_Atis]],Tabla1[[#All],[Numero_de_actuacion]],Tabla1[[#All],[No_identificacion_cliente]],"",0)} | W20: {=_xlfn.XLOOKUP(AVANZA[[#This Row],[Num_Agrupacion_Pet_Atis]],Tabla1[[#All],[Numero_de_actuacion]],Tabla1[[#All],[Movil_de_contacto]],"",0)} | X20: =IF(OR(AVANZA[[#This Row],[ESTADO LEG]]="Legalizada grabacion",AVANZA[[#This Row],[ESTADO LEG]]="Legalizada aut"),1,0) -> 1 | Y20: =IF(OR(AVANZA[[#This Row],[ESTADO LEG]]="pdte legalizar",AVANZA[[#This Row],[ESTADO LEG]]="No cruza"),1,0) -> 0 | Z20: {=IF(AVANZA[[#This Row],[Variable]]="Terminada",LOWER(_xlfn.XLOOKUP(AVANZA[[#This Row],[ID_Peticion]],Tabla6[[#All],[NUM_PETICION]],Tabla6[[#All],[ESTADO_LEG]],"NO CRUZA",0)),AVANZA[[#This Row],[Variable]])} -> legalizada grabacion | AA20: {=_xlfn.XLOOKUP(AVANZA[[#This Row],[ID_Peticion]],Tabla6[[#All],[NUM_PETICION]],Tabla6[[#All],[DIF_DIAS]],"",0)} -> 4 | AB20: {=IFERROR(_xlfn.XLOOKUP(AVANZA[[#This Row],[ID_Peticion]],Tabla6[[#All],[NUM_PETICION]],Tabla6[[#All],[FEC_LEGAL]],"",0),"")} -> 46148 | AC20: =IF(AVANZA[[#This Row],[FECHA LEG]]<>0,IFERROR(AVANZA[[#This Row],[FECHA LEG]]-AVANZA[[#This Row],[FechaIniEstadoSubPetAtis]],0),TODAY()-AVANZA[[#This Row],[FechaIniEstadoSubPetAtis]]) -> 4 | AD20: =IF(AVANZA[[#This Row],[FINAL Vs LG]]<>0,IF(AVANZA[[#This Row],[FINAL Vs LG]]<7.1,"100%",IF(AND(AVANZA[[#This Row],[FINAL Vs LG]]>7.1,AVANZA[[#This Row],[FINAL Vs LG]]<11.1),"50%","0%")),0) -> 100% | AE20: =VLOOKUP(DAY(TODAY()),BACK!F:G,2,0) -> 14 | AF20: =BACK!$I$2 -> 24 | AG20: =IF(AVANZA[[#This Row],[Oferta_empaquetada_comisiones]]="SI",1,0) -> 0 | AH20: =IF(AVANZA[[#This Row],[Variable]]="TERMINADA",IFERROR(VLOOKUP(AVANZA[[#This Row],[SUPERVISOR]],Tabla2[#All],4,0),0),) -> 3.5 | AI20: =IF(AVANZA[[#This Row],[Producto]]="BA",1,0) -> 0 | AJ20: =IF(AVANZA[[#This Row],[Producto]]="DUO",1,0) -> 0 | AK20: =IF(AVANZA[[#This Row],[Producto]]="TRIO",1,0) -> 1 | AL20: 1648048636331251387 | AM20: -1 | AN20: -1 | AO20: 1785856239 | AP20: 46143.347 | AQ20: -1 | AR20: 2512690703 | AS20: -1 | AT20: -1 | AU20: -1 | AV20: -1 | AW20: -1 | AX20: FixedCreateSubscriber | AY20: -1 | AZ20: 2026 | BA20: 5 | BB20: 2 | BC20: -1 | BD20: Broadband Service | BE20: -1 | BF20: 20001620890788 | BG20: Convergente_Plan Ancha 900Mbps_Mov Ilim_Trio_25422 | BH20: 25422 | BI20: FS202605010817092002 | BJ20: -1 | BK20: -1 | BL20: -1 | BM20: TERMINADA | BN20: Individual | BO20: 6080347152 | BP20: Movistar Total | BQ20: 2026 | BR20: 5 | BS20: 1 | BT20: 46144.449 | BU20: OS90 | BV20: 46144 | BW20: Completed | BX20: 46143 | BY20: 46144 | BZ20: Call Back To CRM | CA20: BOGOTA, D.C. | CB20: BOGOTA, D.C. | CC20: CL 124 A KR 54 B-12 RECREO LOS FRAILES 12 BQU 5 APT 209 LAT:4.70710962 LON:-74.0642317 | CD20: RECREO LOS FRAILES | CE20: -1 | CF20: 11001000 | CG20: Bogota | CH20: ATACANTE | CI20: 1073250775 | CJ20: SHARON NATALIA GONZALEZ CAAADULCE | CK20: CANAL ONLINE | CL20: ON LINE | CM20: ATENTO COLOMBIA S.A. | CN20: CANAL ON LINE - ATENTO CLICK TO CALL | CT20: 5 | CU20: BA + LB + IPTV | CW20: MTotal_Trio_Voz Ilim Nal _Ba Ancha 900Mbps_IPTV_2_Decos_Mov Ilim_Nac_25425 | CX20: 25425 | DA20: SV | DB20: -1 | DF20: ALTA | DJ20: 900000 | DK20: Cliente Nuevo | DL20: Cliente Nuevo | DN20: TRIO | DR20: sngonzalezca | DS20: SHARON NATALIA GONZALEZ CAAADULCE | DT20: 1073250775 | DV20: 1 | DW20: BOGOTA | ED20: 46144 | EE20: Norte | EF20: 20 | EP20: 830065842-5 | ES20: 17 | FA20: CANAL ONLINE | FB20: Bogotá D.C | FD20: Bogotá D.C | FE20: Bogotá | FF20: Bogotá | FK20: ATENTO | FL20: 11001000OH_BOGALMATG_I_7360_21000_Morato_7MORAT-PC6-87-09SS6-87-09@11001000_OH_BOGALMATG_I_7360_21000_Morato_7_MORAT-PC6-87-09_SS6-87-09 | FN20: CANAL ON LINE - ATENTO CLICK TO CALL | FO20: 9900202020033 | FR20: 99915 | GB20: PON | GC20: BA + LB + IPTV | GD20: 25188 | GF20: 2353 | GG20: 25422 | GI20: 73235 | GJ20: 25427 | GL20: 24327 | GM20: 118898 | GS20: FS | GT20: 43829 | GU20: CENTRO EXP | GV20: NO VALIDADO | GW20: Si | GX20: Solo Movil | GY20: Convergente Solo Contrato | GZ20: Convergente Nuevo | HA20: PRE-ONNET | HB20: BOGOTA 1 | HC20: BOGOTA 1 | HD20: BOGOTA NORTE | HE20: Individual | HF20: 470574060 | HG20: Venta Hogar (F) a cliente Pospago | HR20: Asistido | HV20: 118900 | HW20: SI | HX20: Migracion Pos-Pos | HY20: 117583 | HZ20: 17668 | IA20: SI | IB20: NO | ID20: >= 120 | IE20: BOGOTA | IF20: BOGOTA | IG20: BOGOTA | IH20: Digital | II20: Fibra | IJ20: B2C | IK20: Asistido | IL20: C2C | IM20: Atento | IN20: Alta | IO20: 3177856417 | IP20: - | IQ20: Digital | IS20: ELECTRONICA | IT20: Googleads_Oferta | IU20: CO_HOGAR_COL-FIBRA-ASISTIDA-BOGOTA-B2C_22-06-13_SEM_LDS-WEB_AON_ABT_BRAND | IV20: SEM_SEM_CPL | IW20: Fija-Fibra-web-CajadeProducto-LP-pauta-fibra | IY20: NO
A21: =DAY(AVANZA[[#This Row],[FechaSeguimiento]]) -> 2 | B21: =MONTH(AVANZA[[#This Row],[FechaSeguimiento]]) -> 5 | C21: =LOWER(IF(AND(AVANZA[[#This Row],[Mes_Reg]]=MONTH(TODAY()),AND(AVANZA[[#This Row],[Dia_Reg]]>0,AVANZA[[#This Row],[Dia_Reg]]<9)),"SEMANA 1","")&IF(AND(AVANZA[[#This Row],[Mes_Reg]]=MONTH(TODAY()),AND(AVANZA[[#This Row],[Dia_Reg]]>8,AVANZA[[#This Row],[Dia_Reg]]<16)),"SEMANA 2","")&IF(AND(AVANZA[[#This Row],[Mes_Reg]]=MONTH(TODAY()),AND(AVANZA[[#This Row],[Dia_Reg]]>15,AVANZA[[#This Row],[Dia_Reg]]<23)),"SEMANA 3","")&IF(AND(AVANZA[[#This Row],[Mes_Reg]]=MONTH(TODAY()),AND(AVANZA[[#This Row],[Dia_Reg]]>22,AVANZA[[#This Row],[Dia_Reg]]<31)),"SEMANA 4","")&IF(AVANZA[[#This Row],[Mes_Reg]]<>MONTH(TODAY()),"BOLSA MES ANTERIOR","")) -> semana 1 | D21: =LOWER(IFERROR(VLOOKUP(AVANZA[[#This Row],[ID_Peticion]],CANCELADAS[#All],2,0),"")) | E21: =LOWER(IFERROR(VLOOKUP(AVANZA[[#This Row],[ID_Peticion]],CANCELADAS[#All],3,0),"")) | F21: =LOWER(IF(AVANZA[[#This Row],[CEDULA CLIENTE]]<>""," CC: " & COUNTIFS(AVANZA[CEDULA CLIENTE],AVANZA[[#This Row],[CEDULA CLIENTE]]),"")& IF(AVANZA[[#This Row],[Direccion]]<>""," DIR: " & COUNTIFS(AVANZA[Direccion],AVANZA[[#This Row],[Direccion]]),"")) -> dir: 1 | G21: =IFERROR(VLOOKUP(AVANZA[[#This Row],[Cedula_Vendedor_Atis]],PLANTA[[#All],[CEDULA]:[LINEA]],3,0),"No Cruza") -> Marisol Avella | H21: =IFERROR(VLOOKUP(AVANZA[[#This Row],[Cedula_Vendedor_Atis]],PLANTA[[#All],[CEDULA]:[LINEA]],4,0),"No Cruza") -> Fija | I21: =LOWER(IF(AVANZA[[#This Row],[ATRIBUIBLE]]="",AVANZA[[#This Row],[Variable]],AVANZA[[#This Row],[ATRIBUIBLE]])) -> terminada | J21: =IF(AVANZA[[#This Row],[Variable]]=AVANZA[[#Headers],[TERMINADA]],1,0) -> 1 | K21: =IF(AVANZA[[#This Row],[Variable]]=AVANZA[[#Headers],[ANULADA]],1,0) -> 0 | L21: =IF(AVANZA[[#This Row],[Variable]]=AVANZA[[#Headers],[PENDIENTE]],1,0) -> 0 | M21: =IF(AVANZA[[#This Row],[ESTADO AGENDA]]="AGENDADA",1,0) -> 0 | N21: =IF(AVANZA[[#This Row],[ESTADO AGENDA]]="PENDIENTE DE AGENDAR",1,0) -> 0 | O21: =IF(AVANZA[[#This Row],[ESTADO AGENDA]]="SUSPENDIDA",1,0) -> 0 | P21: {=_xlfn.XLOOKUP(AVANZA[[#This Row],[Num_Agrupacion_Pet_Atis]],Tabla1[[#All],[Numero_de_actuacion]],Tabla1[[#All],[Estado_de_la_orden]],"",0)} | Q21: {=_xlfn.XLOOKUP(AVANZA[[#This Row],[Num_Agrupacion_Pet_Atis]],Tabla1[[#All],[Numero_de_actuacion]],Tabla1[[#All],[Fecha_de_la_cita]],"",0)} | R21: {=_xlfn.XLOOKUP(AVANZA[[#This Row],[Num_Agrupacion_Pet_Atis]],Tabla1[[#All],[Numero_de_actuacion]],Tabla1[[#All],[Franja_horaria_de_la_cita]],"",0)} | S21: =IFERROR(DAY(AVANZA[[#This Row],[FECHA AGENDA]]),"") | T21: =IFERROR(MONTH(AVANZA[[#This Row],[FECHA AGENDA]]),"") | U21: {=_xlfn.XLOOKUP(AVANZA[[#This Row],[Num_Agrupacion_Pet_Atis]],Tabla1[[#All],[Numero_de_actuacion]],Tabla1[[#All],[Motivo_de_suspension]],"",0)} | V21: {=_xlfn.XLOOKUP(AVANZA[[#This Row],[Num_Agrupacion_Pet_Atis]],Tabla1[[#All],[Numero_de_actuacion]],Tabla1[[#All],[No_identificacion_cliente]],"",0)} | W21: {=_xlfn.XLOOKUP(AVANZA[[#This Row],[Num_Agrupacion_Pet_Atis]],Tabla1[[#All],[Numero_de_actuacion]],Tabla1[[#All],[Movil_de_contacto]],"",0)} | X21: =IF(OR(AVANZA[[#This Row],[ESTADO LEG]]="Legalizada grabacion",AVANZA[[#This Row],[ESTADO LEG]]="Legalizada aut"),1,0) -> 1 | Y21: =IF(OR(AVANZA[[#This Row],[ESTADO LEG]]="pdte legalizar",AVANZA[[#This Row],[ESTADO LEG]]="No cruza"),1,0) -> 0 | Z21: {=IF(AVANZA[[#This Row],[Variable]]="Terminada",LOWER(_xlfn.XLOOKUP(AVANZA[[#This Row],[ID_Peticion]],Tabla6[[#All],[NUM_PETICION]],Tabla6[[#All],[ESTADO_LEG]],"NO CRUZA",0)),AVANZA[[#This Row],[Variable]])} -> legalizada grabacion | AA21: {=_xlfn.XLOOKUP(AVANZA[[#This Row],[ID_Peticion]],Tabla6[[#All],[NUM_PETICION]],Tabla6[[#All],[DIF_DIAS]],"",0)} -> 4 | AB21: {=IFERROR(_xlfn.XLOOKUP(AVANZA[[#This Row],[ID_Peticion]],Tabla6[[#All],[NUM_PETICION]],Tabla6[[#All],[FEC_LEGAL]],"",0),"")} -> 46148 | AC21: =IF(AVANZA[[#This Row],[FECHA LEG]]<>0,IFERROR(AVANZA[[#This Row],[FECHA LEG]]-AVANZA[[#This Row],[FechaIniEstadoSubPetAtis]],0),TODAY()-AVANZA[[#This Row],[FechaIniEstadoSubPetAtis]]) -> 4 | AD21: =IF(AVANZA[[#This Row],[FINAL Vs LG]]<>0,IF(AVANZA[[#This Row],[FINAL Vs LG]]<7.1,"100%",IF(AND(AVANZA[[#This Row],[FINAL Vs LG]]>7.1,AVANZA[[#This Row],[FINAL Vs LG]]<11.1),"50%","0%")),0) -> 100% | AE21: =VLOOKUP(DAY(TODAY()),BACK!F:G,2,0) -> 14 | AF21: =BACK!$I$2 -> 24 | AG21: =IF(AVANZA[[#This Row],[Oferta_empaquetada_comisiones]]="SI",1,0) -> 0 | AH21: =IF(AVANZA[[#This Row],[Variable]]="TERMINADA",IFERROR(VLOOKUP(AVANZA[[#This Row],[SUPERVISOR]],Tabla2[#All],4,0),0),) -> 3.5 | AI21: =IF(AVANZA[[#This Row],[Producto]]="BA",1,0) -> 1 | AJ21: =IF(AVANZA[[#This Row],[Producto]]="DUO",1,0) -> 0 | AK21: =IF(AVANZA[[#This Row],[Producto]]="TRIO",1,0) -> 0 | AL21: 1648048636331251387 | AM21: -1 | AN21: -1 | AO21: 1785885967 | AP21: 46143.305 | AQ21: -1 | AR21: 2512690782 | AS21: -1 | AT21: -1 | AU21: -1 | AV21: -1 | AW21: -1 | AX21: FixedCreateSubscriber | AY21: -1 | AZ21: 2026 | BA21: 5 | BB21: 2 | BC21: -1 | BD21: Broadband Service | BE21: -1 | BF21: 20001620893751 | BG21: Plan Banda Ancha 900Mbps Solo Internet_Nac_25423 | BH21: 25423 | BI21: FS202605010718082000 | BJ21: -1 | BK21: -1 | BL21: -1 | BM21: TERMINADA | BN21: Individual | BO21: 6108790091 | BP21: Gold | BQ21: 2026 | BR21: 5 | BS21: 1 | BT21: 46144.639 | BU21: OS90 | BV21: 46144 | BW21: Completed | BX21: 46143 | BY21: 46144 | BZ21: Call Back To CRM | CA21: MEDELLIN | CB21: ANTIOQUIA | CC21: KR 13 CL 4 B S-97 LOS BALSOS NO.1 97 CAS 127 LAT:6.18977392 LON:-75.55484634 | CD21: LOS BALSOS NO.1 | CE21: -1 | CF21: 05001000 | CG21: Antioquia - Choco | CH21: SIN PRESENCIA | CI21: 1073250775 | CJ21: SHARON NATALIA GONZALEZ CAAADULCE | CK21: CANAL ONLINE | CL21: ON LINE | CM21: ATENTO COLOMBIA S.A. | CN21: CANAL ON LINE - ATENTO CLICK TO CALL | CT21: 5 | CU21: Broadband Service | CW21: Plan Banda Ancha 900Mbps Solo Internet_Nac_25423 | CX21: 25423 | DA21: SV | DB21: -1 | DF21: ALTA | DJ21: 900000 | DK21: Cliente Nuevo | DL21: Cliente Existente | DN21: BA | DR21: sngonzalezca | DS21: SHARON NATALIA GONZALEZ CAAADULCE | DT21: 1073250775 | DV21: 1 | DW21: NOROCCIDENTE | ED21: 46144 | EF21: 9 | EP21: 830065842-5 | ES21: POBLADO12 | EZ21: OLT#10.37.80.158 | FA21: CANAL ONLINE | FB21: Antioquia | FD21: Antioquia | FE21: Medellín | FF21: Medellín | FK21: ATENTO | FL21: 5001000155303903630085|5001000_630085_CT2-61-01 | FN21: CANAL ON LINE - ATENTO CLICK TO CALL | FO21: 9900202020033 | FR21: 79824 | GB21: PON | GC21: Broadband Service | GD21: 0 | GF21: 0 | GG21: 25423 | GI21: 79824 | GJ21: 0 | GL21: 0 | GM21: 94990 | GS21: FS | GT21: 45565 | GU21: CENTRO EXP | GV21: VALIDADO | GW21: No | GZ21: No Convergente | HA21: ATP | HB21: MEDELLIN | HC21: MEDELLIN | HD21: MEDELLIN + NOROCCIDENTE | HE21: Individual | HF21: 618575550 | HR21: Asistido | HV21: 94990 | HW21: NO | HY21: 0 | HZ21: 0 | IA21: NO | IB21: NO | IE21: BOGOTA | IF21: BOGOTA | IG21: BOGOTA | IH21: Digital | II21: Fibra | IJ21: B2C | IK21: Asistido | IL21: C2C | IM21: Atento | IN21: Alta | IP21: - | IQ21: Digital | IS21: ELECTRONICA | IT21: Organico | IW21: Fibra-Fibra-web-CajadeProducto-LP_Hogar_Naked | IY21: NO
A22: =DAY(AVANZA[[#This Row],[FechaSeguimiento]]) -> 2 | B22: =MONTH(AVANZA[[#This Row],[FechaSeguimiento]]) -> 5 | C22: =LOWER(IF(AND(AVANZA[[#This Row],[Mes_Reg]]=MONTH(TODAY()),AND(AVANZA[[#This Row],[Dia_Reg]]>0,AVANZA[[#This Row],[Dia_Reg]]<9)),"SEMANA 1","")&IF(AND(AVANZA[[#This Row],[Mes_Reg]]=MONTH(TODAY()),AND(AVANZA[[#This Row],[Dia_Reg]]>8,AVANZA[[#This Row],[Dia_Reg]]<16)),"SEMANA 2","")&IF(AND(AVANZA[[#This Row],[Mes_Reg]]=MONTH(TODAY()),AND(AVANZA[[#This Row],[Dia_Reg]]>15,AVANZA[[#This Row],[Dia_Reg]]<23)),"SEMANA 3","")&IF(AND(AVANZA[[#This Row],[Mes_Reg]]=MONTH(TODAY()),AND(AVANZA[[#This Row],[Dia_Reg]]>22,AVANZA[[#This Row],[Dia_Reg]]<31)),"SEMANA 4","")&IF(AVANZA[[#This Row],[Mes_Reg]]<>MONTH(TODAY()),"BOLSA MES ANTERIOR","")) -> bolsa mes anterior | D22: =LOWER(IFERROR(VLOOKUP(AVANZA[[#This Row],[ID_Peticion]],CANCELADAS[#All],2,0),"")) | E22: =LOWER(IFERROR(VLOOKUP(AVANZA[[#This Row],[ID_Peticion]],CANCELADAS[#All],3,0),"")) | F22: =LOWER(IF(AVANZA[[#This Row],[CEDULA CLIENTE]]<>""," CC: " & COUNTIFS(AVANZA[CEDULA CLIENTE],AVANZA[[#This Row],[CEDULA CLIENTE]]),"")& IF(AVANZA[[#This Row],[Direccion]]<>""," DIR: " & COUNTIFS(AVANZA[Direccion],AVANZA[[#This Row],[Direccion]]),"")) -> dir: 1 | G22: =IFERROR(VLOOKUP(AVANZA[[#This Row],[Cedula_Vendedor_Atis]],PLANTA[[#All],[CEDULA]:[LINEA]],3,0),"No Cruza") -> Marisol Avella | H22: =IFERROR(VLOOKUP(AVANZA[[#This Row],[Cedula_Vendedor_Atis]],PLANTA[[#All],[CEDULA]:[LINEA]],4,0),"No Cruza") -> Fija | I22: =LOWER(IF(AVANZA[[#This Row],[ATRIBUIBLE]]="",AVANZA[[#This Row],[Variable]],AVANZA[[#This Row],[ATRIBUIBLE]])) -> terminada | J22: =IF(AVANZA[[#This Row],[Variable]]=AVANZA[[#Headers],[TERMINADA]],1,0) -> 1 | K22: =IF(AVANZA[[#This Row],[Variable]]=AVANZA[[#Headers],[ANULADA]],1,0) -> 0 | L22: =IF(AVANZA[[#This Row],[Variable]]=AVANZA[[#Headers],[PENDIENTE]],1,0) -> 0 | M22: =IF(AVANZA[[#This Row],[ESTADO AGENDA]]="AGENDADA",1,0) -> 0 | N22: =IF(AVANZA[[#This Row],[ESTADO AGENDA]]="PENDIENTE DE AGENDAR",1,0) -> 0 | O22: =IF(AVANZA[[#This Row],[ESTADO AGENDA]]="SUSPENDIDA",1,0) -> 0 | P22: {=_xlfn.XLOOKUP(AVANZA[[#This Row],[Num_Agrupacion_Pet_Atis]],Tabla1[[#All],[Numero_de_actuacion]],Tabla1[[#All],[Estado_de_la_orden]],"",0)} | Q22: {=_xlfn.XLOOKUP(AVANZA[[#This Row],[Num_Agrupacion_Pet_Atis]],Tabla1[[#All],[Numero_de_actuacion]],Tabla1[[#All],[Fecha_de_la_cita]],"",0)} | R22: {=_xlfn.XLOOKUP(AVANZA[[#This Row],[Num_Agrupacion_Pet_Atis]],Tabla1[[#All],[Numero_de_actuacion]],Tabla1[[#All],[Franja_horaria_de_la_cita]],"",0)} | S22: =IFERROR(DAY(AVANZA[[#This Row],[FECHA AGENDA]]),"") | T22: =IFERROR(MONTH(AVANZA[[#This Row],[FECHA AGENDA]]),"") | U22: {=_xlfn.XLOOKUP(AVANZA[[#This Row],[Num_Agrupacion_Pet_Atis]],Tabla1[[#All],[Numero_de_actuacion]],Tabla1[[#All],[Motivo_de_suspension]],"",0)} | V22: {=_xlfn.XLOOKUP(AVANZA[[#This Row],[Num_Agrupacion_Pet_Atis]],Tabla1[[#All],[Numero_de_actuacion]],Tabla1[[#All],[No_identificacion_cliente]],"",0)} | W22: {=_xlfn.XLOOKUP(AVANZA[[#This Row],[Num_Agrupacion_Pet_Atis]],Tabla1[[#All],[Numero_de_actuacion]],Tabla1[[#All],[Movil_de_contacto]],"",0)} | X22: =IF(OR(AVANZA[[#This Row],[ESTADO LEG]]="Legalizada grabacion",AVANZA[[#This Row],[ESTADO LEG]]="Legalizada aut"),1,0) -> 1 | Y22: =IF(OR(AVANZA[[#This Row],[ESTADO LEG]]="pdte legalizar",AVANZA[[#This Row],[ESTADO LEG]]="No cruza"),1,0) -> 0 | Z22: {=IF(AVANZA[[#This Row],[Variable]]="Terminada",LOWER(_xlfn.XLOOKUP(AVANZA[[#This Row],[ID_Peticion]],Tabla6[[#All],[NUM_PETICION]],Tabla6[[#All],[ESTADO_LEG]],"NO CRUZA",0)),AVANZA[[#This Row],[Variable]])} -> legalizada grabacion | AA22: {=_xlfn.XLOOKUP(AVANZA[[#This Row],[ID_Peticion]],Tabla6[[#All],[NUM_PETICION]],Tabla6[[#All],[DIF_DIAS]],"",0)} -> 4 | AB22: {=IFERROR(_xlfn.XLOOKUP(AVANZA[[#This Row],[ID_Peticion]],Tabla6[[#All],[NUM_PETICION]],Tabla6[[#All],[FEC_LEGAL]],"",0),"")} -> 46148 | AC22: =IF(AVANZA[[#This Row],[FECHA LEG]]<>0,IFERROR(AVANZA[[#This Row],[FECHA LEG]]-AVANZA[[#This Row],[FechaIniEstadoSubPetAtis]],0),TODAY()-AVANZA[[#This Row],[FechaIniEstadoSubPetAtis]]) -> 4 | AD22: =IF(AVANZA[[#This Row],[FINAL Vs LG]]<>0,IF(AVANZA[[#This Row],[FINAL Vs LG]]<7.1,"100%",IF(AND(AVANZA[[#This Row],[FINAL Vs LG]]>7.1,AVANZA[[#This Row],[FINAL Vs LG]]<11.1),"50%","0%")),0) -> 100% | AE22: =VLOOKUP(DAY(TODAY()),BACK!F:G,2,0) -> 14 | AF22: =BACK!$I$2 -> 24 | AG22: =IF(AVANZA[[#This Row],[Oferta_empaquetada_comisiones]]="SI",1,0) -> 0 | AH22: =IF(AVANZA[[#This Row],[Variable]]="TERMINADA",IFERROR(VLOOKUP(AVANZA[[#This Row],[SUPERVISOR]],Tabla2[#All],4,0),0),) -> 3.5 | AI22: =IF(AVANZA[[#This Row],[Producto]]="BA",1,0) -> 0 | AJ22: =IF(AVANZA[[#This Row],[Producto]]="DUO",1,0) -> 0 | AK22: =IF(AVANZA[[#This Row],[Producto]]="TRIO",1,0) -> 1 | AL22: 1760285521955967900 | AM22: -1 | AN22: -1 | AO22: 1784293064 | AP22: 46140.616 | AQ22: -1 | AR22: 2512683583 | AS22: -1 | AT22: -1 | AU22: -1 | AV22: -1 | AW22: -1 | AX22: FixedCreateSubscriber | AY22: -1 | AZ22: 2026 | BA22: 5 | BB22: 2 | BC22: -1 | BD22: Broadband Service | BE22: -1 | BF22: 20001619516720 | BG22: Plan Banda Ancha 900Mbps_IPTV_1 Decos_Netflix_Trio_25356 | BH22: 25356 | BI22: FS202604281446321245 | BJ22: -1 | BK22: -1 | BL22: -1 | BM22: TERMINADA | BN22: Individual | BO22: 6108728505 | BP22: Gold | BQ22: 2026 | BR22: 4 | BS22: 28 | BT22: 46144.4 | BU22: OS90 | BV22: 46144 | BW22: Completed | BX22: 46140 | BY22: 46144 | BZ22: Call Back To CRM | CA22: BOGOTA, D.C. | CB22: BOGOTA, D.C. | CC22: CL 23 KR 72 A-91 LA FELICIDAD 91 TOR 3 APT 601 LAT:4.65947063 LON:-74.11917254 | CD22: LA FELICIDAD | CE22: -1 | CF22: 11001000 | CG22: Bogota | CH22: ATACANTE | CI22: 1063565638 | CJ22: JOYNNER FERNANDO BRISENO OLIVIERI | CK22: CANAL ONLINE | CL22: TELEVENTAS | CM22: ATENTO COLOMBIA S.A. | CN22: CANAL ON LINE - ATENTO OUT BOUND | CT22: 4 | CU22: BA + LB + IPTV | CW22: Trio Voz Ilimitada Nacional 200 Min LDI Banda Ancha 900Mbps_IPTV_1 Decos_Netflix_Nac_25344 | CX22: 25344 | DA22: SV | DB22: -1 | DF22: ALTA | DJ22: 900000 | DK22: Cliente Nuevo | DL22: Cliente Nuevo | DN22: TRIO | DR22: jbrisenool | DS22: JOYNNER FERNANDO BRISENO OLIVIERI | DT22: 1063565638 | DV22: 1 | DW22: BOGOTA | ED22: 46144 | EE22: Occidente | EF22: 5 | EP22: 830065842-5 | ES22: Extension Calle 22 | EZ22: OLT#10.37.80.98 | FA22: CANAL ONLINE | FB22: Bogotá D.C | FD22: Bogotá D.C | FE22: Bogotá | FF22: Bogotá | FK22: ATENTO | FL22: 11001000124822082757732|11001000_124822082_PC2-50-06 | FN22: CANAL ON LINE - ATENTO OUT BOUND | FO22: 9900202020034 | FR22: 126039 | GB22: PON | GC22: BA + LB + IPTV | GD22: 14854 | GF22: 2351 | GG22: 25356 | GI22: 83479 | GJ22: 25362 | GL22: 40209 | GM22: 149986 | GS22: FS | GT22: 44742 | GU22: CENTRO EXP | GV22: SIN EMAIL | GW22: No | GZ22: No Convergente | HA22: ATP | HE22: Individual | HF22: 465574115 | HR22: Asistido | HV22: 149990 | HW22: NO | HY22: 0 | HZ22: 0 | IA22: NO | IB22: NO | IE22: BOGOTA | IF22: BOGOTA | IG22: BOGOTA | IH22: Digital | II22: Fibra | IJ22: B2C | IK22: Asistido | IL22: Outbound | IM22: Atento | IN22: Alta | IP22: - | IQ22: Digital | IS22: ELECTRONICA | IT22: Organico | IW22: Fibra-MovistarTotal-web-BarraFija-LP_MovistarTotal_BarraFija_Asistido | IY22: NO
A23: =DAY(AVANZA[[#This Row],[FechaSeguimiento]]) -> 2 | B23: =MONTH(AVANZA[[#This Row],[FechaSeguimiento]]) -> 5 | C23: =LOWER(IF(AND(AVANZA[[#This Row],[Mes_Reg]]=MONTH(TODAY()),AND(AVANZA[[#This Row],[Dia_Reg]]>0,AVANZA[[#This Row],[Dia_Reg]]<9)),"SEMANA 1","")&IF(AND(AVANZA[[#This Row],[Mes_Reg]]=MONTH(TODAY()),AND(AVANZA[[#This Row],[Dia_Reg]]>8,AVANZA[[#This Row],[Dia_Reg]]<16)),"SEMANA 2","")&IF(AND(AVANZA[[#This Row],[Mes_Reg]]=MONTH(TODAY()),AND(AVANZA[[#This Row],[Dia_Reg]]>15,AVANZA[[#This Row],[Dia_Reg]]<23)),"SEMANA 3","")&IF(AND(AVANZA[[#This Row],[Mes_Reg]]=MONTH(TODAY()),AND(AVANZA[[#This Row],[Dia_Reg]]>22,AVANZA[[#This Row],[Dia_Reg]]<31)),"SEMANA 4","")&IF(AVANZA[[#This Row],[Mes_Reg]]<>MONTH(TODAY()),"BOLSA MES ANTERIOR","")) -> bolsa mes anterior | D23: =LOWER(IFERROR(VLOOKUP(AVANZA[[#This Row],[ID_Peticion]],CANCELADAS[#All],2,0),"")) | E23: =LOWER(IFERROR(VLOOKUP(AVANZA[[#This Row],[ID_Peticion]],CANCELADAS[#All],3,0),"")) | F23: =LOWER(IF(AVANZA[[#This Row],[CEDULA CLIENTE]]<>""," CC: " & COUNTIFS(AVANZA[CEDULA CLIENTE],AVANZA[[#This Row],[CEDULA CLIENTE]]),"")& IF(AVANZA[[#This Row],[Direccion]]<>""," DIR: " & COUNTIFS(AVANZA[Direccion],AVANZA[[#This Row],[Direccion]]),"")) -> dir: 1 | G23: =IFERROR(VLOOKUP(AVANZA[[#This Row],[Cedula_Vendedor_Atis]],PLANTA[[#All],[CEDULA]:[LINEA]],3,0),"No Cruza") -> Marisol Avella | H23: =IFERROR(VLOOKUP(AVANZA[[#This Row],[Cedula_Vendedor_Atis]],PLANTA[[#All],[CEDULA]:[LINEA]],4,0),"No Cruza") -> Fija | I23: =LOWER(IF(AVANZA[[#This Row],[ATRIBUIBLE]]="",AVANZA[[#This Row],[Variable]],AVANZA[[#This Row],[ATRIBUIBLE]])) -> terminada | J23: =IF(AVANZA[[#This Row],[Variable]]=AVANZA[[#Headers],[TERMINADA]],1,0) -> 1 | K23: =IF(AVANZA[[#This Row],[Variable]]=AVANZA[[#Headers],[ANULADA]],1,0) -> 0 | L23: =IF(AVANZA[[#This Row],[Variable]]=AVANZA[[#Headers],[PENDIENTE]],1,0) -> 0 | M23: =IF(AVANZA[[#This Row],[ESTADO AGENDA]]="AGENDADA",1,0) -> 0 | N23: =IF(AVANZA[[#This Row],[ESTADO AGENDA]]="PENDIENTE DE AGENDAR",1,0) -> 0 | O23: =IF(AVANZA[[#This Row],[ESTADO AGENDA]]="SUSPENDIDA",1,0) -> 0 | P23: {=_xlfn.XLOOKUP(AVANZA[[#This Row],[Num_Agrupacion_Pet_Atis]],Tabla1[[#All],[Numero_de_actuacion]],Tabla1[[#All],[Estado_de_la_orden]],"",0)} | Q23: {=_xlfn.XLOOKUP(AVANZA[[#This Row],[Num_Agrupacion_Pet_Atis]],Tabla1[[#All],[Numero_de_actuacion]],Tabla1[[#All],[Fecha_de_la_cita]],"",0)} | R23: {=_xlfn.XLOOKUP(AVANZA[[#This Row],[Num_Agrupacion_Pet_Atis]],Tabla1[[#All],[Numero_de_actuacion]],Tabla1[[#All],[Franja_horaria_de_la_cita]],"",0)} | S23: =IFERROR(DAY(AVANZA[[#This Row],[FECHA AGENDA]]),"") | T23: =IFERROR(MONTH(AVANZA[[#This Row],[FECHA AGENDA]]),"") | U23: {=_xlfn.XLOOKUP(AVANZA[[#This Row],[Num_Agrupacion_Pet_Atis]],Tabla1[[#All],[Numero_de_actuacion]],Tabla1[[#All],[Motivo_de_suspension]],"",0)} | V23: {=_xlfn.XLOOKUP(AVANZA[[#This Row],[Num_Agrupacion_Pet_Atis]],Tabla1[[#All],[Numero_de_actuacion]],Tabla1[[#All],[No_identificacion_cliente]],"",0)} | W23: {=_xlfn.XLOOKUP(AVANZA[[#This Row],[Num_Agrupacion_Pet_Atis]],Tabla1[[#All],[Numero_de_actuacion]],Tabla1[[#All],[Movil_de_contacto]],"",0)} | X23: =IF(OR(AVANZA[[#This Row],[ESTADO LEG]]="Legalizada grabacion",AVANZA[[#This Row],[ESTADO LEG]]="Legalizada aut"),1,0) -> 1 | Y23: =IF(OR(AVANZA[[#This Row],[ESTADO LEG]]="pdte legalizar",AVANZA[[#This Row],[ESTADO LEG]]="No cruza"),1,0) -> 0 | Z23: {=IF(AVANZA[[#This Row],[Variable]]="Terminada",LOWER(_xlfn.XLOOKUP(AVANZA[[#This Row],[ID_Peticion]],Tabla6[[#All],[NUM_PETICION]],Tabla6[[#All],[ESTADO_LEG]],"NO CRUZA",0)),AVANZA[[#This Row],[Variable]])} -> legalizada grabacion | AA23: {=_xlfn.XLOOKUP(AVANZA[[#This Row],[ID_Peticion]],Tabla6[[#All],[NUM_PETICION]],Tabla6[[#All],[DIF_DIAS]],"",0)} -> 4 | AB23: {=IFERROR(_xlfn.XLOOKUP(AVANZA[[#This Row],[ID_Peticion]],Tabla6[[#All],[NUM_PETICION]],Tabla6[[#All],[FEC_LEGAL]],"",0),"")} -> 46148 | AC23: =IF(AVANZA[[#This Row],[FECHA LEG]]<>0,IFERROR(AVANZA[[#This Row],[FECHA LEG]]-AVANZA[[#This Row],[FechaIniEstadoSubPetAtis]],0),TODAY()-AVANZA[[#This Row],[FechaIniEstadoSubPetAtis]]) -> 4 | AD23: =IF(AVANZA[[#This Row],[FINAL Vs LG]]<>0,IF(AVANZA[[#This Row],[FINAL Vs LG]]<7.1,"100%",IF(AND(AVANZA[[#This Row],[FINAL Vs LG]]>7.1,AVANZA[[#This Row],[FINAL Vs LG]]<11.1),"50%","0%")),0) -> 100% | AE23: =VLOOKUP(DAY(TODAY()),BACK!F:G,2,0) -> 14 | AF23: =BACK!$I$2 -> 24 | AG23: =IF(AVANZA[[#This Row],[Oferta_empaquetada_comisiones]]="SI",1,0) -> 0 | AH23: =IF(AVANZA[[#This Row],[Variable]]="TERMINADA",IFERROR(VLOOKUP(AVANZA[[#This Row],[SUPERVISOR]],Tabla2[#All],4,0),0),) -> 3.5 | AI23: =IF(AVANZA[[#This Row],[Producto]]="BA",1,0) -> 1 | AJ23: =IF(AVANZA[[#This Row],[Producto]]="DUO",1,0) -> 0 | AK23: =IF(AVANZA[[#This Row],[Producto]]="TRIO",1,0) -> 0 | AL23: 1705673845639647342 | AM23: -1 | AN23: -1 | AO23: 1785068153 | AP23: 46142.302 | AQ23: -1 | AR23: 2512688604 | AS23: -1 | AT23: -1 | AU23: -1 | AV23: -1 | AW23: -1 | AX23: FixedCreateSubscriber | AY23: -1 | AZ23: 2026 | BA23: 5 | BB23: 2 | BC23: -1 | BD23: Broadband Service | BE23: -1 | BF23: 20001620217276 | BG23: Convergente_MTotal_Single_Voz Ilim Nal _Ba Ancha 900Mbps_Mov Ilim_Netflix_Nac_25335 | BH23: 25335 | BI23: FS202604300714151759 | BJ23: -1 | BK23: -1 | BL23: -1 | BM23: TERMINADA | BN23: Individual | BO23: 1023943675 | BP23: Movistar Total | BQ23: 2026 | BR23: 4 | BS23: 30 | BT23: 46144.483 | BU23: OS90 | BV23: 46144 | BW23: Completed | BX23: 46142 | BY23: 46144 | BZ23: Call Back To CRM | CA23: MEDELLIN | CB23: ANTIOQUIA | CC23: CL 2 S KR 20-185 LOS NARANJOS 185 TOR 1 APT 1404 LAT:6.19476675 LON:-75.55744258 | CD23: LOS NARANJOS | CE23: -1 | CF23: 05001000 | CG23: Antioquia - Choco | CH23: SIN PRESENCIA | CI23: 1031182302 | CJ23: TATIANA PERILLA ALFONSO | CK23: CANAL ONLINE | CL23: TELEVENTAS | CM23: ATENTO COLOMBIA S.A. | CN23: CANAL ON LINE - ATENTO OUT BOUND | CT23: 6 | CU23: Broadband Service | CW23: Convergente_MTotal_Single_Voz Ilim Nal _Ba Ancha 900Mbps_Mov Ilim_Netflix_Nac_25335 | CX23: 25335 | DA23: SV | DB23: -1 | DF23: ALTA | DJ23: 900000 | DK23: Cliente Nuevo | DL23: Cliente Existente | DN23: BA | DR23: tperillaal | DS23: TATIANA PERILLA ALFONSO | DT23: 1031182302 | DV23: 1 | DW23: NOROCCIDENTE | ED23: 46144 | EF23: 1 | EP23: 830065842-5 | ES23: POBLADO12 | EZ23: OLT#10.37.80.158 | FA23: CANAL ONLINE | FB23: Antioquia | FD23: Antioquia | FE23: Medellín | FF23: Medellín | FK23: ATENTO | FL23: 5001000137049391876396|5001000_876396_PC2-32-01 | FN23: CANAL ON LINE - ATENTO OUT BOUND | FO23: 9900202020034 | FR23: 87311 | GB23: PON | GC23: Broadband Service | GD23: 0 | GF23: 0 | GG23: 25335 | GI23: 87311 | GJ23: 0 | GL23: 0 | GM23: 103900 | GS23: FS | GT23: 45291 | GU23: CENTRO EXP | GV23: NO VALIDADO | GW23: Si | GX23: Solo Movil | GY23: Convergente Solo Contrato | GZ23: Convergente Nuevo | HA23: ATP | HE23: Individual | HF23: 619075555 | HG23: Venta Hogar (F) a cliente Pospago | HR23: Asistido | HV23: 103900 | HW23: SI | HX23: Migracion Pos-Pos | HY23: 104979 | HZ23: 17668 | IA23: SI | IB23: NO | ID23: >= 120 | IE23: BOGOTA | IF23: BOGOTA | IG23: BOGOTA | IH23: Digital | II23: Fibra | IJ23: B2C | IK23: Asistido | IL23: Outbound | IM23: Atento | IN23: Alta | IP23: - | IQ23: Digital | IS23: ELECTRONICA | IT23: App | IU23: app_gif_fibra_asistido | IV23: app_gif_fibra | IW23: Fija-Fibra-web-CajadeProducto-LP-pauta-fibra | IY23: NO
A24: =DAY(AVANZA[[#This Row],[FechaSeguimiento]]) -> 2 | B24: =MONTH(AVANZA[[#This Row],[FechaSeguimiento]]) -> 5 | C24: =LOWER(IF(AND(AVANZA[[#This Row],[Mes_Reg]]=MONTH(TODAY()),AND(AVANZA[[#This Row],[Dia_Reg]]>0,AVANZA[[#This Row],[Dia_Reg]]<9)),"SEMANA 1","")&IF(AND(AVANZA[[#This Row],[Mes_Reg]]=MONTH(TODAY()),AND(AVANZA[[#This Row],[Dia_Reg]]>8,AVANZA[[#This Row],[Dia_Reg]]<16)),"SEMANA 2","")&IF(AND(AVANZA[[#This Row],[Mes_Reg]]=MONTH(TODAY()),AND(AVANZA[[#This Row],[Dia_Reg]]>15,AVANZA[[#This Row],[Dia_Reg]]<23)),"SEMANA 3","")&IF(AND(AVANZA[[#This Row],[Mes_Reg]]=MONTH(TODAY()),AND(AVANZA[[#This Row],[Dia_Reg]]>22,AVANZA[[#This Row],[Dia_Reg]]<31)),"SEMANA 4","")&IF(AVANZA[[#This Row],[Mes_Reg]]<>MONTH(TODAY()),"BOLSA MES ANTERIOR","")) -> semana 1 | D24: =LOWER(IFERROR(VLOOKUP(AVANZA[[#This Row],[ID_Peticion]],CANCELADAS[#All],2,0),"")) | E24: =LOWER(IFERROR(VLOOKUP(AVANZA[[#This Row],[ID_Peticion]],CANCELADAS[#All],3,0),"")) | F24: =LOWER(IF(AVANZA[[#This Row],[CEDULA CLIENTE]]<>""," CC: " & COUNTIFS(AVANZA[CEDULA CLIENTE],AVANZA[[#This Row],[CEDULA CLIENTE]]),"")& IF(AVANZA[[#This Row],[Direccion]]<>""," DIR: " & COUNTIFS(AVANZA[Direccion],AVANZA[[#This Row],[Direccion]]),"")) -> dir: 1 | G24: =IFERROR(VLOOKUP(AVANZA[[#This Row],[Cedula_Vendedor_Atis]],PLANTA[[#All],[CEDULA]:[LINEA]],3,0),"No Cruza") -> Marisol Avella | H24: =IFERROR(VLOOKUP(AVANZA[[#This Row],[Cedula_Vendedor_Atis]],PLANTA[[#All],[CEDULA]:[LINEA]],4,0),"No Cruza") -> Fija | I24: =LOWER(IF(AVANZA[[#This Row],[ATRIBUIBLE]]="",AVANZA[[#This Row],[Variable]],AVANZA[[#This Row],[ATRIBUIBLE]])) -> terminada | J24: =IF(AVANZA[[#This Row],[Variable]]=AVANZA[[#Headers],[TERMINADA]],1,0) -> 1 | K24: =IF(AVANZA[[#This Row],[Variable]]=AVANZA[[#Headers],[ANULADA]],1,0) -> 0 | L24: =IF(AVANZA[[#This Row],[Variable]]=AVANZA[[#Headers],[PENDIENTE]],1,0) -> 0 | M24: =IF(AVANZA[[#This Row],[ESTADO AGENDA]]="AGENDADA",1,0) -> 0 | N24: =IF(AVANZA[[#This Row],[ESTADO AGENDA]]="PENDIENTE DE AGENDAR",1,0) -> 0 | O24: =IF(AVANZA[[#This Row],[ESTADO AGENDA]]="SUSPENDIDA",1,0) -> 0 | P24: {=_xlfn.XLOOKUP(AVANZA[[#This Row],[Num_Agrupacion_Pet_Atis]],Tabla1[[#All],[Numero_de_actuacion]],Tabla1[[#All],[Estado_de_la_orden]],"",0)} | Q24: {=_xlfn.XLOOKUP(AVANZA[[#This Row],[Num_Agrupacion_Pet_Atis]],Tabla1[[#All],[Numero_de_actuacion]],Tabla1[[#All],[Fecha_de_la_cita]],"",0)} | R24: {=_xlfn.XLOOKUP(AVANZA[[#This Row],[Num_Agrupacion_Pet_Atis]],Tabla1[[#All],[Numero_de_actuacion]],Tabla1[[#All],[Franja_horaria_de_la_cita]],"",0)} | S24: =IFERROR(DAY(AVANZA[[#This Row],[FECHA AGENDA]]),"") | T24: =IFERROR(MONTH(AVANZA[[#This Row],[FECHA AGENDA]]),"") | U24: {=_xlfn.XLOOKUP(AVANZA[[#This Row],[Num_Agrupacion_Pet_Atis]],Tabla1[[#All],[Numero_de_actuacion]],Tabla1[[#All],[Motivo_de_suspension]],"",0)} | V24: {=_xlfn.XLOOKUP(AVANZA[[#This Row],[Num_Agrupacion_Pet_Atis]],Tabla1[[#All],[Numero_de_actuacion]],Tabla1[[#All],[No_identificacion_cliente]],"",0)} | W24: {=_xlfn.XLOOKUP(AVANZA[[#This Row],[Num_Agrupacion_Pet_Atis]],Tabla1[[#All],[Numero_de_actuacion]],Tabla1[[#All],[Movil_de_contacto]],"",0)} | X24: =IF(OR(AVANZA[[#This Row],[ESTADO LEG]]="Legalizada grabacion",AVANZA[[#This Row],[ESTADO LEG]]="Legalizada aut"),1,0) -> 1 | Y24: =IF(OR(AVANZA[[#This Row],[ESTADO LEG]]="pdte legalizar",AVANZA[[#This Row],[ESTADO LEG]]="No cruza"),1,0) -> 0 | Z24: {=IF(AVANZA[[#This Row],[Variable]]="Terminada",LOWER(_xlfn.XLOOKUP(AVANZA[[#This Row],[ID_Peticion]],Tabla6[[#All],[NUM_PETICION]],Tabla6[[#All],[ESTADO_LEG]],"NO CRUZA",0)),AVANZA[[#This Row],[Variable]])} -> legalizada grabacion | AA24: {=_xlfn.XLOOKUP(AVANZA[[#This Row],[ID_Peticion]],Tabla6[[#All],[NUM_PETICION]],Tabla6[[#All],[DIF_DIAS]],"",0)} -> 4 | AB24: {=IFERROR(_xlfn.XLOOKUP(AVANZA[[#This Row],[ID_Peticion]],Tabla6[[#All],[NUM_PETICION]],Tabla6[[#All],[FEC_LEGAL]],"",0),"")} -> 46148 | AC24: =IF(AVANZA[[#This Row],[FECHA LEG]]<>0,IFERROR(AVANZA[[#This Row],[FECHA LEG]]-AVANZA[[#This Row],[FechaIniEstadoSubPetAtis]],0),TODAY()-AVANZA[[#This Row],[FechaIniEstadoSubPetAtis]]) -> 4 | AD24: =IF(AVANZA[[#This Row],[FINAL Vs LG]]<>0,IF(AVANZA[[#This Row],[FINAL Vs LG]]<7.1,"100%",IF(AND(AVANZA[[#This Row],[FINAL Vs LG]]>7.1,AVANZA[[#This Row],[FINAL Vs LG]]<11.1),"50%","0%")),0) -> 100% | AE24: =VLOOKUP(DAY(TODAY()),BACK!F:G,2,0) -> 14 | AF24: =BACK!$I$2 -> 24 | AG24: =IF(AVANZA[[#This Row],[Oferta_empaquetada_comisiones]]="SI",1,0) -> 0 | AH24: =IF(AVANZA[[#This Row],[Variable]]="TERMINADA",IFERROR(VLOOKUP(AVANZA[[#This Row],[SUPERVISOR]],Tabla2[#All],4,0),0),) -> 3.5 | AI24: =IF(AVANZA[[#This Row],[Producto]]="BA",1,0) -> 1 | AJ24: =IF(AVANZA[[#This Row],[Producto]]="DUO",1,0) -> 0 | AK24: =IF(AVANZA[[#This Row],[Producto]]="TRIO",1,0) -> 0 | AL24: 1526683800046962252 | AM24: -1 | AN24: -1 | AO24: 1786098589 | AP24: 46144.373 | AQ24: -1 | AR24: 2512691905 | AS24: -1 | AT24: -1 | AU24: -1 | AV24: -1 | AW24: -1 | AX24: FixedCreateSubscriber | AY24: -1 | AZ24: 2026 | BA24: 5 | BB24: 2 | BC24: -1 | BD24: Broadband Service | BE24: -1 | BF24: 20001621332006 | BG24: Plan Banda Ancha 900Mbps Solo Internet_Nac_25423 | BH24: 25423 | BI24: FS202605020856072126 | BJ24: -1 | BK24: -1 | BL24: -1 | BM24: TERMINADA | BN24: Individual | BO24: 6108774477 | BP24: Gold | BQ24: 2026 | BR24: 5 | BS24: 2 | BT24: 46144.742 | BU24: OS90 | BV24: 46144 | BW24: Completed | BX24: 46144 | BY24: 46144 | BZ24: Call Back To CRM | CA24: BOGOTA, D.C. | CB24: BOGOTA, D.C. | CC24: CL 133 KR 151 A-51 LISBOA-SUBA 51 LAT:4.74355066 LON:-74.122355 | CD24: LISBOA-SUBA | CE24: -1 | CF24: 11001000 | CG24: Bogota | CH24: ATACANTE | CI24: 73211780 | CJ24: WALTER BERRIO GONZALEZ | CK24: CANAL ONLINE | CL24: ON LINE | CM24: ATENTO COLOMBIA S.A. | CN24: CANAL ON LINE - ATENTO IN BOUND | CT24: 2 | CU24: Broadband Service | CW24: Plan Banda Ancha 900Mbps Solo Internet_Nac_25423 | CX24: 25423 | DA24: SV | DB24: -1 | DF24: ALTA | DJ24: 900000 | DK24: Cliente Nuevo | DL24: Cliente Existente | DN24: BA | DR24: wberriogo | DS24: WALTER BERRIO GONZALEZ | DT24: 73211780 | DV24: 1 | DW24: BOGOTA | ED24: 46144 | EE24: Norte | EF24: 9 | EP24: 830065842-5 | ES24: 153 | FA24: CANAL ONLINE | FB24: Bogotá D.C | FD24: Bogotá D.C | FE24: Bogotá | FF24: Bogotá | FK24: ATENTO | FL24: 11001000OH_BOGALVRIC_I_7360_23000_VillaMaria_3VIMAR-CT1/2-30-10SS2-30-10@11001000_OH_BOGALVRIC_I_7360_23000_VillaMaria_3_VIMAR-CT1/2-30-10_SS2-30-10 | FN24: CANAL ON LINE - ATENTO IN BOUND | FO24: 9900202020035 | FR24: 94990 | GB24: PON | GC24: Broadband Service | GD24: 0 | GF24: 0 | GG24: 25423 | GI24: 94990 | GJ24: 0 | GL24: 0 | GM24: 113038 | GS24: FS | GT24: 44620 | GU24: CENTRO EXP | GV24: SIN EMAIL | GW24: No | GZ24: No Convergente | HA24: ONNET | HB24: BOGOTA 1 | HC24: BOGOTA 1 | HD24: BOGOTA NORTE | HE24: Individual | HF24: 474074120 | HR24: Asistido | HV24: 94990 | HW24: NO | HY24: 0 | HZ24: 0 | IA24: NO | IB24: NO | IE24: BOGOTA | IF24: BOGOTA | IG24: BOGOTA | IH24: Digital | II24: Fibra | IJ24: B2C | IK24: Asistido | IL24: Inbound | IM24: Atento | IN24: Alta | IP24: - | IQ24: Digital | IS24: ELECTRONICA | IT24: Googleads_Oferta | IU24: CO_MARCA_COL-PUREBRAND-B2C_22-02-16_SEM_LDS-WEB_AON_RMKT_BRAND | IV24: SEM_SEM_CPL | IW24: Fija-Fibra-web-CajadeProducto-LP-pauta-fibra | IY24: NO
A25: =DAY(AVANZA[[#This Row],[FechaSeguimiento]]) -> 2 | B25: =MONTH(AVANZA[[#This Row],[FechaSeguimiento]]) -> 5 | C25: =LOWER(IF(AND(AVANZA[[#This Row],[Mes_Reg]]=MONTH(TODAY()),AND(AVANZA[[#This Row],[Dia_Reg]]>0,AVANZA[[#This Row],[Dia_Reg]]<9)),"SEMANA 1","")&IF(AND(AVANZA[[#This Row],[Mes_Reg]]=MONTH(TODAY()),AND(AVANZA[[#This Row],[Dia_Reg]]>8,AVANZA[[#This Row],[Dia_Reg]]<16)),"SEMANA 2","")&IF(AND(AVANZA[[#This Row],[Mes_Reg]]=MONTH(TODAY()),AND(AVANZA[[#This Row],[Dia_Reg]]>15,AVANZA[[#This Row],[Dia_Reg]]<23)),"SEMANA 3","")&IF(AND(AVANZA[[#This Row],[Mes_Reg]]=MONTH(TODAY()),AND(AVANZA[[#This Row],[Dia_Reg]]>22,AVANZA[[#This Row],[Dia_Reg]]<31)),"SEMANA 4","")&IF(AVANZA[[#This Row],[Mes_Reg]]<>MONTH(TODAY()),"BOLSA MES ANTERIOR","")) -> bolsa mes anterior | D25: =LOWER(IFERROR(VLOOKUP(AVANZA[[#This Row],[ID_Peticion]],CANCELADAS[#All],2,0),"")) | E25: =LOWER(IFERROR(VLOOKUP(AVANZA[[#This Row],[ID_Peticion]],CANCELADAS[#All],3,0),"")) | F25: =LOWER(IF(AVANZA[[#This Row],[CEDULA CLIENTE]]<>""," CC: " & COUNTIFS(AVANZA[CEDULA CLIENTE],AVANZA[[#This Row],[CEDULA CLIENTE]]),"")& IF(AVANZA[[#This Row],[Direccion]]<>""," DIR: " & COUNTIFS(AVANZA[Direccion],AVANZA[[#This Row],[Direccion]]),"")) -> dir: 1 | G25: =IFERROR(VLOOKUP(AVANZA[[#This Row],[Cedula_Vendedor_Atis]],PLANTA[[#All],[CEDULA]:[LINEA]],3,0),"No Cruza") -> Marisol Avella | H25: =IFERROR(VLOOKUP(AVANZA[[#This Row],[Cedula_Vendedor_Atis]],PLANTA[[#All],[CEDULA]:[LINEA]],4,0),"No Cruza") -> Fija | I25: =LOWER(IF(AVANZA[[#This Row],[ATRIBUIBLE]]="",AVANZA[[#This Row],[Variable]],AVANZA[[#This Row],[ATRIBUIBLE]])) -> terminada | J25: =IF(AVANZA[[#This Row],[Variable]]=AVANZA[[#Headers],[TERMINADA]],1,0) -> 1 | K25: =IF(AVANZA[[#This Row],[Variable]]=AVANZA[[#Headers],[ANULADA]],1,0) -> 0 | L25: =IF(AVANZA[[#This Row],[Variable]]=AVANZA[[#Headers],[PENDIENTE]],1,0) -> 0 | M25: =IF(AVANZA[[#This Row],[ESTADO AGENDA]]="AGENDADA",1,0) -> 0 | N25: =IF(AVANZA[[#This Row],[ESTADO AGENDA]]="PENDIENTE DE AGENDAR",1,0) -> 0 | O25: =IF(AVANZA[[#This Row],[ESTADO AGENDA]]="SUSPENDIDA",1,0) -> 0 | P25: {=_xlfn.XLOOKUP(AVANZA[[#This Row],[Num_Agrupacion_Pet_Atis]],Tabla1[[#All],[Numero_de_actuacion]],Tabla1[[#All],[Estado_de_la_orden]],"",0)} | Q25: {=_xlfn.XLOOKUP(AVANZA[[#This Row],[Num_Agrupacion_Pet_Atis]],Tabla1[[#All],[Numero_de_actuacion]],Tabla1[[#All],[Fecha_de_la_cita]],"",0)} | R25: {=_xlfn.XLOOKUP(AVANZA[[#This Row],[Num_Agrupacion_Pet_Atis]],Tabla1[[#All],[Numero_de_actuacion]],Tabla1[[#All],[Franja_horaria_de_la_cita]],"",0)} | S25: =IFERROR(DAY(AVANZA[[#This Row],[FECHA AGENDA]]),"") | T25: =IFERROR(MONTH(AVANZA[[#This Row],[FECHA AGENDA]]),"") | U25: {=_xlfn.XLOOKUP(AVANZA[[#This Row],[Num_Agrupacion_Pet_Atis]],Tabla1[[#All],[Numero_de_actuacion]],Tabla1[[#All],[Motivo_de_suspension]],"",0)} | V25: {=_xlfn.XLOOKUP(AVANZA[[#This Row],[Num_Agrupacion_Pet_Atis]],Tabla1[[#All],[Numero_de_actuacion]],Tabla1[[#All],[No_identificacion_cliente]],"",0)} | W25: {=_xlfn.XLOOKUP(AVANZA[[#This Row],[Num_Agrupacion_Pet_Atis]],Tabla1[[#All],[Numero_de_actuacion]],Tabla1[[#All],[Movil_de_contacto]],"",0)} | X25: =IF(OR(AVANZA[[#This Row],[ESTADO LEG]]="Legalizada grabacion",AVANZA[[#This Row],[ESTADO LEG]]="Legalizada aut"),1,0) -> 1 | Y25: =IF(OR(AVANZA[[#This Row],[ESTADO LEG]]="pdte legalizar",AVANZA[[#This Row],[ESTADO LEG]]="No cruza"),1,0) -> 0 | Z25: {=IF(AVANZA[[#This Row],[Variable]]="Terminada",LOWER(_xlfn.XLOOKUP(AVANZA[[#This Row],[ID_Peticion]],Tabla6[[#All],[NUM_PETICION]],Tabla6[[#All],[ESTADO_LEG]],"NO CRUZA",0)),AVANZA[[#This Row],[Variable]])} -> legalizada grabacion | AA25: {=_xlfn.XLOOKUP(AVANZA[[#This Row],[ID_Peticion]],Tabla6[[#All],[NUM_PETICION]],Tabla6[[#All],[DIF_DIAS]],"",0)} -> 4 | AB25: {=IFERROR(_xlfn.XLOOKUP(AVANZA[[#This Row],[ID_Peticion]],Tabla6[[#All],[NUM_PETICION]],Tabla6[[#All],[FEC_LEGAL]],"",0),"")} -> 46148 | AC25: =IF(AVANZA[[#This Row],[FECHA LEG]]<>0,IFERROR(AVANZA[[#This Row],[FECHA LEG]]-AVANZA[[#This Row],[FechaIniEstadoSubPetAtis]],0),TODAY()-AVANZA[[#This Row],[FechaIniEstadoSubPetAtis]]) -> 4 | AD25: =IF(AVANZA[[#This Row],[FINAL Vs LG]]<>0,IF(AVANZA[[#This Row],[FINAL Vs LG]]<7.1,"100%",IF(AND(AVANZA[[#This Row],[FINAL Vs LG]]>7.1,AVANZA[[#This Row],[FINAL Vs LG]]<11.1),"50%","0%")),0) -> 100% | AE25: =VLOOKUP(DAY(TODAY()),BACK!F:G,2,0) -> 14 | AF25: =BACK!$I$2 -> 24 | AG25: =IF(AVANZA[[#This Row],[Oferta_empaquetada_comisiones]]="SI",1,0) -> 0 | AH25: =IF(AVANZA[[#This Row],[Variable]]="TERMINADA",IFERROR(VLOOKUP(AVANZA[[#This Row],[SUPERVISOR]],Tabla2[#All],4,0),0),) -> 3.5 | AI25: =IF(AVANZA[[#This Row],[Producto]]="BA",1,0) -> 1 | AJ25: =IF(AVANZA[[#This Row],[Producto]]="DUO",1,0) -> 0 | AK25: =IF(AVANZA[[#This Row],[Producto]]="TRIO",1,0) -> 0 | AL25: 1540848641938144519 | AM25: -1 | AN25: -1 | AO25: 1784414408 | AP25: 46140.799 | AQ25: -1 | AR25: 2512685110 | AS25: -1 | AT25: -1 | AU25: -1 | AV25: -1 | AW25: -1 | AX25: FixedCreateSubscriber | AY25: -1 | AZ25: 2026 | BA25: 5 | BB25: 2 | BC25: -1 | BD25: Broadband Service | BE25: -1 | BF25: 20001619632332 | BG25: Plan Banda Ancha 900Mbps Solo Internet_Netflix_Nac_25341 | BH25: 25341 | BI25: FS202604281910261088 | BJ25: -1 | BK25: -1 | BL25: -1 | BM25: TERMINADA | BN25: Individual | BO25: 6108732611 | BP25: Gold | BQ25: 2026 | BR25: 4 | BS25: 28 | BT25: 46144.403 | BU25: OS90 | BV25: 46144 | BW25: Completed | BX25: 46140 | BY25: 46144 | BZ25: Call Back To CRM | CA25: BOGOTA, D.C. | CB25: BOGOTA, D.C. | CC25: CL 6 A KR 93 D-17 OSORIO II 17 INT 2 APT 601 LAT:4.65473 LON:-74.16505706 | CD25: OSORIO II | CE25: -1 | CF25: 11001000 | CG25: Bogota | CH25: ATACANTE | CI25: 1193125457 | CJ25: ANDRES LEONARDO BARRERA ARGUMEDO | CK25: CANAL ONLINE | CL25: ON LINE | CM25: ATENTO COLOMBIA S.A. | CN25: CANAL ON LINE - ATENTO CLICK TO CALL | CT25: 3 | CU25: Broadband Service | CW25: Plan Banda Ancha 900Mbps Solo Internet_Netflix_Nac_25341 | CX25: 25341 | DA25: SV | DB25: -1 | DF25: ALTA | DJ25: 900000 | DK25: Cliente Nuevo | DL25: Cliente Existente | DN25: BA | DR25: albarreraar | DS25: ANDRES LEONARDO BARRERA ARGUMEDO | DT25: 1193125457 | DV25: 1 | DW25: BOGOTA | ED25: 46144 | EE25: Occidente | EF25: 5 | EP25: 830065842-5 | ES25: 149 | FA25: CANAL ONLINE | FB25: Bogotá D.C | FD25: Bogotá D.C | FE25: Bogotá | FF25: Bogotá | FK25: ATENTO | FL25: 11001000OH_BOGALGDOE_I_7360_CentrodeGravedad2_5CGDOS-PC4-111-04SS4-111-04@11001000_OH_BOGALGDOE_I_7360_CentrodeGravedad2_5_CGDOS-PC4-111-04_SS4-111-04 | FN25: CANAL ON LINE - ATENTO CLICK TO CALL | FO25: 9900202020033 | FR25: 109972 | GB25: PON | GC25: Broadband Service | GD25: 0 | GF25: 0 | GG25: 25341 | GI25: 109972 | GJ25: 0 | GL25: 0 | GM25: 130866 | GS25: FS | GT25: 45442 | GU25: CENTRO EXP | GV25: VALIDADO | GW25: No | GZ25: No Convergente | HA25: ONNET | HB25: BOGOTA 2 | HC25: BOGOTA 2 | HD25: BOGOTA OCCIDENTE | HE25: Individual | HF25: 465074165 | HR25: Asistido | HV25: 112990 | HW25: NO | HY25: 0 | HZ25: 0 | IA25: SI | IB25: NO | IE25: BOGOTA | IF25: BOGOTA | IG25: BOGOTA | IH25: Digital | II25: Fibra | IJ25: B2C | IK25: Asistido | IL25: C2C | IM25: Atento | IN25: Alta | IP25: - | IQ25: Digital | IS25: FISICA | IT25: WhatsApp Bot | IY25: NO
A26: =DAY(AVANZA[[#This Row],[FechaSeguimiento]]) -> 2 | B26: =MONTH(AVANZA[[#This Row],[FechaSeguimiento]]) -> 5 | C26: =LOWER(IF(AND(AVANZA[[#This Row],[Mes_Reg]]=MONTH(TODAY()),AND(AVANZA[[#This Row],[Dia_Reg]]>0,AVANZA[[#This Row],[Dia_Reg]]<9)),"SEMANA 1","")&IF(AND(AVANZA[[#This Row],[Mes_Reg]]=MONTH(TODAY()),AND(AVANZA[[#This Row],[Dia_Reg]]>8,AVANZA[[#This Row],[Dia_Reg]]<16)),"SEMANA 2","")&IF(AND(AVANZA[[#This Row],[Mes_Reg]]=MONTH(TODAY()),AND(AVANZA[[#This Row],[Dia_Reg]]>15,AVANZA[[#This Row],[Dia_Reg]]<23)),"SEMANA 3","")&IF(AND(AVANZA[[#This Row],[Mes_Reg]]=MONTH(TODAY()),AND(AVANZA[[#This Row],[Dia_Reg]]>22,AVANZA[[#This Row],[Dia_Reg]]<31)),"SEMANA 4","")&IF(AVANZA[[#This Row],[Mes_Reg]]<>MONTH(TODAY()),"BOLSA MES ANTERIOR","")) -> bolsa mes anterior | D26: =LOWER(IFERROR(VLOOKUP(AVANZA[[#This Row],[ID_Peticion]],CANCELADAS[#All],2,0),"")) -> qc - cliente desea el producto pero en una fecha posterior | E26: =LOWER(IFERROR(VLOOKUP(AVANZA[[#This Row],[ID_Peticion]],CANCELADAS[#All],3,0),"")) -> asesor | F26: =LOWER(IF(AVANZA[[#This Row],[CEDULA CLIENTE]]<>""," CC: " & COUNTIFS(AVANZA[CEDULA CLIENTE],AVANZA[[#This Row],[CEDULA CLIENTE]]),"")& IF(AVANZA[[#This Row],[Direccion]]<>""," DIR: " & COUNTIFS(AVANZA[Direccion],AVANZA[[#This Row],[Direccion]]),"")) -> dir: 1 | G26: =IFERROR(VLOOKUP(AVANZA[[#This Row],[Cedula_Vendedor_Atis]],PLANTA[[#All],[CEDULA]:[LINEA]],3,0),"No Cruza") -> Marisol Avella | H26: =IFERROR(VLOOKUP(AVANZA[[#This Row],[Cedula_Vendedor_Atis]],PLANTA[[#All],[CEDULA]:[LINEA]],4,0),"No Cruza") -> Fija | I26: =LOWER(IF(AVANZA[[#This Row],[ATRIBUIBLE]]="",AVANZA[[#This Row],[Variable]],AVANZA[[#This Row],[ATRIBUIBLE]])) -> asesor | J26: =IF(AVANZA[[#This Row],[Variable]]=AVANZA[[#Headers],[TERMINADA]],1,0) -> 0 | K26: =IF(AVANZA[[#This Row],[Variable]]=AVANZA[[#Headers],[ANULADA]],1,0) -> 1 | L26: =IF(AVANZA[[#This Row],[Variable]]=AVANZA[[#Headers],[PENDIENTE]],1,0) -> 0 | M26: =IF(AVANZA[[#This Row],[ESTADO AGENDA]]="AGENDADA",1,0) -> 0 | N26: =IF(AVANZA[[#This Row],[ESTADO AGENDA]]="PENDIENTE DE AGENDAR",1,0) -> 0 | O26: =IF(AVANZA[[#This Row],[ESTADO AGENDA]]="SUSPENDIDA",1,0) -> 0 | P26: {=_xlfn.XLOOKUP(AVANZA[[#This Row],[Num_Agrupacion_Pet_Atis]],Tabla1[[#All],[Numero_de_actuacion]],Tabla1[[#All],[Estado_de_la_orden]],"",0)} | Q26: {=_xlfn.XLOOKUP(AVANZA[[#This Row],[Num_Agrupacion_Pet_Atis]],Tabla1[[#All],[Numero_de_actuacion]],Tabla1[[#All],[Fecha_de_la_cita]],"",0)} | R26: {=_xlfn.XLOOKUP(AVANZA[[#This Row],[Num_Agrupacion_Pet_Atis]],Tabla1[[#All],[Numero_de_actuacion]],Tabla1[[#All],[Franja_horaria_de_la_cita]],"",0)} | S26: =IFERROR(DAY(AVANZA[[#This Row],[FECHA AGENDA]]),"") | T26: =IFERROR(MONTH(AVANZA[[#This Row],[FECHA AGENDA]]),"") | U26: {=_xlfn.XLOOKUP(AVANZA[[#This Row],[Num_Agrupacion_Pet_Atis]],Tabla1[[#All],[Numero_de_actuacion]],Tabla1[[#All],[Motivo_de_suspension]],"",0)} | V26: {=_xlfn.XLOOKUP(AVANZA[[#This Row],[Num_Agrupacion_Pet_Atis]],Tabla1[[#All],[Numero_de_actuacion]],Tabla1[[#All],[No_identificacion_cliente]],"",0)} | W26: {=_xlfn.XLOOKUP(AVANZA[[#This Row],[Num_Agrupacion_Pet_Atis]],Tabla1[[#All],[Numero_de_actuacion]],Tabla1[[#All],[Movil_de_contacto]],"",0)} | X26: =IF(OR(AVANZA[[#This Row],[ESTADO LEG]]="Legalizada grabacion",AVANZA[[#This Row],[ESTADO LEG]]="Legalizada aut"),1,0) -> 0 | Y26: =IF(OR(AVANZA[[#This Row],[ESTADO LEG]]="pdte legalizar",AVANZA[[#This Row],[ESTADO LEG]]="No cruza"),1,0) -> 0 | Z26: {=IF(AVANZA[[#This Row],[Variable]]="Terminada",LOWER(_xlfn.XLOOKUP(AVANZA[[#This Row],[ID_Peticion]],Tabla6[[#All],[NUM_PETICION]],Tabla6[[#All],[ESTADO_LEG]],"NO CRUZA",0)),AVANZA[[#This Row],[Variable]])} -> ANULADA | AA26: {=_xlfn.XLOOKUP(AVANZA[[#This Row],[ID_Peticion]],Tabla6[[#All],[NUM_PETICION]],Tabla6[[#All],[DIF_DIAS]],"",0)} | AB26: {=IFERROR(_xlfn.XLOOKUP(AVANZA[[#This Row],[ID_Peticion]],Tabla6[[#All],[NUM_PETICION]],Tabla6[[#All],[FEC_LEGAL]],"",0),"")} | AC26: =IF(AVANZA[[#This Row],[FECHA LEG]]<>0,IFERROR(AVANZA[[#This Row],[FECHA LEG]]-AVANZA[[#This Row],[FechaIniEstadoSubPetAtis]],0),TODAY()-AVANZA[[#This Row],[FechaIniEstadoSubPetAtis]]) -> 0 | AD26: =IF(AVANZA[[#This Row],[FINAL Vs LG]]<>0,IF(AVANZA[[#This Row],[FINAL Vs LG]]<7.1,"100%",IF(AND(AVANZA[[#This Row],[FINAL Vs LG]]>7.1,AVANZA[[#This Row],[FINAL Vs LG]]<11.1),"50%","0%")),0) -> 0 | AE26: =VLOOKUP(DAY(TODAY()),BACK!F:G,2,0) -> 14 | AF26: =BACK!$I$2 -> 24 | AG26: =IF(AVANZA[[#This Row],[Oferta_empaquetada_comisiones]]="SI",1,0) -> 0 | AH26: =IF(AVANZA[[#This Row],[Variable]]="TERMINADA",IFERROR(VLOOKUP(AVANZA[[#This Row],[SUPERVISOR]],Tabla2[#All],4,0),0),) -> 0 | AI26: =IF(AVANZA[[#This Row],[Producto]]="BA",1,0) -> 1 | AJ26: =IF(AVANZA[[#This Row],[Producto]]="DUO",1,0) -> 0 | AK26: =IF(AVANZA[[#This Row],[Producto]]="TRIO",1,0) -> 0 | AL26: 1651508247288716261 | AM26: -1 | AN26: -1 | AO26: 1771228385 | AP26: 46120.532 | AQ26: -1 | AR26: 2512633664 | AS26: -1 | AT26: -1 | AU26: -1 | AV26: -1 | AW26: -1 | AX26: FixedCreateSubscriber | AY26: -1 | AZ26: 2026 | BA26: 5 | BB26: 2 | BC26: -1 | BD26: Broadband Service | BE26: -1 | BF26: 20001607780541 | BG26: Convergente_MTotal_Single_Voz Ilim Nal _Ba Ancha 900Mbps_Mov Ilim_Nac_25421 | BH26: 25421 | BI26: FS202604081246113326 | BJ26: -1 | BK26: -1 | BL26: -1 | BM26: ANULADA | BN26: Individual | BO26: 6086627947 | BP26: Gold | BQ26: 2026 | BR26: 4 | BS26: 8 | BT26: 46144.662 | BU26: OS80 | BV26: 46144 | BW26: Cancelled | BX26: 46120 | BY26: 46144 | BZ26: Call Back To CRM | CA26: BOGOTA, D.C. | CB26: BOGOTA, D.C. | CC26: KR 4 A CL 55-26 BOSQUE CALDERON 26 APT 402 LAT:4.6411042 LON:-74.06066561 | CD26: BOSQUE CALDERON | CE26: -1 | CF26: 11001000 | CG26: Bogota | CH26: ATACANTE | CI26: 1000857923 | CJ26: SERGIO ANDREY RICO DIAZ | CK26: CANAL ONLINE | CL26: ON LINE | CM26: ATENTO COLOMBIA S.A. | CN26: CANAL ON LINE - ATENTO CLICK TO CALL | CT26: 4 | CU26: Broadband Service | CW26: Convergente_MTotal_Single_Voz Ilim Nal _Ba Ancha 900Mbps_Mov Ilim_Nac_25421 | CX26: 25421 | CY26: CLIENTE DESEA EL PRODUCTO PERO EN UNA FECHA POSTERIOR | DA26: SV | DB26: -1 | DF26: ANULADA COMERCIAL | DJ26: 900000 | DK26: Cliente Nuevo | DL26: Cliente Nuevo | DN26: BA | DR26: saricodi | DS26: SERGIO ANDREY RICO DIAZ | DT26: 1000857923 | DV26: 1 | DW26: BOGOTA | ED26: 46144 | EF26: 1 | EP26: 830065842-5 | FA26: CANAL ONLINE | FB26: Bogotá D.C | FD26: Bogotá D.C | FE26: Bogotá | FF26: Bogotá | FK26: ATENTO | FN26: CANAL ON LINE - ATENTO CLICK TO CALL | FO26: 9900202020033 | FR26: 0 | GB26: PON | GM26: 0 | GS26: FS | GU26: CENTRO EXP | GV26: SIN EMAIL | GW26: Si | GX26: Solo Movil | GY26: Solo Movil | GZ26: Convergente Nuevo | HE26: Individual | HF26: 464074060 | HR26: Asistido | HV26: 85900 | HW26: SI | HY26: 0 | HZ26: 0 | IA26: SI | IB26: NO | IC26: QC - CLIENTE DESEA EL PRODUCTO PERO EN UNA FECHA POSTERIOR Se marca a los numeros: 3175164761 6013103455 Titular JUAN CARLOS DURAN CRANE no se logra contacto, se registra intento de contacto 02/05/2026 03:46 p._x001A_m. Ya se realizaron los 6 intentos de c | IE26: BOGOTA | IF26: BOGOTA | IG26: BOGOTA | IH26: Digital | II26: Fibra | IJ26: B2C | IK26: Asistido | IL26: C2C | IM26: Atento | IN26: - | IP26: Producto Para Fecha Posterior | IQ26: Digital | IS26: ELECTRONICA | IT26: Googleads_Oferta | IU26: CO_HOGAR_COL-FIBRA-ASISTIDA-BOGOTA-B2C_22-06-13_SEM_LDS-WEB_AON_ABT_BRAND | IV26: SEM_SEM_CPL | IW26: Fija-Fibra-web-CajadeProducto-LP-pauta-fibra | IY26: NO
A27: =DAY(AVANZA[[#This Row],[FechaSeguimiento]]) -> 2 | B27: =MONTH(AVANZA[[#This Row],[FechaSeguimiento]]) -> 5 | C27: =LOWER(IF(AND(AVANZA[[#This Row],[Mes_Reg]]=MONTH(TODAY()),AND(AVANZA[[#This Row],[Dia_Reg]]>0,AVANZA[[#This Row],[Dia_Reg]]<9)),"SEMANA 1","")&IF(AND(AVANZA[[#This Row],[Mes_Reg]]=MONTH(TODAY()),AND(AVANZA[[#This Row],[Dia_Reg]]>8,AVANZA[[#This Row],[Dia_Reg]]<16)),"SEMANA 2","")&IF(AND(AVANZA[[#This Row],[Mes_Reg]]=MONTH(TODAY()),AND(AVANZA[[#This Row],[Dia_Reg]]>15,AVANZA[[#This Row],[Dia_Reg]]<23)),"SEMANA 3","")&IF(AND(AVANZA[[#This Row],[Mes_Reg]]=MONTH(TODAY()),AND(AVANZA[[#This Row],[Dia_Reg]]>22,AVANZA[[#This Row],[Dia_Reg]]<31)),"SEMANA 4","")&IF(AVANZA[[#This Row],[Mes_Reg]]<>MONTH(TODAY()),"BOLSA MES ANTERIOR","")) -> semana 1 | D27: =LOWER(IFERROR(VLOOKUP(AVANZA[[#This Row],[ID_Peticion]],CANCELADAS[#All],2,0),"")) | E27: =LOWER(IFERROR(VLOOKUP(AVANZA[[#This Row],[ID_Peticion]],CANCELADAS[#All],3,0),"")) | F27: =LOWER(IF(AVANZA[[#This Row],[CEDULA CLIENTE]]<>""," CC: " & COUNTIFS(AVANZA[CEDULA CLIENTE],AVANZA[[#This Row],[CEDULA CLIENTE]]),"")& IF(AVANZA[[#This Row],[Direccion]]<>""," DIR: " & COUNTIFS(AVANZA[Direccion],AVANZA[[#This Row],[Direccion]]),"")) -> dir: 1 | G27: =IFERROR(VLOOKUP(AVANZA[[#This Row],[Cedula_Vendedor_Atis]],PLANTA[[#All],[CEDULA]:[LINEA]],3,0),"No Cruza") -> Marisol Avella | H27: =IFERROR(VLOOKUP(AVANZA[[#This Row],[Cedula_Vendedor_Atis]],PLANTA[[#All],[CEDULA]:[LINEA]],4,0),"No Cruza") -> Fija | I27: =LOWER(IF(AVANZA[[#This Row],[ATRIBUIBLE]]="",AVANZA[[#This Row],[Variable]],AVANZA[[#This Row],[ATRIBUIBLE]])) -> terminada | J27: =IF(AVANZA[[#This Row],[Variable]]=AVANZA[[#Headers],[TERMINADA]],1,0) -> 1 | K27: =IF(AVANZA[[#This Row],[Variable]]=AVANZA[[#Headers],[ANULADA]],1,0) -> 0 | L27: =IF(AVANZA[[#This Row],[Variable]]=AVANZA[[#Headers],[PENDIENTE]],1,0) -> 0 | M27: =IF(AVANZA[[#This Row],[ESTADO AGENDA]]="AGENDADA",1,0) -> 0 | N27: =IF(AVANZA[[#This Row],[ESTADO AGENDA]]="PENDIENTE DE AGENDAR",1,0) -> 0 | O27: =IF(AVANZA[[#This Row],[ESTADO AGENDA]]="SUSPENDIDA",1,0) -> 0 | P27: {=_xlfn.XLOOKUP(AVANZA[[#This Row],[Num_Agrupacion_Pet_Atis]],Tabla1[[#All],[Numero_de_actuacion]],Tabla1[[#All],[Estado_de_la_orden]],"",0)} | Q27: {=_xlfn.XLOOKUP(AVANZA[[#This Row],[Num_Agrupacion_Pet_Atis]],Tabla1[[#All],[Numero_de_actuacion]],Tabla1[[#All],[Fecha_de_la_cita]],"",0)} | R27: {=_xlfn.XLOOKUP(AVANZA[[#This Row],[Num_Agrupacion_Pet_Atis]],Tabla1[[#All],[Numero_de_actuacion]],Tabla1[[#All],[Franja_horaria_de_la_cita]],"",0)} | S27: =IFERROR(DAY(AVANZA[[#This Row],[FECHA AGENDA]]),"") | T27: =IFERROR(MONTH(AVANZA[[#This Row],[FECHA AGENDA]]),"") | U27: {=_xlfn.XLOOKUP(AVANZA[[#This Row],[Num_Agrupacion_Pet_Atis]],Tabla1[[#All],[Numero_de_actuacion]],Tabla1[[#All],[Motivo_de_suspension]],"",0)} | V27: {=_xlfn.XLOOKUP(AVANZA[[#This Row],[Num_Agrupacion_Pet_Atis]],Tabla1[[#All],[Numero_de_actuacion]],Tabla1[[#All],[No_identificacion_cliente]],"",0)} | W27: {=_xlfn.XLOOKUP(AVANZA[[#This Row],[Num_Agrupacion_Pet_Atis]],Tabla1[[#All],[Numero_de_actuacion]],Tabla1[[#All],[Movil_de_contacto]],"",0)} | X27: =IF(OR(AVANZA[[#This Row],[ESTADO LEG]]="Legalizada grabacion",AVANZA[[#This Row],[ESTADO LEG]]="Legalizada aut"),1,0) -> 1 | Y27: =IF(OR(AVANZA[[#This Row],[ESTADO LEG]]="pdte legalizar",AVANZA[[#This Row],[ESTADO LEG]]="No cruza"),1,0) -> 0 | Z27: {=IF(AVANZA[[#This Row],[Variable]]="Terminada",LOWER(_xlfn.XLOOKUP(AVANZA[[#This Row],[ID_Peticion]],Tabla6[[#All],[NUM_PETICION]],Tabla6[[#All],[ESTADO_LEG]],"NO CRUZA",0)),AVANZA[[#This Row],[Variable]])} -> legalizada grabacion | AA27: {=_xlfn.XLOOKUP(AVANZA[[#This Row],[ID_Peticion]],Tabla6[[#All],[NUM_PETICION]],Tabla6[[#All],[DIF_DIAS]],"",0)} -> 4 | AB27: {=IFERROR(_xlfn.XLOOKUP(AVANZA[[#This Row],[ID_Peticion]],Tabla6[[#All],[NUM_PETICION]],Tabla6[[#All],[FEC_LEGAL]],"",0),"")} -> 46148 | AC27: =IF(AVANZA[[#This Row],[FECHA LEG]]<>0,IFERROR(AVANZA[[#This Row],[FECHA LEG]]-AVANZA[[#This Row],[FechaIniEstadoSubPetAtis]],0),TODAY()-AVANZA[[#This Row],[FechaIniEstadoSubPetAtis]]) -> 4 | AD27: =IF(AVANZA[[#This Row],[FINAL Vs LG]]<>0,IF(AVANZA[[#This Row],[FINAL Vs LG]]<7.1,"100%",IF(AND(AVANZA[[#This Row],[FINAL Vs LG]]>7.1,AVANZA[[#This Row],[FINAL Vs LG]]<11.1),"50%","0%")),0) -> 100% | AE27: =VLOOKUP(DAY(TODAY()),BACK!F:G,2,0) -> 14 | AF27: =BACK!$I$2 -> 24 | AG27: =IF(AVANZA[[#This Row],[Oferta_empaquetada_comisiones]]="SI",1,0) -> 0 | AH27: =IF(AVANZA[[#This Row],[Variable]]="TERMINADA",IFERROR(VLOOKUP(AVANZA[[#This Row],[SUPERVISOR]],Tabla2[#All],4,0),0),) -> 3.5 | AI27: =IF(AVANZA[[#This Row],[Producto]]="BA",1,0) -> 0 | AJ27: =IF(AVANZA[[#This Row],[Producto]]="DUO",1,0) -> 0 | AK27: =IF(AVANZA[[#This Row],[Producto]]="TRIO",1,0) -> 1 | AL27: 53061857 | AM27: -1 | AN27: -1 | AO27: 1786050947 | AP27: 46143.562 | AQ27: -1 | AR27: 2512690935 | AS27: -1 | AT27: -1 | AU27: -1 | AV27: -1 | AW27: -1 | AX27: FixedCreateSubscriber | AY27: -1 | AZ27: 2026 | BA27: 5 | BB27: 2 | BC27: -1 | BD27: Broadband Service | BE27: -1 | BF27: 20001621091238 | BG27: Convergente_Plan Ancha 900Mbps_Mov Ilim_Trio_25422 | BH27: 25422 | BI27: FS202605011329031823 | BJ27: -1 | BK27: -1 | BL27: -1 | BM27: TERMINADA | BN27: Individual | BO27: 6090091157 | BP27: Movistar Total | BQ27: 2026 | BR27: 5 | BS27: 1 | BT27: 46144.744 | BU27: OS90 | BV27: 46144 | BW27: Completed | BX27: 46143 | BY27: 46144 | BZ27: Call Back To CRM | CA27: FACATATIVA | CB27: CUNDINAMARCA | CC27: KR 18 CL 5-31 NUEVA HOLANDA 31 APT 1 LAT:4.82171647 LON:-74.34828014 | CD27: NUEVA HOLANDA | CE27: -1 | CF27: 25269000 | CG27: Bogota | CH27: INCUMBENTE COMPETITIVO | CI27: 53061857 | CJ27: NOHORA AMADO LONDONO | CK27: CANAL ONLINE | CL27: ON LINE | CM27: ATENTO COLOMBIA S.A. | CN27: CANAL ON LINE - ATENTO CLICK TO CALL | CT27: 2 | CU27: BA + LB + IPTV | CW27: MTotal_Trio_Voz Ilim Nal _Ba Ancha 900Mbps_IPTV_2_Decos_Mov Ilim_Nac_25425 | CX27: 25425 | DA27: SV | DB27: -1 | DF27: ALTA | DJ27: 900000 | DK27: Cliente Nuevo | DL27: Cliente Nuevo | DN27: TRIO | DR27: namadolo | DS27: NOHORA AMADO LONDONO | DT27: 53061857 | DV27: 1 | DW27: BOGOTA | ED27: 46144 | EE27: Occidente | EF27: 26 | EP27: 830065842-5 | ES27: FACA5 | FA27: CANAL ONLINE | FB27: Cundinamarca | FD27: Cundinamarca | FE27: Facatativá | FF27: Facatativá | FK27: ATENTO | FL27: 25269000OH_CUNALVTRC_I_7360_Facatativa_centro_3FACAT-CT5/6-17-07SS5-17-07@25269000_OH_CUNALVTRC_I_7360_Facatativa_centro_3_FACAT-CT5/6-17-07_SS5-17-07 | FN27: CANAL ON LINE - ATENTO CLICK TO CALL | FO27: 9900202020033 | FR27: 113904 | GB27: PON | GC27: BA + LB + IPTV | GD27: 25188 | GF27: 2353 | GG27: 25422 | GI27: 87224 | GJ27: 25427 | GL27: 24327 | GM27: 135545 | GS27: FS | GT27: 44865 | GU27: CENTRO EXP | GV27: SIN EMAIL | GW27: Si | GX27: Convergente Solo Contrato | GY27: Convergente Solo Contrato | GZ27: Convergente Existente | HA27: ONNET | HB27: AREA METROPOLITANA 3 | HC27: FACATATIVA | HD27: BOGOTA OCCIDENTE | HE27: Individual | HF27: 482074345 | HG27: Venta Hogar (F) a cliente Movistar Total | HR27: Asistido | HV27: 118900 | HW27: SI | HX27: Migracion Pos-Pos | HY27: 131572 | HZ27: 17668 | IA27: SI | IB27: NO | ID27: >= 120 | IE27: BOGOTA | IF27: BOGOTA | IG27: BOGOTA | IH27: Digital | II27: Fibra | IJ27: B2C | IK27: Asistido | IL27: C2C | IM27: Atento | IN27: Alta | IP27: - | IQ27: Digital | IS27: ELECTRONICA | IY27: NO
